Workbook

Sheet Mercury
A2: Date (UTC) | B2: Description | C2: Amount | D2: Status | E2: Source Account | F2: Bank Description | G2: Reference | H2: Note | I2: Last Four Digits | J2: Name On Card | K2: Mercury Category | L2: Category | M2: Source of Category | N2: GL Code | O2: Source of GL Code | P2: Timestamp | Q2: Original Currency | R2: Check Number | S2: Tags | T2: Cardholder Email | U2: Tracking ID | V2: Failure Reason | W2: Failure Reason | X2: Year (real) | Y2: Year (allocated) | Z2: Month (real) | AA2: Month (allocated) | AB2: Quarter | AC2: Statement | AD2: Type 1 | AE2: Type 2 | AF2: Type 2_B | AG2: Type 3 | AH2: Type 4 for checking flows (no edits) | AI2: Type 4 (edited)
A3: 31/08/26 | B3: Mercury IO Cashback | C3: 131.38 | D3: Sent | E3: Welcome to Column N.A. (Mercury Checking xx5998) | P3: ############ | X3: 2026 | Y3: 2026 | Z3: 8 | AA3: 8 | AB3: 3 | AC3: =VLOOKUP($B3,Dictionary_v2!$B:$E,2,0) -> P&L | AD3: Recurring | AE3: =VLOOKUP($B3,Dictionary_v2!$B:$E,3,0) -> 2. Candidates Sourcing | AF3: =VLOOKUP(AE3,Dictionary_v2!R:S,2,0) -> 2. Candidates Sourcing | AG3: =VLOOKUP($B3,Dictionary_v2!$B:$E,4,0) -> 1. Social Media | AH3: =if(C3>0,"In","Out") -> In | AI3: =if(C3>0,"In","Out") -> In
A4: 31/08/26 | B4: Welcome to Column N.A. (Mercury Checking xx5998) | C4: 8777.25 | D4: Sent | E4: Mercury Credit | F4: IO AUTOPAY | P4: ############ | X4: 2026 | Y4: 2026 | Z4: 8 | AA4: 8 | AB4: 3 | AC4: =VLOOKUP($B4,Dictionary_v2!$B:$E,2,0) -> Intercompany | AD4: Recurring | AE4: =VLOOKUP($B4,Dictionary_v2!$B:$E,3,0) | AG4: =VLOOKUP($B4,Dictionary_v2!$B:$E,4,0) | AH4: =if(C4>0,"In","Out") -> In | AI4: =if(C4>0,"In","Out") -> In
A5: 31/08/26 | B5: Mercury Credit | C5: -8777.25 | D5: Sent | E5: Welcome to Column N.A. (Mercury Checking xx5998) | F5: IO AUTOPAY | P5: ############ | X5: 2026 | Y5: 2026 | Z5: 8 | AA5: 8 | AB5: 3 | AC5: =VLOOKUP($B5,Dictionary_v2!$B:$E,2,0) -> Intercompany | AD5: Recurring | AE5: =VLOOKUP($B5,Dictionary_v2!$B:$E,3,0) | AG5: =VLOOKUP($B5,Dictionary_v2!$B:$E,4,0) | AH5: =if(C5>0,"In","Out") -> Out | AI5: =if(C5>0,"In","Out") -> Out
A6: 30/08/26 | B6: Anthropic | C6: -90.02 | D6: Sent | E6: Mercury Credit | F6: ANTHROPIC | I6: 3684 | J6: Ivan Amelong | K6: Software | P6: ############ | Q6: USD | T6: i@nexiu.ai | X6: 2026 | Y6: 2026 | Z6: 8 | AA6: 8 | AB6: 3 | AC6: =VLOOKUP($B6,Dictionary_v2!$B:$E,2,0) -> P&L | AD6: Recurring | AE6: =VLOOKUP($B6,Dictionary_v2!$B:$E,3,0) -> 3. Platform | AF6: =VLOOKUP(AE6,Dictionary_v2!R:S,2,0) -> 3. Platform | AG6: =VLOOKUP($B6,Dictionary_v2!$B:$E,4,0) -> 1. Variable | AH6: =if(C6>0,"In","Out") -> Out | AI6: =if(C6>0,"In","Out") -> Out
A7: 28/08/26 | B7: Facebook | C7: -48.95 | D7: Sent | E7: Mercury Credit | F7: FACEBK *YEGWTY9E92 | I7: 2489 | J7: Ivan Amelong | K7: Advertising | P7: ############ | Q7: USD | T7: i@nexiu.ai | X7: 2026 | Y7: 2026 | Z7: 8 | AA7: 8 | AB7: 3 | AC7: =VLOOKUP($B7,Dictionary_v2!$B:$E,2,0) -> P&L | AD7: Recurring | AE7: =VLOOKUP($B7,Dictionary_v2!$B:$E,3,0) -> 2. Candidates Sourcing | AF7: =VLOOKUP(AE7,Dictionary_v2!R:S,2,0) -> 2. Candidates Sourcing | AG7: =VLOOKUP($B7,Dictionary_v2!$B:$E,4,0) -> 1. Social media | AH7: =if(C7>0,"In","Out") -> Out | AI7: =if(C7>0,"In","Out") -> Out
A8: 27/08/26 | B8: Ivan Amelong - Wise (Ivan Amelong) | C8: -5500 | D8: Sent | E8: Welcome to Column N.A. (Mercury Checking xx5998) | F8: Send Money transaction initiated on Mercury | G8: From Nexiu AI, LLC via mercury.com | P8: ############ | U8: 121145431611741 | X8: 2026 | Y8: 2026 | Z8: 8 | AA8: 8 | AB8: 3 | AC8: =VLOOKUP($B8,Dictionary_v2!$B:$E,2,0) -> P&L | AD8: Recurring | AE8: =VLOOKUP($B8,Dictionary_v2!$B:$E,3,0) -> 7. Founders | AF8: =VLOOKUP(AE8,Dictionary_v2!R:S,2,0) -> 6. Other fixed and admin | AG8: =VLOOKUP($B8,Dictionary_v2!$B:$E,4,0) -> 1. Salaries | AH8: =if(C8>0,"In","Out") -> Out | AI8: =if(C8>0,"In","Out") -> Out
A9: 27/08/26 | B9: Fede (BoA) (Federico David Naides) | C9: -5500 | D9: Sent | E9: Welcome to Column N.A. (Mercury Checking xx5998) | F9: Send Money transaction initiated on Mercury | G9: From Nexiu AI, LLC | P9: ############ | U9: rttr_3IVRYnxSyk0ARsTrjLezShg08Br | X9: 2026 | Y9: 2026 | Z9: 8 | AA9: 8 | AB9: 3 | AC9: =VLOOKUP($B9,Dictionary_v2!$B:$E,2,0) -> P&L | AD9: Recurring | AE9: =VLOOKUP($B9,Dictionary_v2!$B:$E,3,0) -> 7. Founders | AF9: =VLOOKUP(AE9,Dictionary_v2!R:S,2,0) -> 6. Other fixed and admin | AG9: =VLOOKUP($B9,Dictionary_v2!$B:$E,4,0) -> 1. Salaries | AH9: =if(C9>0,"In","Out") -> Out | AI9: =if(C9>0,"In","Out") -> Out
A10: 27/08/26 | B10: Intl. Wire Fee | C10: -15 | D10: Sent | E10: Welcome to Column N.A. (Mercury Checking xx5998) | F10: OUR fee for international wire | P10: ############ | X10: 2026 | Y10: 2026 | Z10: 8 | AA10: 8 | AB10: 3 | AC10: =VLOOKUP($B10,Dictionary_v2!$B:$E,2,0) -> P&L | AD10: Recurring | AE10: =VLOOKUP($B10,Dictionary_v2!$B:$E,3,0) -> 3. Platform | AF10: =VLOOKUP(AE10,Dictionary_v2!R:S,2,0) -> 3. Platform | AG10: =VLOOKUP($B10,Dictionary_v2!$B:$E,4,0) -> 2. Fixed | AH10: =if(C10>0,"In","Out") -> Out | AI10: =if(C10>0,"In","Out") -> Out
A11: 27/08/26 | B11: Efren (Ecuador) (Efren Rogelio Narvaez Peña) | C11: -5000 | D11: Sent | E11: Welcome to Column N.A. (Mercury Checking xx5998) | F11: Send Money transaction initiated on Mercury | G11: From Nexiu AI LLC | P11: ############ | X11: 2026 | Y11: 2026 | Z11: 8 | AA11: 8 | AB11: 3 | AC11: =VLOOKUP($B11,Dictionary_v2!$B:$E,2,0) -> P&L | AD11: Recurring | AE11: =VLOOKUP($B11,Dictionary_v2!$B:$E,3,0) -> 7. Founders | AF11: =VLOOKUP(AE11,Dictionary_v2!R:S,2,0) -> 6. Other fixed and admin | AG11: =VLOOKUP($B11,Dictionary_v2!$B:$E,4,0) -> 1. Salaries | AH11: =if(C11>0,"In","Out") -> Out | AI11: =if(C11>0,"In","Out") -> Out
A12: 27/08/26 | B12: Welcome to Column N.A. (Mercury Checking xx5998) | C12: -11585.8 | D12: Sent | E12: Mercury Checking xx0301 | F12: Transfer between your Mercury accounts | P12: ############ | X12: 2026 | Y12: 2026 | Z12: 8 | AA12: 8 | AB12: 3 | AC12: =VLOOKUP($B12,Dictionary_v2!$B:$E,2,0) -> Intercompany | AD12: Recurring | AE12: =VLOOKUP($B12,Dictionary_v2!$B:$E,3,0) | AG12: =VLOOKUP($B12,Dictionary_v2!$B:$E,4,0) | AH12: =if(C12>0,"In","Out") -> Out | AI12: =if(C12>0,"In","Out") -> Out
A13: 27/08/26 | B13: Mercury Checking xx0301 | C13: 11585.8 | D13: Sent | E13: Welcome to Column N.A. (Mercury Checking xx5998) | F13: Transfer between your Mercury accounts | P13: ############ | X13: 2026 | Y13: 2026 | Z13: 8 | AA13: 8 | AB13: 3 | AC13: =VLOOKUP($B13,Dictionary_v2!$B:$E,2,0) -> Intercompany | AD13: Recurring | AE13: =VLOOKUP($B13,Dictionary_v2!$B:$E,3,0) | AG13: =VLOOKUP($B13,Dictionary_v2!$B:$E,4,0) | AH13: =if(C13>0,"In","Out") -> In | AI13: =if(C13>0,"In","Out") -> In
A14: 27/08/26 | B14: Welcome to Column N.A. (Mercury Checking xx5998) | C14: -19000 | D14: Sent | E14: Treasury | F14: Liquidation of Treasury assets | P14: ############ | U14: 20260827B1Q8154C326164 | X14: 2026 | Y14: 2026 | Z14: 8 | AA14: 8 | AB14: 3 | AC14: =VLOOKUP($B14,Dictionary_v2!$B:$E,2,0) -> Intercompany | AD14: Recurring | AE14: =VLOOKUP($B14,Dictionary_v2!$B:$E,3,0) | AG14: =VLOOKUP($B14,Dictionary_v2!$B:$E,4,0) | AH14: =if(C14>0,"In","Out") -> Out | AI14: =if(C14>0,"In","Out") -> Out
A15: 27/08/26 | B15: Treasury | C15: 19000 | D15: Sent | E15: Welcome to Column N.A. (Mercury Checking xx5998) | F15: Liquidation of Treasury assets | P15: ############ | U15: 20260827B1Q8154C326164 | X15: 2026 | Y15: 2026 | Z15: 8 | AA15: 8 | AB15: 3 | AC15: =VLOOKUP($B15,Dictionary_v2!$B:$E,2,0) -> Intercompany | AD15: Recurring | AE15: =VLOOKUP($B15,Dictionary_v2!$B:$E,3,0) | AG15: =VLOOKUP($B15,Dictionary_v2!$B:$E,4,0) | AH15: =if(C15>0,"In","Out") -> In | AI15: =if(C15>0,"In","Out") -> In
A16: 27/08/26 | B16: Anthropic | C16: -90.02 | D16: Sent | E16: Mercury Credit | F16: ANTHROPIC | I16: 3684 | J16: Ivan Amelong | K16: Software | P16: ############ | Q16: USD | T16: i@nexiu.ai | X16: 2026 | Y16: 2026 | Z16: 8 | AA16: 8 | AB16: 3 | AC16: =VLOOKUP($B16,Dictionary_v2!$B:$E,2,0) -> P&L | AD16: Recurring | AE16: =VLOOKUP($B16,Dictionary_v2!$B:$E,3,0) -> 3. Platform | AF16: =VLOOKUP(AE16,Dictionary_v2!R:S,2,0) -> 3. Platform | AG16: =VLOOKUP($B16,Dictionary_v2!$B:$E,4,0) -> 1. Variable | AH16: =if(C16>0,"In","Out") -> Out | AI16: =if(C16>0,"In","Out") -> Out
A17: 27/08/26 | B17: Facebook | C17: -985 | D17: Sent | E17: Mercury Credit | F17: FACEBK *Y4CTA26GV4 | I17: 2489 | J17: Ivan Amelong | K17: Advertising | P17: ############ | Q17: USD | T17: i@nexiu.ai | X17: 2026 | Y17: 2026 | Z17: 8 | AA17: 8 | AB17: 3 | AC17: =VLOOKUP($B17,Dictionary_v2!$B:$E,2,0) -> P&L | AD17: Recurring | AE17: =VLOOKUP($B17,Dictionary_v2!$B:$E,3,0) -> 2. Candidates Sourcing | AF17: =VLOOKUP(AE17,Dictionary_v2!R:S,2,0) -> 2. Candidates Sourcing | AG17: =VLOOKUP($B17,Dictionary_v2!$B:$E,4,0) -> 1. Social media | AH17: =if(C17>0,"In","Out") -> Out | AI17: =if(C17>0,"In","Out") -> Out
A18: 27/08/26 | B18: Facebook | C18: -10 | D18: Sent | E18: Mercury Checking xx0301 | F18: FACEBK *8SHQA26GV4 | I18: 9824 | J18: Ivan Amelong | K18: Advertising | P18: ############ | Q18: USD | T18: i@nexiu.ai | X18: 2026 | Y18: 2026 | Z18: 8 | AA18: 8 | AB18: 3 | AC18: =VLOOKUP($B18,Dictionary_v2!$B:$E,2,0) -> P&L | AD18: Recurring | AE18: =VLOOKUP($B18,Dictionary_v2!$B:$E,3,0) -> 2. Candidates Sourcing | AF18: =VLOOKUP(AE18,Dictionary_v2!R:S,2,0) -> 2. Candidates Sourcing | AG18: =VLOOKUP($B18,Dictionary_v2!$B:$E,4,0) -> 1. Social media | AH18: =if(C18>0,"In","Out") -> Out | AI18: =if(C18>0,"In","Out") -> Out
A19: 27/08/26 | B19: Facebook | C19: -343.37 | D19: Sent | E19: Mercury Checking xx0301 | F19: FACEBK *7FAR73EGV4 | I19: 9824 | J19: Ivan Amelong | K19: Advertising | P19: ############ | Q19: USD | T19: i@nexiu.ai | X19: 2026 | Y19: 2026 | Z19: 8 | AA19: 8 | AB19: 3 | AC19: =VLOOKUP($B19,Dictionary_v2!$B:$E,2,0) -> P&L | AD19: Recurring | AE19: =VLOOKUP($B19,Dictionary_v2!$B:$E,3,0) -> 2. Candidates Sourcing | AF19: =VLOOKUP(AE19,Dictionary_v2!R:S,2,0) -> 2. Candidates Sourcing | AG19: =VLOOKUP($B19,Dictionary_v2!$B:$E,4,0) -> 1. Social media | AH19: =if(C19>0,"In","Out") -> Out | AI19: =if(C19>0,"In","Out") -> Out
A20: 27/08/26 | B20: Facebook | C20: -4 | D20: Sent | E20: Mercury Credit | F20: FACEBK *J992W5JAR4 | I20: 3684 | J20: Ivan Amelong | K20: Advertising | P20: ############ | Q20: USD | T20: i@nexiu.ai | X20: 2026 | Y20: 2026 | Z20: 8 | AA20: 8 | AB20: 3 | AC20: =VLOOKUP($B20,Dictionary_v2!$B:$E,2,0) -> P&L | AD20: Recurring | AE20: =VLOOKUP($B20,Dictionary_v2!$B:$E,3,0) -> 2. Candidates Sourcing | AF20: =VLOOKUP(AE20,Dictionary_v2!R:S,2,0) -> 2. Candidates Sourcing | AG20: =VLOOKUP($B20,Dictionary_v2!$B:$E,4,0) -> 1. Social media | AH20: =if(C20>0,"In","Out") -> Out | AI20: =if(C20>0,"In","Out") -> Out
A21: 27/08/26 | B21: Metapay | C21: -9.71 | D21: Sent | E21: Mercury Credit | F21: METAPAY*MV4B | I21: 9691 | J21: Ivan Amelong | K21: FinancialInstitutionsAndFees | P21: ############ | Q21: MXN | T21: i@nexiu.ai | X21: 2026 | Y21: 2026 | Z21: 8 | AA21: 8 | AB21: 3 | AC21: =VLOOKUP($B21,Dictionary_v2!$B:$E,2,0) -> P&L | AD21: Recurring | AE21: =VLOOKUP($B21,Dictionary_v2!$B:$E,3,0) -> 3. Platform | AF21: =VLOOKUP(AE21,Dictionary_v2!R:S,2,0) -> 3. Platform | AG21: =VLOOKUP($B21,Dictionary_v2!$B:$E,4,0) -> 2. Fixed | AH21: =if(C21>0,"In","Out") -> Out | AI21: =if(C21>0,"In","Out") -> Out
A22: 27/08/26 | B22: Intl. Transaction Fee | C22: -0.29 | D22: Sent | E22: Mercury Credit | K22: FinancialInstitutionsAndFees | P22: ############ | X22: 2026 | Y22: 2026 | Z22: 8 | AA22: 8 | AB22: 3 | AC22: =VLOOKUP($B22,Dictionary_v2!$B:$E,2,0) -> P&L | AD22: Recurring | AE22: =VLOOKUP($B22,Dictionary_v2!$B:$E,3,0) -> 3. Platform | AF22: =VLOOKUP(AE22,Dictionary_v2!R:S,2,0) -> 3. Platform | AG22: =VLOOKUP($B22,Dictionary_v2!$B:$E,4,0) -> 2. Fixed | AH22: =if(C22>0,"In","Out") -> Out | AI22: =if(C22>0,"In","Out") -> Out
A23: 27/08/26 | B23: Facebook | C23: -498.48 | D23: Failed | E23: Mercury Credit | F23: FACEBK *X56MV3EAR4 | I23: 3684 | J23: Ivan Amelong | K23: Advertising | P23: ############ | Q23: USD | T23: i@nexiu.ai | V23: This transaction failed because it exceeded the spend limit for the card. | X23: 2026 | Y23: 2026 | Z23: 8 | AA23: 8 | AB23: 3 | AC23: =VLOOKUP($B23,Dictionary_v2!$B:$E,2,0) -> P&L | AD23: Recurring | AE23: =VLOOKUP($B23,Dictionary_v2!$B:$E,3,0) -> 2. Candidates Sourcing | AF23: =VLOOKUP(AE23,Dictionary_v2!R:S,2,0) -> 2. Candidates Sourcing | AG23: =VLOOKUP($B23,Dictionary_v2!$B:$E,4,0) -> 1. Social media | AH23: =if(C23>0,"In","Out") -> Out | AI23: =if(C23>0,"In","Out") -> Out
A24: 27/08/26 | B24: Facebook | C24: -744 | D24: Failed | E24: Mercury Credit | F24: FACEBK *SHMYV5JAR4 | I24: 3684 | J24: Ivan Amelong | K24: Advertising | P24: ############ | Q24: USD | T24: i@nexiu.ai | V24: This transaction failed because it exceeded the spend limit for the card. | X24: 2026 | Y24: 2026 | Z24: 8 | AA24: 8 | AB24: 3 | AC24: =VLOOKUP($B24,Dictionary_v2!$B:$E,2,0) -> P&L | AD24: Recurring | AE24: =VLOOKUP($B24,Dictionary_v2!$B:$E,3,0) -> 2. Candidates Sourcing | AF24: =VLOOKUP(AE24,Dictionary_v2!R:S,2,0) -> 2. Candidates Sourcing | AG24: =VLOOKUP($B24,Dictionary_v2!$B:$E,4,0) -> 1. Social media | AH24: =if(C24>0,"In","Out") -> Out | AI24: =if(C24>0,"In","Out") -> Out
A25: 27/08/26 | B25: Facebook | C25: -744 | D25: Failed | E25: Mercury Credit | F25: FACEBK *VDZRH46AR4 | I25: 3684 | J25: Ivan Amelong | K25: Advertising | P25: ############ | Q25: USD | T25: i@nexiu.ai | V25: This transaction failed because it exceeded the spend limit for the card. | X25: 2026 | Y25: 2026 | Z25: 8 | AA25: 8 | AB25: 3 | AC25: =VLOOKUP($B25,Dictionary_v2!$B:$E,2,0) -> P&L | AD25: Recurring | AE25: =VLOOKUP($B25,Dictionary_v2!$B:$E,3,0) -> 2. Candidates Sourcing | AF25: =VLOOKUP(AE25,Dictionary_v2!R:S,2,0) -> 2. Candidates Sourcing | AG25: =VLOOKUP($B25,Dictionary_v2!$B:$E,4,0) -> 1. Social media | AH25: =if(C25>0,"In","Out") -> Out | AI25: =if(C25>0,"In","Out") -> Out
A26: 27/08/26 | B26: Facebook | C26: 0 | D26: Failed | E26: Mercury Credit | F26: FACEBK *YK7JP32AR4 | I26: 3684 | J26: Ivan Amelong | K26: Advertising | P26: ############ | Q26: USD | T26: i@nexiu.ai | V26: The merchant canceled this transaction, possibly due to incorrect billing information. | X26: 2026 | Y26: 2026 | Z26: 8 | AA26: 8 | AB26: 3 | AC26: =VLOOKUP($B26,Dictionary_v2!$B:$E,2,0) -> P&L | AD26: Recurring | AE26: =VLOOKUP($B26,Dictionary_v2!$B:$E,3,0) -> 2. Candidates Sourcing | AF26: =VLOOKUP(AE26,Dictionary_v2!R:S,2,0) -> 2. Candidates Sourcing | AG26: =VLOOKUP($B26,Dictionary_v2!$B:$E,4,0) -> 1. Social media | AH26: =if(C26>0,"In","Out") -> Out | AI26: =if(C26>0,"In","Out") -> Out
A27: 26/08/26 | B27: Facebook | C27: -498.48 | D27: Failed | E27: Mercury Credit | F27: FACEBK *X7Z9P32AR4 | I27: 3684 | J27: Ivan Amelong | K27: Advertising | P27: ############ | Q27: USD | T27: i@nexiu.ai | V27: This transaction failed because it exceeded the spend limit for the card. | X27: 2026 | Y27: 2026 | Z27: 8 | AA27: 8 | AB27: 3 | AC27: =VLOOKUP($B27,Dictionary_v2!$B:$E,2,0) -> P&L | AD27: Recurring | AE27: =VLOOKUP($B27,Dictionary_v2!$B:$E,3,0) -> 2. Candidates Sourcing | AF27: =VLOOKUP(AE27,Dictionary_v2!R:S,2,0) -> 2. Candidates Sourcing | AG27: =VLOOKUP($B27,Dictionary_v2!$B:$E,4,0) -> 1. Social media | AH27: =if(C27>0,"In","Out") -> Out | AI27: =if(C27>0,"In","Out") -> Out
A28: 26/08/26 | B28: Facebook | C28: -744 | D28: Failed | E28: Mercury Credit | F28: FACEBK *4AK8Q3NAR4 | I28: 3684 | J28: Ivan Amelong | K28: Advertising | P28: ############ | Q28: USD | T28: i@nexiu.ai | V28: This transaction failed because it exceeded the spend limit for the card. | X28: 2026 | Y28: 2026 | Z28: 8 | AA28: 8 | AB28: 3 | AC28: =VLOOKUP($B28,Dictionary_v2!$B:$E,2,0) -> P&L | AD28: Recurring | AE28: =VLOOKUP($B28,Dictionary_v2!$B:$E,3,0) -> 2. Candidates Sourcing | AF28: =VLOOKUP(AE28,Dictionary_v2!R:S,2,0) -> 2. Candidates Sourcing | AG28: =VLOOKUP($B28,Dictionary_v2!$B:$E,4,0) -> 1. Social media | AH28: =if(C28>0,"In","Out") -> Out | AI28: =if(C28>0,"In","Out") -> Out
A29: 26/08/26 | B29: Facebook | C29: -744 | D29: Failed | E29: Mercury Credit | F29: FACEBK *HEU5852BR4 | I29: 3684 | J29: Ivan Amelong | K29: Advertising | P29: ############ | Q29: USD | T29: i@nexiu.ai | V29: This transaction failed because it exceeded the spend limit for the card. | X29: 2026 | Y29: 2026 | Z29: 8 | AA29: 8 | AB29: 3 | AC29: =VLOOKUP($B29,Dictionary_v2!$B:$E,2,0) -> P&L | AD29: Recurring | AE29: =VLOOKUP($B29,Dictionary_v2!$B:$E,3,0) -> 2. Candidates Sourcing | AF29: =VLOOKUP(AE29,Dictionary_v2!R:S,2,0) -> 2. Candidates Sourcing | AG29: =VLOOKUP($B29,Dictionary_v2!$B:$E,4,0) -> 1. Social media | AH29: =if(C29>0,"In","Out") -> Out | AI29: =if(C29>0,"In","Out") -> Out
A30: 26/08/26 | B30: Facebook | C30: -744 | D30: Failed | E30: Mercury Credit | F30: FACEBK *C55BP5AAR4 | I30: 3684 | J30: Ivan Amelong | K30: Advertising | P30: ############ | Q30: USD | T30: i@nexiu.ai | V30: This transaction failed because it exceeded the spend limit for the card. | X30: 2026 | Y30: 2026 | Z30: 8 | AA30: 8 | AB30: 3 | AC30: =VLOOKUP($B30,Dictionary_v2!$B:$E,2,0) -> P&L | AD30: Recurring | AE30: =VLOOKUP($B30,Dictionary_v2!$B:$E,3,0) -> 2. Candidates Sourcing | AF30: =VLOOKUP(AE30,Dictionary_v2!R:S,2,0) -> 2. Candidates Sourcing | AG30: =VLOOKUP($B30,Dictionary_v2!$B:$E,4,0) -> 1. Social media | AH30: =if(C30>0,"In","Out") -> Out | AI30: =if(C30>0,"In","Out") -> Out
A31: 26/08/26 | B31: Facebook | C31: -744 | D31: Failed | E31: Mercury Credit | F31: FACEBK *696634WAR4 | I31: 3684 | J31: Ivan Amelong | K31: Advertising | P31: ############ | Q31: USD | T31: i@nexiu.ai | V31: This transaction failed because it exceeded the spend limit for the card. | X31: 2026 | Y31: 2026 | Z31: 8 | AA31: 8 | AB31: 3 | AC31: =VLOOKUP($B31,Dictionary_v2!$B:$E,2,0) -> P&L | AD31: Recurring | AE31: =VLOOKUP($B31,Dictionary_v2!$B:$E,3,0) -> 2. Candidates Sourcing | AF31: =VLOOKUP(AE31,Dictionary_v2!R:S,2,0) -> 2. Candidates Sourcing | AG31: =VLOOKUP($B31,Dictionary_v2!$B:$E,4,0) -> 1. Social media | AH31: =if(C31>0,"In","Out") -> Out | AI31: =if(C31>0,"In","Out") -> Out
A32: 26/08/26 | B32: Facebook | C32: -498.48 | D32: Failed | E32: Mercury Credit | F32: FACEBK *2UU9P32AR4 | I32: 3684 | J32: Ivan Amelong | K32: Advertising | P32: ############ | Q32: USD | T32: i@nexiu.ai | V32: This transaction failed because it exceeded the spend limit for the card. | X32: 2026 | Y32: 2026 | Z32: 8 | AA32: 8 | AB32: 3 | AC32: =VLOOKUP($B32,Dictionary_v2!$B:$E,2,0) -> P&L | AD32: Recurring | AE32: =VLOOKUP($B32,Dictionary_v2!$B:$E,3,0) -> 2. Candidates Sourcing | AF32: =VLOOKUP(AE32,Dictionary_v2!R:S,2,0) -> 2. Candidates Sourcing | AG32: =VLOOKUP($B32,Dictionary_v2!$B:$E,4,0) -> 1. Social media | AH32: =if(C32>0,"In","Out") -> Out | AI32: =if(C32>0,"In","Out") -> Out
A33: 26/08/26 | B33: Facebook | C33: -744 | D33: Failed | E33: Mercury Credit | F33: FACEBK *2G3QV5JAR4 | I33: 3684 | J33: Ivan Amelong | K33: Advertising | P33: ############ | Q33: USD | T33: i@nexiu.ai | V33: This transaction failed because it exceeded the spend limit for the card. | X33: 2026 | Y33: 2026 | Z33: 8 | AA33: 8 | AB33: 3 | AC33: =VLOOKUP($B33,Dictionary_v2!$B:$E,2,0) -> P&L | AD33: Recurring | AE33: =VLOOKUP($B33,Dictionary_v2!$B:$E,3,0) -> 2. Candidates Sourcing | AF33: =VLOOKUP(AE33,Dictionary_v2!R:S,2,0) -> 2. Candidates Sourcing | AG33: =VLOOKUP($B33,Dictionary_v2!$B:$E,4,0) -> 1. Social media | AH33: =if(C33>0,"In","Out") -> Out | AI33: =if(C33>0,"In","Out") -> Out
A34: 26/08/26 | B34: Facebook | C34: -498.48 | D34: Failed | E34: Mercury Credit | F34: FACEBK *4UQ9P32AR4 | I34: 3684 | J34: Ivan Amelong | K34: Advertising | P34: ############ | Q34: USD | T34: i@nexiu.ai | V34: This transaction failed because it exceeded the spend limit for the card. | X34: 2026 | Y34: 2026 | Z34: 8 | AA34: 8 | AB34: 3 | AC34: =VLOOKUP($B34,Dictionary_v2!$B:$E,2,0) -> P&L | AD34: Recurring | AE34: =VLOOKUP($B34,Dictionary_v2!$B:$E,3,0) -> 2. Candidates Sourcing | AF34: =VLOOKUP(AE34,Dictionary_v2!R:S,2,0) -> 2. Candidates Sourcing | AG34: =VLOOKUP($B34,Dictionary_v2!$B:$E,4,0) -> 1. Social media | AH34: =if(C34>0,"In","Out") -> Out | AI34: =if(C34>0,"In","Out") -> Out
A35: 26/08/26 | B35: Facebook | C35: -744 | D35: Failed | E35: Mercury Credit | F35: FACEBK *XLQ9P32AR4 | I35: 3684 | J35: Ivan Amelong | K35: Advertising | P35: ############ | Q35: USD | T35: i@nexiu.ai | V35: This transaction failed because it exceeded the spend limit for the card. | X35: 2026 | Y35: 2026 | Z35: 8 | AA35: 8 | AB35: 3 | AC35: =VLOOKUP($B35,Dictionary_v2!$B:$E,2,0) -> P&L | AD35: Recurring | AE35: =VLOOKUP($B35,Dictionary_v2!$B:$E,3,0) -> 2. Candidates Sourcing | AF35: =VLOOKUP(AE35,Dictionary_v2!R:S,2,0) -> 2. Candidates Sourcing | AG35: =VLOOKUP($B35,Dictionary_v2!$B:$E,4,0) -> 1. Social media | AH35: =if(C35>0,"In","Out") -> Out | AI35: =if(C35>0,"In","Out") -> Out
A36: 26/08/26 | B36: Welcome to Column N.A. (Mercury Checking xx5998) | C36: -5000 | D36: Sent | E36: Treasury | F36: Liquidation of Treasury assets | P36: ############ | U36: 20260826B1Q8152C298051 | X36: 2026 | Y36: 2026 | Z36: 8 | AA36: 8 | AB36: 3 | AC36: =VLOOKUP($B36,Dictionary_v2!$B:$E,2,0) -> Intercompany | AD36: Recurring | AE36: =VLOOKUP($B36,Dictionary_v2!$B:$E,3,0) | AG36: =VLOOKUP($B36,Dictionary_v2!$B:$E,4,0) | AH36: =if(C36>0,"In","Out") -> Out | AI36: =if(C36>0,"In","Out") -> Out
A37: 26/08/26 | B37: Treasury | C37: 5000 | D37: Sent | E37: Welcome to Column N.A. (Mercury Checking xx5998) | F37: Liquidation of Treasury assets | P37: ############ | U37: 20260826B1Q8152C298051 | X37: 2026 | Y37: 2026 | Z37: 8 | AA37: 8 | AB37: 3 | AC37: =VLOOKUP($B37,Dictionary_v2!$B:$E,2,0) -> Intercompany | AD37: Recurring | AE37: =VLOOKUP($B37,Dictionary_v2!$B:$E,3,0) | AG37: =VLOOKUP($B37,Dictionary_v2!$B:$E,4,0) | AH37: =if(C37>0,"In","Out") -> In | AI37: =if(C37>0,"In","Out") -> In
A38: 26/08/26 | B38: Monica Tonanzin García Vega (Monica Tonanzin García Vega) | C38: -1033 | D38: Sent | E38: Welcome to Column N.A. (Mercury Checking xx5998) | F38: Send Money transaction initiated on Mercury | G38: Contractor, Aug 2026 | P38: ############ | U38: 121145431600187 | X38: 2026 | Y38: 2026 | Z38: 8 | AA38: 8 | AB38: 3 | AC38: =VLOOKUP($B38,Dictionary_v2!$B:$E,2,0) -> P&L | AD38: Recurring | AE38: =VLOOKUP($B38,Dictionary_v2!$B:$E,3,0) -> 4. People | AF38: =VLOOKUP(AE38,Dictionary_v2!R:S,2,0) -> 4. People | AG38: =VLOOKUP($B38,Dictionary_v2!$B:$E,4,0) -> 1. Operations | AH38: =if(C38>0,"In","Out") -> Out | AI38: =if(C38>0,"In","Out") -> Out
A39: 26/08/26 | B39: Bullmetrix LLC (Bullmetrix LLC) | C39: -1500 | D39: Sent | E39: Welcome to Column N.A. (Mercury Checking xx5998) | F39: Send Money transaction initiated on Mercury | G39: Payment, invoice: 2026485 | P39: ############ | U39: 121145431600179 | X39: 2026 | Y39: 2026 | Z39: 8 | AA39: 8 | AB39: 3 | AC39: =VLOOKUP($B39,Dictionary_v2!$B:$E,2,0) -> P&L | AD39: Recurring | AE39: =VLOOKUP($B39,Dictionary_v2!$B:$E,3,0) -> 5. Marketing | AF39: =VLOOKUP(AE39,Dictionary_v2!R:S,2,0) -> 5. Marketing | AG39: =VLOOKUP($B39,Dictionary_v2!$B:$E,4,0) -> 2. Agency | AH39: =if(C39>0,"In","Out") -> Out | AI39: =if(C39>0,"In","Out") -> Out
A40: 26/08/26 | B40: Intl. Wire Foreign Exchange Fee | C40: -10.33 | D40: Sent | E40: Welcome to Column N.A. (Mercury Checking xx5998) | F40: Currency exchange fee for international wire | P40: ############ | X40: 2026 | Y40: 2026 | Z40: 8 | AA40: 8 | AB40: 3 | AC40: =VLOOKUP($B40,Dictionary_v2!$B:$E,2,0) -> P&L | AD40: Recurring | AE40: =VLOOKUP($B40,Dictionary_v2!$B:$E,3,0) -> 3. Platform | AF40: =VLOOKUP(AE40,Dictionary_v2!R:S,2,0) -> 3. Platform | AG40: =VLOOKUP($B40,Dictionary_v2!$B:$E,4,0) -> 2. Fixed | AH40: =if(C40>0,"In","Out") -> Out | AI40: =if(C40>0,"In","Out") -> Out
A41: 26/08/26 | B41: Andrea Gomez (Andrea Gómez Romero) | C41: -1032.96 | D41: Sent | E41: Welcome to Column N.A. (Mercury Checking xx5998) | F41: Send Money transaction initiated on Mercury | G41: From Nexiu AI LLC | P41: ############ | X41: 2026 | Y41: 2026 | Z41: 8 | AA41: 8 | AB41: 3 | AC41: =VLOOKUP($B41,Dictionary_v2!$B:$E,2,0) -> P&L | AD41: Recurring | AE41: =VLOOKUP($B41,Dictionary_v2!$B:$E,3,0) -> 4. People | AF41: =VLOOKUP(AE41,Dictionary_v2!R:S,2,0) -> 4. People | AG41: =VLOOKUP($B41,Dictionary_v2!$B:$E,4,0) -> 1. Operations | AH41: =if(C41>0,"In","Out") -> Out | AI41: =if(C41>0,"In","Out") -> Out
A42: 26/08/26 | B42: Aldana Casas (Aldana Casas) | C42: -1200 | D42: Sent | E42: Welcome to Column N.A. (Mercury Checking xx5998) | F42: Send Money transaction initiated on Mercury | G42: Contractor, Aug 2026 | P42: ############ | U42: 121145431600426 | X42: 2026 | Y42: 2026 | Z42: 8 | AA42: 8 | AB42: 3 | AC42: =VLOOKUP($B42,Dictionary_v2!$B:$E,2,0) -> P&L | AD42: Recurring | AE42: =VLOOKUP($B42,Dictionary_v2!$B:$E,3,0) -> 5. Marketing | AF42: =VLOOKUP(AE42,Dictionary_v2!R:S,2,0) -> 5. Marketing | AG42: =VLOOKUP($B42,Dictionary_v2!$B:$E,4,0) -> 1. People | AH42: =if(C42>0,"In","Out") -> Out | AI42: =if(C42>0,"In","Out") -> Out
A43: 26/08/26 | B43: Facebook | C43: -140 | D43: Sent | E43: Mercury Credit | F43: FACEBK *Y29ZHYHD92 | I43: 3684 | J43: Ivan Amelong | K43: Advertising | P43: ############ | Q43: USD | T43: i@nexiu.ai | X43: 2026 | Y43: 2026 | Z43: 8 | AA43: 8 | AB43: 3 | AC43: =VLOOKUP($B43,Dictionary_v2!$B:$E,2,0) -> P&L | AD43: Recurring | AE43: =VLOOKUP($B43,Dictionary_v2!$B:$E,3,0) -> 2. Candidates Sourcing | AF43: =VLOOKUP(AE43,Dictionary_v2!R:S,2,0) -> 2. Candidates Sourcing | AG43: =VLOOKUP($B43,Dictionary_v2!$B:$E,4,0) -> 1. Social media | AH43: =if(C43>0,"In","Out") -> Out | AI43: =if(C43>0,"In","Out") -> Out
A44: 26/08/26 | B44: Anthropic | C44: -90.04 | D44: Sent | E44: Mercury Credit | F44: ANTHROPIC | I44: 3684 | J44: Ivan Amelong | K44: Software | P44: ############ | Q44: USD | T44: i@nexiu.ai | X44: 2026 | Y44: 2026 | Z44: 8 | AA44: 8 | AB44: 3 | AC44: =VLOOKUP($B44,Dictionary_v2!$B:$E,2,0) -> P&L | AD44: Recurring | AE44: =VLOOKUP($B44,Dictionary_v2!$B:$E,3,0) -> 3. Platform | AF44: =VLOOKUP(AE44,Dictionary_v2!R:S,2,0) -> 3. Platform | AG44: =VLOOKUP($B44,Dictionary_v2!$B:$E,4,0) -> 1. Variable | AH44: =if(C44>0,"In","Out") -> Out | AI44: =if(C44>0,"In","Out") -> Out
A45: 25/08/26 | B45: Facebook | C45: -1.11 | D45: Sent | E45: Mercury Credit | F45: FACEBK *VHSMC4SAR4 | I45: 3684 | J45: Ivan Amelong | K45: Advertising | P45: ############ | Q45: USD | T45: i@nexiu.ai | X45: 2026 | Y45: 2026 | Z45: 8 | AA45: 8 | AB45: 3 | AC45: =VLOOKUP($B45,Dictionary_v2!$B:$E,2,0) -> P&L | AD45: Recurring | AE45: =VLOOKUP($B45,Dictionary_v2!$B:$E,3,0) -> 2. Candidates Sourcing | AF45: =VLOOKUP(AE45,Dictionary_v2!R:S,2,0) -> 2. Candidates Sourcing | AG45: =VLOOKUP($B45,Dictionary_v2!$B:$E,4,0) -> 1. Social media | AH45: =if(C45>0,"In","Out") -> Out | AI45: =if(C45>0,"In","Out") -> Out
A46: 25/08/26 | B46: Facebook | C46: -656.56 | D46: Sent | E46: Mercury Credit | F46: FACEBK *KZ34732AR4 | I46: 3684 | J46: Ivan Amelong | K46: Advertising | P46: ############ | Q46: USD | T46: i@nexiu.ai | X46: 2026 | Y46: 2026 | Z46: 8 | AA46: 8 | AB46: 3 | AC46: =VLOOKUP($B46,Dictionary_v2!$B:$E,2,0) -> P&L | AD46: Recurring | AE46: =VLOOKUP($B46,Dictionary_v2!$B:$E,3,0) -> 2. Candidates Sourcing | AF46: =VLOOKUP(AE46,Dictionary_v2!R:S,2,0) -> 2. Candidates Sourcing | AG46: =VLOOKUP($B46,Dictionary_v2!$B:$E,4,0) -> 1. Social media | AH46: =if(C46>0,"In","Out") -> Out | AI46: =if(C46>0,"In","Out") -> Out
A47: 25/08/26 | B47: Vercel | C47: -40 | D47: Sent | E47: Mercury Credit | F47: VERCEL INC. | I47: 3684 | J47: Ivan Amelong | K47: Software | P47: ############ | Q47: USD | T47: i@nexiu.ai | X47: 2026 | Y47: 2026 | Z47: 8 | AA47: 8 | AB47: 3 | AC47: =VLOOKUP($B47,Dictionary_v2!$B:$E,2,0) -> P&L | AD47: Recurring | AE47: =VLOOKUP($B47,Dictionary_v2!$B:$E,3,0) -> 3. Platform | AF47: =VLOOKUP(AE47,Dictionary_v2!R:S,2,0) -> 3. Platform | AG47: =VLOOKUP($B47,Dictionary_v2!$B:$E,4,0) -> 2. Fixed | AH47: =if(C47>0,"In","Out") -> Out | AI47: =if(C47>0,"In","Out") -> Out
A48: 24/08/26 | B48: Whaticket | C48: -49 | D48: Sent | E48: Mercury Credit | F48: WHATICKET | I48: 3684 | J48: Ivan Amelong | K48: Software | P48: ############ | Q48: USD | T48: i@nexiu.ai | X48: 2026 | Y48: 2026 | Z48: 8 | AA48: 8 | AB48: 3 | AC48: =VLOOKUP($B48,Dictionary_v2!$B:$E,2,0) -> P&L | AD48: Recurring | AE48: =VLOOKUP($B48,Dictionary_v2!$B:$E,3,0) -> 3. Platform | AF48: =VLOOKUP(AE48,Dictionary_v2!R:S,2,0) -> 3. Platform | AG48: =VLOOKUP($B48,Dictionary_v2!$B:$E,4,0) -> 1. Variable | AH48: =if(C48>0,"In","Out") -> Out | AI48: =if(C48>0,"In","Out") -> Out
A49: 24/08/26 | B49: Metapay | C49: 9.73 | D49: Sent | E49: Mercury Credit | F49: METAPAY*MV4B | I49: 9691 | J49: Ivan Amelong | K49: FinancialInstitutionsAndFees | P49: ############ | Q49: MXN | T49: i@nexiu.ai | X49: 2026 | Y49: 2026 | Z49: 8 | AA49: 8 | AB49: 3 | AC49: =VLOOKUP($B49,Dictionary_v2!$B:$E,2,0) -> P&L | AD49: Recurring | AE49: =VLOOKUP($B49,Dictionary_v2!$B:$E,3,0) -> 3. Platform | AF49: =VLOOKUP(AE49,Dictionary_v2!R:S,2,0) -> 3. Platform | AG49: =VLOOKUP($B49,Dictionary_v2!$B:$E,4,0) -> 2. Fixed | AH49: =if(C49>0,"In","Out") -> In | AI49: =if(C49>0,"In","Out") -> In
A50: 24/08/26 | B50: Anthropic | C50: -90.02 | D50: Sent | E50: Mercury Credit | F50: ANTHROPIC | I50: 3684 | J50: Ivan Amelong | K50: Software | P50: ############ | Q50: USD | T50: i@nexiu.ai | X50: 2026 | Y50: 2026 | Z50: 8 | AA50: 8 | AB50: 3 | AC50: =VLOOKUP($B50,Dictionary_v2!$B:$E,2,0) -> P&L | AD50: Recurring | AE50: =VLOOKUP($B50,Dictionary_v2!$B:$E,3,0) -> 3. Platform | AF50: =VLOOKUP(AE50,Dictionary_v2!R:S,2,0) -> 3. Platform | AG50: =VLOOKUP($B50,Dictionary_v2!$B:$E,4,0) -> 1. Variable | AH50: =if(C50>0,"In","Out") -> Out | AI50: =if(C50>0,"In","Out") -> Out
A51: 23/08/26 | B51: Facebook | C51: -140 | D51: Sent | E51: Mercury Credit | F51: FACEBK *DKLU9Y9E92 | I51: 3684 | J51: Ivan Amelong | K51: Advertising | P51: ############ | Q51: USD | T51: i@nexiu.ai | X51: 2026 | Y51: 2026 | Z51: 8 | AA51: 8 | AB51: 3 | AC51: =VLOOKUP($B51,Dictionary_v2!$B:$E,2,0) -> P&L | AD51: Recurring | AE51: =VLOOKUP($B51,Dictionary_v2!$B:$E,3,0) -> 2. Candidates Sourcing | AF51: =VLOOKUP(AE51,Dictionary_v2!R:S,2,0) -> 2. Candidates Sourcing | AG51: =VLOOKUP($B51,Dictionary_v2!$B:$E,4,0) -> 1. Social media | AH51: =if(C51>0,"In","Out") -> Out | AI51: =if(C51>0,"In","Out") -> Out
A52: 23/08/26 | B52: Facebook | C52: -145.52 | D52: Sent | E52: Mercury Credit | F52: FACEBK *4J83732AR4 | I52: 3684 | J52: Ivan Amelong | K52: Advertising | P52: ############ | Q52: USD | T52: i@nexiu.ai | X52: 2026 | Y52: 2026 | Z52: 8 | AA52: 8 | AB52: 3 | AC52: =VLOOKUP($B52,Dictionary_v2!$B:$E,2,0) -> P&L | AD52: Recurring | AE52: =VLOOKUP($B52,Dictionary_v2!$B:$E,3,0) -> 2. Candidates Sourcing | AF52: =VLOOKUP(AE52,Dictionary_v2!R:S,2,0) -> 2. Candidates Sourcing | AG52: =VLOOKUP($B52,Dictionary_v2!$B:$E,4,0) -> 1. Social media | AH52: =if(C52>0,"In","Out") -> Out | AI52: =if(C52>0,"In","Out") -> Out
A53: 23/08/26 | B53: Metapay | C53: -19.99 | D53: Sent | E53: Mercury Credit | F53: METAPAY*MV4B | I53: 3684 | J53: Ivan Amelong | K53: FinancialInstitutionsAndFees | P53: ############ | Q53: USD | T53: i@nexiu.ai | X53: 2026 | Y53: 2026 | Z53: 8 | AA53: 8 | AB53: 3 | AC53: =VLOOKUP($B53,Dictionary_v2!$B:$E,2,0) -> P&L | AD53: Recurring | AE53: =VLOOKUP($B53,Dictionary_v2!$B:$E,3,0) -> 3. Platform | AF53: =VLOOKUP(AE53,Dictionary_v2!R:S,2,0) -> 3. Platform | AG53: =VLOOKUP($B53,Dictionary_v2!$B:$E,4,0) -> 2. Fixed | AH53: =if(C53>0,"In","Out") -> Out | AI53: =if(C53>0,"In","Out") -> Out
A54: 23/08/26 | B54: Facebook | C54: -160.49 | D54: Sent | E54: Mercury Credit | F54: FACEBK *YA7DV4JAR4 | I54: 3684 | J54: Ivan Amelong | K54: Advertising | P54: ############ | Q54: USD | T54: i@nexiu.ai | X54: 2026 | Y54: 2026 | Z54: 8 | AA54: 8 | AB54: 3 | AC54: =VLOOKUP($B54,Dictionary_v2!$B:$E,2,0) -> P&L | AD54: Recurring | AE54: =VLOOKUP($B54,Dictionary_v2!$B:$E,3,0) -> 2. Candidates Sourcing | AF54: =VLOOKUP(AE54,Dictionary_v2!R:S,2,0) -> 2. Candidates Sourcing | AG54: =VLOOKUP($B54,Dictionary_v2!$B:$E,4,0) -> 1. Social media | AH54: =if(C54>0,"In","Out") -> Out | AI54: =if(C54>0,"In","Out") -> Out
A55: 22/08/26 | B55: Rest C Real Tijuana | C55: -26.68 | D55: Sent | E55: Mercury Checking xx0301 | F55: REST C REAL TIJUANA | I55: 4376 | J55: Ivan Amelong | K55: Restaurants | P55: ############ | Q55: MXN | T55: i@nexiu.ai | X55: 2026 | Y55: 2026 | Z55: 8 | AA55: 8 | AB55: 3 | AC55: =VLOOKUP($B55,Dictionary_v2!$B:$E,2,0) -> P&L | AD55: Recurring | AE55: =VLOOKUP($B55,Dictionary_v2!$B:$E,3,0) -> 5. Marketing | AF55: =VLOOKUP(AE55,Dictionary_v2!R:S,2,0) -> 5. Marketing | AG55: =VLOOKUP($B55,Dictionary_v2!$B:$E,4,0) -> 3. Events | AH55: =if(C55>0,"In","Out") -> Out | AI55: =if(C55>0,"In","Out") -> Out
A56: 22/08/26 | B56: Intl. Transaction Fee | C56: -0.8 | D56: Sent | E56: Mercury Checking xx0301 | K56: FinancialInstitutionsAndFees | P56: ############ | X56: 2026 | Y56: 2026 | Z56: 8 | AA56: 8 | AB56: 3 | AC56: =VLOOKUP($B56,Dictionary_v2!$B:$E,2,0) -> P&L | AD56: Recurring | AE56: =VLOOKUP($B56,Dictionary_v2!$B:$E,3,0) -> 3. Platform | AF56: =VLOOKUP(AE56,Dictionary_v2!R:S,2,0) -> 3. Platform | AG56: =VLOOKUP($B56,Dictionary_v2!$B:$E,4,0) -> 2. Fixed | AH56: =if(C56>0,"In","Out") -> Out | AI56: =if(C56>0,"In","Out") -> Out
A57: 22/08/26 | B57: Office Max Tijuana | C57: -3.07 | D57: Sent | E57: Mercury Checking xx0301 | F57: OFFICE MAX TIJUANA | I57: 4376 | J57: Ivan Amelong | K57: Grocery | P57: ############ | Q57: MXN | T57: i@nexiu.ai | X57: 2026 | Y57: 2026 | Z57: 8 | AA57: 8 | AB57: 3 | AC57: =VLOOKUP($B57,Dictionary_v2!$B:$E,2,0) -> P&L | AD57: Recurring | AE57: =VLOOKUP($B57,Dictionary_v2!$B:$E,3,0) -> 5. Marketing | AF57: =VLOOKUP(AE57,Dictionary_v2!R:S,2,0) -> 5. Marketing | AG57: =VLOOKUP($B57,Dictionary_v2!$B:$E,4,0) -> 3. Events | AH57: =if(C57>0,"In","Out") -> Out | AI57: =if(C57>0,"In","Out") -> Out
A58: 22/08/26 | B58: Intl. Transaction Fee | C58: -0.09 | D58: Sent | E58: Mercury Checking xx0301 | K58: FinancialInstitutionsAndFees | P58: ############ | X58: 2026 | Y58: 2026 | Z58: 8 | AA58: 8 | AB58: 3 | AC58: =VLOOKUP($B58,Dictionary_v2!$B:$E,2,0) -> P&L | AD58: Recurring | AE58: =VLOOKUP($B58,Dictionary_v2!$B:$E,3,0) -> 3. Platform | AF58: =VLOOKUP(AE58,Dictionary_v2!R:S,2,0) -> 3. Platform | AG58: =VLOOKUP($B58,Dictionary_v2!$B:$E,4,0) -> 2. Fixed | AH58: =if(C58>0,"In","Out") -> Out | AI58: =if(C58>0,"In","Out") -> Out
A59: 22/08/26 | B59: Intl. Transaction Fee | C59: -1.23 | D59: Sent | E59: Mercury Checking xx0301 | K59: FinancialInstitutionsAndFees | P59: ############ | X59: 2026 | Y59: 2026 | Z59: 8 | AA59: 8 | AB59: 3 | AC59: =VLOOKUP($B59,Dictionary_v2!$B:$E,2,0) -> P&L | AD59: Recurring | AE59: =VLOOKUP($B59,Dictionary_v2!$B:$E,3,0) -> 3. Platform | AF59: =VLOOKUP(AE59,Dictionary_v2!R:S,2,0) -> 3. Platform | AG59: =VLOOKUP($B59,Dictionary_v2!$B:$E,4,0) -> 2. Fixed | AH59: =if(C59>0,"In","Out") -> Out | AI59: =if(C59>0,"In","Out") -> Out
A60: 22/08/26 | B60: Office Max Tijuana | C60: -41.15 | D60: Sent | E60: Mercury Checking xx0301 | F60: OFFICE MAX TIJUANA | I60: 4376 | J60: Ivan Amelong | K60: Grocery | P60: ############ | Q60: MXN | T60: i@nexiu.ai | X60: 2026 | Y60: 2026 | Z60: 8 | AA60: 8 | AB60: 3 | AC60: =VLOOKUP($B60,Dictionary_v2!$B:$E,2,0) -> P&L | AD60: Recurring | AE60: =VLOOKUP($B60,Dictionary_v2!$B:$E,3,0) -> 5. Marketing | AF60: =VLOOKUP(AE60,Dictionary_v2!R:S,2,0) -> 5. Marketing | AG60: =VLOOKUP($B60,Dictionary_v2!$B:$E,4,0) -> 3. Events | AH60: =if(C60>0,"In","Out") -> Out | AI60: =if(C60>0,"In","Out") -> Out
A61: 22/08/26 | B61: Office Max Tijuana | C61: -60.87 | D61: Sent | E61: Mercury Checking xx0301 | F61: OFFICE MAX TIJUANA | I61: 4376 | J61: Ivan Amelong | K61: Grocery | P61: ############ | Q61: MXN | T61: i@nexiu.ai | X61: 2026 | Y61: 2026 | Z61: 8 | AA61: 8 | AB61: 3 | AC61: =VLOOKUP($B61,Dictionary_v2!$B:$E,2,0) -> P&L | AD61: Recurring | AE61: =VLOOKUP($B61,Dictionary_v2!$B:$E,3,0) -> 5. Marketing | AF61: =VLOOKUP(AE61,Dictionary_v2!R:S,2,0) -> 5. Marketing | AG61: =VLOOKUP($B61,Dictionary_v2!$B:$E,4,0) -> 3. Events | AH61: =if(C61>0,"In","Out") -> Out | AI61: =if(C61>0,"In","Out") -> Out
A62: 22/08/26 | B62: Intl. Transaction Fee | C62: -1.83 | D62: Sent | E62: Mercury Checking xx0301 | K62: FinancialInstitutionsAndFees | P62: ############ | X62: 2026 | Y62: 2026 | Z62: 8 | AA62: 8 | AB62: 3 | AC62: =VLOOKUP($B62,Dictionary_v2!$B:$E,2,0) -> P&L | AD62: Recurring | AE62: =VLOOKUP($B62,Dictionary_v2!$B:$E,3,0) -> 3. Platform | AF62: =VLOOKUP(AE62,Dictionary_v2!R:S,2,0) -> 3. Platform | AG62: =VLOOKUP($B62,Dictionary_v2!$B:$E,4,0) -> 2. Fixed | AH62: =if(C62>0,"In","Out") -> Out | AI62: =if(C62>0,"In","Out") -> Out
A63: 22/08/26 | B63: Anthropic | C63: -90.04 | D63: Sent | E63: Mercury Credit | F63: ANTHROPIC | I63: 3684 | J63: Ivan Amelong | K63: Software | P63: ############ | Q63: USD | T63: i@nexiu.ai | X63: 2026 | Y63: 2026 | Z63: 8 | AA63: 8 | AB63: 3 | AC63: =VLOOKUP($B63,Dictionary_v2!$B:$E,2,0) -> P&L | AD63: Recurring | AE63: =VLOOKUP($B63,Dictionary_v2!$B:$E,3,0) -> 3. Platform | AF63: =VLOOKUP(AE63,Dictionary_v2!R:S,2,0) -> 3. Platform | AG63: =VLOOKUP($B63,Dictionary_v2!$B:$E,4,0) -> 1. Variable | AH63: =if(C63>0,"In","Out") -> Out | AI63: =if(C63>0,"In","Out") -> Out
A64: 21/08/26 | B64: Mercury Checking xx8107 | C64: 10810 | D64: Sent | E64: Mercury Checking xx0301 | P64: ############ | U64: 91311220015694 | X64: 2026 | Y64: 2026 | Z64: 8 | AA64: 8 | AB64: 3 | AC64: =VLOOKUP($B64,Dictionary_v2!$B:$E,2,0) -> Intercompany | AD64: Recurring | AE64: =VLOOKUP($B64,Dictionary_v2!$B:$E,3,0) | AG64: =VLOOKUP($B64,Dictionary_v2!$B:$E,4,0) | AH64: =if(C64>0,"In","Out") -> In | AI64: =if(C64>0,"In","Out") -> In
A65: 21/08/26 | B65: Mercury Checking xx0301 | C65: -10810 | D65: Sent | E65: Mercury Checking xx8107 | P65: ############ | U65: 91311220015694 | X65: 2026 | Y65: 2026 | Z65: 8 | AA65: 8 | AB65: 3 | AC65: =VLOOKUP($B65,Dictionary_v2!$B:$E,2,0) -> Intercompany | AD65: Recurring | AE65: =VLOOKUP($B65,Dictionary_v2!$B:$E,3,0) | AG65: =VLOOKUP($B65,Dictionary_v2!$B:$E,4,0) | AH65: =if(C65>0,"In","Out") -> Out | AI65: =if(C65>0,"In","Out") -> Out
A66: 21/08/26 | B66: LATIN AMERICA FUTURE AUTOMOBILE MEX | C66: 10810 | D66: Sent | E66: Mercury Checking xx8107 | P66: ############ | X66: 2026 | Y66: 2026 | Z66: 8 | AA66: 8 | AB66: 3 | AC66: =VLOOKUP($B66,Dictionary_v2!$B:$E,2,0) -> P&L | AD66: Recurring | AE66: =VLOOKUP($B66,Dictionary_v2!$B:$E,3,0) -> 1. Collections | AF66: =VLOOKUP(AE66,Dictionary_v2!R:S,2,0) -> 1. Collections | AG66: =VLOOKUP($B66,Dictionary_v2!$B:$E,4,0) -> 1. Full Stack | AH66: =if(C66>0,"In","Out") -> In | AI66: =if(C66>0,"In","Out") -> In
A67: 21/08/26 | B67: Rest C Real Tijuana | C67: -26.66 | D67: Sent | E67: Mercury Checking xx0301 | F67: REST C REAL TIJUANA | I67: 4376 | J67: Ivan Amelong | K67: Restaurants | P67: ############ | Q67: MXN | T67: i@nexiu.ai | X67: 2026 | Y67: 2026 | Z67: 8 | AA67: 8 | AB67: 3 | AC67: =VLOOKUP($B67,Dictionary_v2!$B:$E,2,0) -> P&L | AD67: Recurring | AE67: =VLOOKUP($B67,Dictionary_v2!$B:$E,3,0) -> 5. Marketing | AF67: =VLOOKUP(AE67,Dictionary_v2!R:S,2,0) -> 5. Marketing | AG67: =VLOOKUP($B67,Dictionary_v2!$B:$E,4,0) -> 3. Events | AH67: =if(C67>0,"In","Out") -> Out | AI67: =if(C67>0,"In","Out") -> Out
A68: 21/08/26 | B68: Intl. Transaction Fee | C68: -0.8 | D68: Sent | E68: Mercury Checking xx0301 | K68: FinancialInstitutionsAndFees | P68: ############ | X68: 2026 | Y68: 2026 | Z68: 8 | AA68: 8 | AB68: 3 | AC68: =VLOOKUP($B68,Dictionary_v2!$B:$E,2,0) -> P&L | AD68: Recurring | AE68: =VLOOKUP($B68,Dictionary_v2!$B:$E,3,0) -> 3. Platform | AF68: =VLOOKUP(AE68,Dictionary_v2!R:S,2,0) -> 3. Platform | AG68: =VLOOKUP($B68,Dictionary_v2!$B:$E,4,0) -> 2. Fixed | AH68: =if(C68>0,"In","Out") -> Out | AI68: =if(C68>0,"In","Out") -> Out
A69: 21/08/26 | B69: Recall | C69: -10.38 | D69: Sent | E69: Mercury Credit | F69: RECALL.AI | I69: 3684 | J69: Ivan Amelong | K69: Software | P69: ############ | Q69: USD | T69: i@nexiu.ai | X69: 2026 | Y69: 2026 | Z69: 8 | AA69: 8 | AB69: 3 | AC69: =VLOOKUP($B69,Dictionary_v2!$B:$E,2,0) -> P&L | AD69: Recurring | AE69: =VLOOKUP($B69,Dictionary_v2!$B:$E,3,0) -> 3. Platform | AF69: =VLOOKUP(AE69,Dictionary_v2!R:S,2,0) -> 3. Platform | AG69: =VLOOKUP($B69,Dictionary_v2!$B:$E,4,0) -> 2. Fixed | AH69: =if(C69>0,"In","Out") -> Out | AI69: =if(C69>0,"In","Out") -> Out
A70: 21/08/26 | B70: Facebook | C70: -77 | D70: Sent | E70: Mercury Credit | F70: FACEBK *Q5EMVXHD92 | I70: 3684 | J70: Ivan Amelong | K70: Advertising | P70: ############ | Q70: USD | T70: i@nexiu.ai | X70: 2026 | Y70: 2026 | Z70: 8 | AA70: 8 | AB70: 3 | AC70: =VLOOKUP($B70,Dictionary_v2!$B:$E,2,0) -> P&L | AD70: Recurring | AE70: =VLOOKUP($B70,Dictionary_v2!$B:$E,3,0) -> 2. Candidates Sourcing | AF70: =VLOOKUP(AE70,Dictionary_v2!R:S,2,0) -> 2. Candidates Sourcing | AG70: =VLOOKUP($B70,Dictionary_v2!$B:$E,4,0) -> 1. Social media | AH70: =if(C70>0,"In","Out") -> Out | AI70: =if(C70>0,"In","Out") -> Out
A71: 20/08/26 | B71: Intl. Transaction Fee | C71: -9.44 | D71: Sent | E71: Mercury Checking xx0301 | K71: FinancialInstitutionsAndFees | P71: ############ | X71: 2026 | Y71: 2026 | Z71: 8 | AA71: 8 | AB71: 3 | AC71: =VLOOKUP($B71,Dictionary_v2!$B:$E,2,0) -> P&L | AD71: Recurring | AE71: =VLOOKUP($B71,Dictionary_v2!$B:$E,3,0) -> 3. Platform | AF71: =VLOOKUP(AE71,Dictionary_v2!R:S,2,0) -> 3. Platform | AG71: =VLOOKUP($B71,Dictionary_v2!$B:$E,4,0) -> 2. Fixed | AH71: =if(C71>0,"In","Out") -> Out | AI71: =if(C71>0,"In","Out") -> Out
A72: 20/08/26 | B72: Hot Real Inn Tijuana | C72: -314.52 | D72: Sent | E72: Mercury Checking xx0301 | F72: HOT REAL INN TIJUANA | I72: 4376 | J72: Ivan Amelong | K72: Lodging | P72: ############ | Q72: MXN | T72: i@nexiu.ai | X72: 2026 | Y72: 2026 | Z72: 8 | AA72: 8 | AB72: 3 | AC72: =VLOOKUP($B72,Dictionary_v2!$B:$E,2,0) -> P&L | AD72: Recurring | AE72: =VLOOKUP($B72,Dictionary_v2!$B:$E,3,0) -> 5. Marketing | AF72: =VLOOKUP(AE72,Dictionary_v2!R:S,2,0) -> 5. Marketing | AG72: =VLOOKUP($B72,Dictionary_v2!$B:$E,4,0) -> 3. Events | AH72: =if(C72>0,"In","Out") -> Out | AI72: =if(C72>0,"In","Out") -> Out
A73: 20/08/26 | B73: Anthropic | C73: -90.01 | D73: Sent | E73: Mercury Credit | F73: ANTHROPIC | I73: 3684 | J73: Ivan Amelong | K73: Software | P73: ############ | Q73: USD | T73: i@nexiu.ai | X73: 2026 | Y73: 2026 | Z73: 8 | AA73: 8 | AB73: 3 | AC73: =VLOOKUP($B73,Dictionary_v2!$B:$E,2,0) -> P&L | AD73: Recurring | AE73: =VLOOKUP($B73,Dictionary_v2!$B:$E,3,0) -> 3. Platform | AF73: =VLOOKUP(AE73,Dictionary_v2!R:S,2,0) -> 3. Platform | AG73: =VLOOKUP($B73,Dictionary_v2!$B:$E,4,0) -> 1. Variable | AH73: =if(C73>0,"In","Out") -> Out | AI73: =if(C73>0,"In","Out") -> Out
A74: 20/08/26 | B74: Facebook | C74: -77 | D74: Sent | E74: Mercury Credit | F74: FACEBK *JEJPSXHD92 | I74: 3684 | J74: Ivan Amelong | K74: Advertising | P74: ############ | Q74: USD | T74: i@nexiu.ai | X74: 2026 | Y74: 2026 | Z74: 8 | AA74: 8 | AB74: 3 | AC74: =VLOOKUP($B74,Dictionary_v2!$B:$E,2,0) -> P&L | AD74: Recurring | AE74: =VLOOKUP($B74,Dictionary_v2!$B:$E,3,0) -> 2. Candidates Sourcing | AF74: =VLOOKUP(AE74,Dictionary_v2!R:S,2,0) -> 2. Candidates Sourcing | AG74: =VLOOKUP($B74,Dictionary_v2!$B:$E,4,0) -> 1. Social media | AH74: =if(C74>0,"In","Out") -> Out | AI74: =if(C74>0,"In","Out") -> Out
A75: 19/08/26 | B75: Anthropic | C75: -90.07 | D75: Sent | E75: Mercury Credit | F75: ANTHROPIC | I75: 3684 | J75: Ivan Amelong | K75: Software | P75: ############ | Q75: USD | T75: i@nexiu.ai | X75: 2026 | Y75: 2026 | Z75: 8 | AA75: 8 | AB75: 3 | AC75: =VLOOKUP($B75,Dictionary_v2!$B:$E,2,0) -> P&L | AD75: Recurring | AE75: =VLOOKUP($B75,Dictionary_v2!$B:$E,3,0) -> 3. Platform | AF75: =VLOOKUP(AE75,Dictionary_v2!R:S,2,0) -> 3. Platform | AG75: =VLOOKUP($B75,Dictionary_v2!$B:$E,4,0) -> 1. Variable | AH75: =if(C75>0,"In","Out") -> Out | AI75: =if(C75>0,"In","Out") -> Out
A76: 18/08/26 | B76: Facebook | C76: -77 | D76: Sent | E76: Mercury Credit | F76: FACEBK *JNURSXMD92 | I76: 3684 | J76: Ivan Amelong | K76: Advertising | P76: ############ | Q76: USD | T76: i@nexiu.ai | X76: 2026 | Y76: 2026 | Z76: 8 | AA76: 8 | AB76: 3 | AC76: =VLOOKUP($B76,Dictionary_v2!$B:$E,2,0) -> P&L | AD76: Recurring | AE76: =VLOOKUP($B76,Dictionary_v2!$B:$E,3,0) -> 2. Candidates Sourcing | AF76: =VLOOKUP(AE76,Dictionary_v2!R:S,2,0) -> 2. Candidates Sourcing | AG76: =VLOOKUP($B76,Dictionary_v2!$B:$E,4,0) -> 1. Social media | AH76: =if(C76>0,"In","Out") -> Out | AI76: =if(C76>0,"In","Out") -> Out
A77: 18/08/26 | B77: Cookiebot | C77: -34 | D77: Sent | E77: Mercury Credit | F77: COOKIEBOT | I77: 3684 | J77: Ivan Amelong | K77: Software | P77: ############ | Q77: USD | T77: i@nexiu.ai | X77: 2026 | Y77: 2026 | Z77: 8 | AA77: 8 | AB77: 3 | AC77: =VLOOKUP($B77,Dictionary_v2!$B:$E,2,0) -> P&L | AD77: Recurring | AE77: =VLOOKUP($B77,Dictionary_v2!$B:$E,3,0) -> 3. Platform | AF77: =VLOOKUP(AE77,Dictionary_v2!R:S,2,0) -> 3. Platform | AG77: =VLOOKUP($B77,Dictionary_v2!$B:$E,4,0) -> 2. Fixed | AH77: =if(C77>0,"In","Out") -> Out | AI77: =if(C77>0,"In","Out") -> Out
A78: 18/08/26 | B78: Anthropic | C78: -90.1 | D78: Sent | E78: Mercury Credit | F78: ANTHROPIC | I78: 3684 | J78: Ivan Amelong | K78: Software | P78: ############ | Q78: USD | T78: i@nexiu.ai | X78: 2026 | Y78: 2026 | Z78: 8 | AA78: 8 | AB78: 3 | AC78: =VLOOKUP($B78,Dictionary_v2!$B:$E,2,0) -> P&L | AD78: Recurring | AE78: =VLOOKUP($B78,Dictionary_v2!$B:$E,3,0) -> 3. Platform | AF78: =VLOOKUP(AE78,Dictionary_v2!R:S,2,0) -> 3. Platform | AG78: =VLOOKUP($B78,Dictionary_v2!$B:$E,4,0) -> 1. Variable | AH78: =if(C78>0,"In","Out") -> Out | AI78: =if(C78>0,"In","Out") -> Out
A79: 18/08/26 | B79: Facebook | C79: -24.06 | D79: Sent | E79: Mercury Credit | F79: FACEBK *PEHRK2NAR4 | I79: 3684 | J79: Ivan Amelong | K79: Advertising | P79: ############ | Q79: USD | T79: i@nexiu.ai | X79: 2026 | Y79: 2026 | Z79: 8 | AA79: 8 | AB79: 3 | AC79: =VLOOKUP($B79,Dictionary_v2!$B:$E,2,0) -> P&L | AD79: Recurring | AE79: =VLOOKUP($B79,Dictionary_v2!$B:$E,3,0) -> 2. Candidates Sourcing | AF79: =VLOOKUP(AE79,Dictionary_v2!R:S,2,0) -> 2. Candidates Sourcing | AG79: =VLOOKUP($B79,Dictionary_v2!$B:$E,4,0) -> 1. Social media | AH79: =if(C79>0,"In","Out") -> Out | AI79: =if(C79>0,"In","Out") -> Out
A80: 18/08/26 | B80: Facebook | C80: -1000 | D80: Sent | E80: Mercury Credit | F80: FACEBK *JEJ2F3SAR4 | I80: 3684 | J80: Ivan Amelong | K80: Advertising | P80: ############ | Q80: USD | T80: i@nexiu.ai | X80: 2026 | Y80: 2026 | Z80: 8 | AA80: 8 | AB80: 3 | AC80: =VLOOKUP($B80,Dictionary_v2!$B:$E,2,0) -> P&L | AD80: Recurring | AE80: =VLOOKUP($B80,Dictionary_v2!$B:$E,3,0) -> 2. Candidates Sourcing | AF80: =VLOOKUP(AE80,Dictionary_v2!R:S,2,0) -> 2. Candidates Sourcing | AG80: =VLOOKUP($B80,Dictionary_v2!$B:$E,4,0) -> 1. Social media | AH80: =if(C80>0,"In","Out") -> Out | AI80: =if(C80>0,"In","Out") -> Out
A81: 18/08/26 | B81: Intl. Transaction Fee | C81: -2.79 | D81: Sent | E81: Mercury Credit | K81: FinancialInstitutionsAndFees | P81: ############ | X81: 2026 | Y81: 2026 | Z81: 8 | AA81: 8 | AB81: 3 | AC81: =VLOOKUP($B81,Dictionary_v2!$B:$E,2,0) -> P&L | AD81: Recurring | AE81: =VLOOKUP($B81,Dictionary_v2!$B:$E,3,0) -> 3. Platform | AF81: =VLOOKUP(AE81,Dictionary_v2!R:S,2,0) -> 3. Platform | AG81: =VLOOKUP($B81,Dictionary_v2!$B:$E,4,0) -> 2. Fixed | AH81: =if(C81>0,"In","Out") -> Out | AI81: =if(C81>0,"In","Out") -> Out
A82: 18/08/26 | B82: LinkedIn | C82: -92.99 | D82: Sent | E82: Mercury Credit | F82: LinkedIn SN P307300290 | I82: 3684 | J82: Ivan Amelong | K82: Software | P82: ############ | Q82: MXN | T82: i@nexiu.ai | X82: 2026 | Y82: 2026 | Z82: 8 | AA82: 8 | AB82: 3 | AC82: =VLOOKUP($B82,Dictionary_v2!$B:$E,2,0) -> P&L | AD82: Recurring | AE82: =VLOOKUP($B82,Dictionary_v2!$B:$E,3,0) -> 2. Candidates Sourcing | AF82: =VLOOKUP(AE82,Dictionary_v2!R:S,2,0) -> 2. Candidates Sourcing | AG82: =VLOOKUP($B82,Dictionary_v2!$B:$E,4,0) -> 3. Linkedin | AH82: =if(C82>0,"In","Out") -> Out | AI82: =if(C82>0,"In","Out") -> Out
A83: 17/08/26 | B83: Lovable | C83: -25 | D83: Sent | E83: Mercury Credit | F83: LOVABLE | I83: 3684 | J83: Ivan Amelong | K83: Software | P83: ############ | Q83: USD | T83: i@nexiu.ai | X83: 2026 | Y83: 2026 | Z83: 8 | AA83: 8 | AB83: 3 | AC83: =VLOOKUP($B83,Dictionary_v2!$B:$E,2,0) -> P&L | AD83: Recurring | AE83: =VLOOKUP($B83,Dictionary_v2!$B:$E,3,0) -> 3. Platform | AF83: =VLOOKUP(AE83,Dictionary_v2!R:S,2,0) -> 3. Platform | AG83: =VLOOKUP($B83,Dictionary_v2!$B:$E,4,0) -> 2. Fixed | AH83: =if(C83>0,"In","Out") -> Out | AI83: =if(C83>0,"In","Out") -> Out
A84: 16/08/26 | B84: Facebook | C84: -77 | D84: Sent | E84: Mercury Credit | F84: FACEBK *7MFPRY5E92 | I84: 3684 | J84: Ivan Amelong | K84: Advertising | P84: ############ | Q84: USD | T84: i@nexiu.ai | X84: 2026 | Y84: 2026 | Z84: 8 | AA84: 8 | AB84: 3 | AC84: =VLOOKUP($B84,Dictionary_v2!$B:$E,2,0) -> P&L | AD84: Recurring | AE84: =VLOOKUP($B84,Dictionary_v2!$B:$E,3,0) -> 2. Candidates Sourcing | AF84: =VLOOKUP(AE84,Dictionary_v2!R:S,2,0) -> 2. Candidates Sourcing | AG84: =VLOOKUP($B84,Dictionary_v2!$B:$E,4,0) -> 1. Social media | AH84: =if(C84>0,"In","Out") -> Out | AI84: =if(C84>0,"In","Out") -> Out
A85: 16/08/26 | B85: Short.io | C85: -5 | D85: Sent | E85: Mercury Credit | F85: SHORT.IO* TRIAL OVER | I85: 3684 | J85: Ivan Amelong | K85: Software | P85: ############ | Q85: USD | T85: i@nexiu.ai | X85: 2026 | Y85: 2026 | Z85: 8 | AA85: 8 | AB85: 3 | AC85: =VLOOKUP($B85,Dictionary_v2!$B:$E,2,0) -> P&L | AD85: Recurring | AE85: =VLOOKUP($B85,Dictionary_v2!$B:$E,3,0) -> 3. Platform | AF85: =VLOOKUP(AE85,Dictionary_v2!R:S,2,0) -> 3. Platform | AG85: =VLOOKUP($B85,Dictionary_v2!$B:$E,4,0) -> 1. Variable | AH85: =if(C85>0,"In","Out") -> Out | AI85: =if(C85>0,"In","Out") -> Out
A86: 15/08/26 | B86: Facebook | C86: -651.2 | D86: Sent | E86: Mercury Credit | F86: FACEBK *5HWYZZHAR2 | I86: 3684 | J86: Ivan Amelong | K86: Advertising | P86: ############ | Q86: USD | T86: i@nexiu.ai | X86: 2026 | Y86: 2026 | Z86: 8 | AA86: 8 | AB86: 3 | AC86: =VLOOKUP($B86,Dictionary_v2!$B:$E,2,0) -> P&L | AD86: Recurring | AE86: =VLOOKUP($B86,Dictionary_v2!$B:$E,3,0) -> 2. Candidates Sourcing | AF86: =VLOOKUP(AE86,Dictionary_v2!R:S,2,0) -> 2. Candidates Sourcing | AG86: =VLOOKUP($B86,Dictionary_v2!$B:$E,4,0) -> 1. Social media | AH86: =if(C86>0,"In","Out") -> Out | AI86: =if(C86>0,"In","Out") -> Out
A87: 15/08/26 | B87: Facebook | C87: -1.03 | D87: Sent | E87: Mercury Credit | F87: FACEBOOKAD* C3PPD4JAR4 | I87: 3684 | J87: Ivan Amelong | K87: Advertising | P87: ############ | Q87: USD | T87: i@nexiu.ai | X87: 2026 | Y87: 2026 | Z87: 8 | AA87: 8 | AB87: 3 | AC87: =VLOOKUP($B87,Dictionary_v2!$B:$E,2,0) -> P&L | AD87: Recurring | AE87: =VLOOKUP($B87,Dictionary_v2!$B:$E,3,0) -> 2. Candidates Sourcing | AF87: =VLOOKUP(AE87,Dictionary_v2!R:S,2,0) -> 2. Candidates Sourcing | AG87: =VLOOKUP($B87,Dictionary_v2!$B:$E,4,0) -> 1. Social media | AH87: =if(C87>0,"In","Out") -> Out | AI87: =if(C87>0,"In","Out") -> Out
A88: 14/08/26 | B88: Facebook | C88: 0 | D88: Failed | E88: Mercury Credit | F88: FACEBK *JVGC236AR4 | I88: 3684 | J88: Ivan Amelong | K88: Advertising | P88: ############ | Q88: USD | T88: i@nexiu.ai | V88: The merchant canceled this transaction, possibly due to incorrect billing information. | X88: 2026 | Y88: 2026 | Z88: 8 | AA88: 8 | AB88: 3 | AC88: =VLOOKUP($B88,Dictionary_v2!$B:$E,2,0) -> P&L | AD88: Recurring | AE88: =VLOOKUP($B88,Dictionary_v2!$B:$E,3,0) -> 2. Candidates Sourcing | AF88: =VLOOKUP(AE88,Dictionary_v2!R:S,2,0) -> 2. Candidates Sourcing | AG88: =VLOOKUP($B88,Dictionary_v2!$B:$E,4,0) -> 1. Social media | AH88: =if(C88>0,"In","Out") -> Out | AI88: =if(C88>0,"In","Out") -> Out
A89: 14/08/26 | B89: Facebook | C89: 0 | D89: Failed | E89: Mercury Credit | F89: FACEBK *DZ6A43SAR4 | I89: 3684 | J89: Ivan Amelong | K89: Advertising | P89: ############ | Q89: USD | T89: i@nexiu.ai | V89: The merchant canceled this transaction, possibly due to incorrect billing information. | X89: 2026 | Y89: 2026 | Z89: 8 | AA89: 8 | AB89: 3 | AC89: =VLOOKUP($B89,Dictionary_v2!$B:$E,2,0) -> P&L | AD89: Recurring | AE89: =VLOOKUP($B89,Dictionary_v2!$B:$E,3,0) -> 2. Candidates Sourcing | AF89: =VLOOKUP(AE89,Dictionary_v2!R:S,2,0) -> 2. Candidates Sourcing | AG89: =VLOOKUP($B89,Dictionary_v2!$B:$E,4,0) -> 1. Social media | AH89: =if(C89>0,"In","Out") -> Out | AI89: =if(C89>0,"In","Out") -> Out
A90: 14/08/26 | B90: Facebook | C90: -77 | D90: Sent | E90: Mercury Credit | F90: FACEBK *NJKFHY5E92 | I90: 3684 | J90: Ivan Amelong | K90: Advertising | P90: ############ | Q90: USD | T90: i@nexiu.ai | X90: 2026 | Y90: 2026 | Z90: 8 | AA90: 8 | AB90: 3 | AC90: =VLOOKUP($B90,Dictionary_v2!$B:$E,2,0) -> P&L | AD90: Recurring | AE90: =VLOOKUP($B90,Dictionary_v2!$B:$E,3,0) -> 2. Candidates Sourcing | AF90: =VLOOKUP(AE90,Dictionary_v2!R:S,2,0) -> 2. Candidates Sourcing | AG90: =VLOOKUP($B90,Dictionary_v2!$B:$E,4,0) -> 1. Social media | AH90: =if(C90>0,"In","Out") -> Out | AI90: =if(C90>0,"In","Out") -> Out
A91: 13/08/26 | B91: Facebook | C91: -6.85 | D91: Sent | E91: Mercury Credit | F91: FACEBK *LSAA4X9E92 | I91: 3684 | J91: Ivan Amelong | K91: Advertising | P91: ############ | Q91: USD | T91: i@nexiu.ai | X91: 2026 | Y91: 2026 | Z91: 8 | AA91: 8 | AB91: 3 | AC91: =VLOOKUP($B91,Dictionary_v2!$B:$E,2,0) -> P&L | AD91: Recurring | AE91: =VLOOKUP($B91,Dictionary_v2!$B:$E,3,0) -> 2. Candidates Sourcing | AF91: =VLOOKUP(AE91,Dictionary_v2!R:S,2,0) -> 2. Candidates Sourcing | AG91: =VLOOKUP($B91,Dictionary_v2!$B:$E,4,0) -> 1. Social media | AH91: =if(C91>0,"In","Out") -> Out | AI91: =if(C91>0,"In","Out") -> Out
A92: 13/08/26 | B92: Recall | C92: -10.29 | D92: Sent | E92: Mercury Credit | F92: RECALL.AI | I92: 3684 | J92: Ivan Amelong | K92: Software | P92: ############ | Q92: USD | T92: i@nexiu.ai | X92: 2026 | Y92: 2026 | Z92: 8 | AA92: 8 | AB92: 3 | AC92: =VLOOKUP($B92,Dictionary_v2!$B:$E,2,0) -> P&L | AD92: Recurring | AE92: =VLOOKUP($B92,Dictionary_v2!$B:$E,3,0) -> 3. Platform | AF92: =VLOOKUP(AE92,Dictionary_v2!R:S,2,0) -> 3. Platform | AG92: =VLOOKUP($B92,Dictionary_v2!$B:$E,4,0) -> 2. Fixed | AH92: =if(C92>0,"In","Out") -> Out | AI92: =if(C92>0,"In","Out") -> Out
A93: 13/08/26 | B93: LinkedIn | C93: -105.5 | D93: Sent | E93: Mercury Credit | F93: LinkedIn P3069547974 | I93: 3684 | J93: Ivan Amelong | K93: Software | P93: ############ | Q93: USD | T93: i@nexiu.ai | X93: 2026 | Y93: 2026 | Z93: 8 | AA93: 8 | AB93: 3 | AC93: =VLOOKUP($B93,Dictionary_v2!$B:$E,2,0) -> P&L | AD93: Recurring | AE93: =VLOOKUP($B93,Dictionary_v2!$B:$E,3,0) -> 2. Candidates Sourcing | AF93: =VLOOKUP(AE93,Dictionary_v2!R:S,2,0) -> 2. Candidates Sourcing | AG93: =VLOOKUP($B93,Dictionary_v2!$B:$E,4,0) -> 3. Linkedin | AH93: =if(C93>0,"In","Out") -> Out | AI93: =if(C93>0,"In","Out") -> Out
A94: 46364 | B94: Facebook | C94: -77 | D94: Sent | E94: Mercury Credit | F94: FACEBK *EBSB9Y5E92 | I94: 3684 | J94: Ivan Amelong | K94: Advertising | P94: ############ | Q94: USD | T94: i@nexiu.ai | X94: 2026 | Y94: 2026 | Z94: 8 | AA94: 8 | AB94: 3 | AC94: =VLOOKUP($B94,Dictionary_v2!$B:$E,2,0) -> P&L | AD94: Recurring | AE94: =VLOOKUP($B94,Dictionary_v2!$B:$E,3,0) -> 2. Candidates Sourcing | AF94: =VLOOKUP(AE94,Dictionary_v2!R:S,2,0) -> 2. Candidates Sourcing | AG94: =VLOOKUP($B94,Dictionary_v2!$B:$E,4,0) -> 1. Social media | AH94: =if(C94>0,"In","Out") -> Out | AI94: =if(C94>0,"In","Out") -> Out
A95: 46364 | B95: Metapay | C95: -9.61 | D95: Sent | E95: Mercury Credit | F95: METAPAY*MV4B | I95: 9691 | J95: Ivan Amelong | K95: FinancialInstitutionsAndFees | P95: ############ | Q95: MXN | T95: i@nexiu.ai | X95: 2026 | Y95: 2026 | Z95: 8 | AA95: 8 | AB95: 3 | AC95: =VLOOKUP($B95,Dictionary_v2!$B:$E,2,0) -> P&L | AD95: Recurring | AE95: =VLOOKUP($B95,Dictionary_v2!$B:$E,3,0) -> 3. Platform | AF95: =VLOOKUP(AE95,Dictionary_v2!R:S,2,0) -> 3. Platform | AG95: =VLOOKUP($B95,Dictionary_v2!$B:$E,4,0) -> 2. Fixed | AH95: =if(C95>0,"In","Out") -> Out | AI95: =if(C95>0,"In","Out") -> Out
A96: 46364 | B96: Intl. Transaction Fee | C96: -0.29 | D96: Sent | E96: Mercury Credit | K96: FinancialInstitutionsAndFees | P96: ############ | X96: 2026 | Y96: 2026 | Z96: 8 | AA96: 8 | AB96: 3 | AC96: =VLOOKUP($B96,Dictionary_v2!$B:$E,2,0) -> P&L | AD96: Recurring | AE96: =VLOOKUP($B96,Dictionary_v2!$B:$E,3,0) -> 3. Platform | AF96: =VLOOKUP(AE96,Dictionary_v2!R:S,2,0) -> 3. Platform | AG96: =VLOOKUP($B96,Dictionary_v2!$B:$E,4,0) -> 2. Fixed | AH96: =if(C96>0,"In","Out") -> Out | AI96: =if(C96>0,"In","Out") -> Out
A97: 46364 | B97: Facebook | C97: -578.08 | D97: Sent | E97: Mercury Credit | F97: FACEBOOKAD* AV5Q72WAR4 | I97: 3684 | J97: Ivan Amelong | K97: Advertising | P97: ############ | Q97: USD | T97: i@nexiu.ai | X97: 2026 | Y97: 2026 | Z97: 8 | AA97: 8 | AB97: 3 | AC97: =VLOOKUP($B97,Dictionary_v2!$B:$E,2,0) -> P&L | AD97: Recurring | AE97: =VLOOKUP($B97,Dictionary_v2!$B:$E,3,0) -> 2. Candidates Sourcing | AF97: =VLOOKUP(AE97,Dictionary_v2!R:S,2,0) -> 2. Candidates Sourcing | AG97: =VLOOKUP($B97,Dictionary_v2!$B:$E,4,0) -> 1. Social media | AH97: =if(C97>0,"In","Out") -> Out | AI97: =if(C97>0,"In","Out") -> Out
A98: 46364 | B98: Facebook | C98: -3.47 | D98: Sent | E98: Mercury Credit | F98: FACEBK *9L2SDZRAR2 | I98: 3684 | J98: Ivan Amelong | K98: Advertising | P98: ############ | Q98: USD | T98: i@nexiu.ai | X98: 2026 | Y98: 2026 | Z98: 8 | AA98: 8 | AB98: 3 | AC98: =VLOOKUP($B98,Dictionary_v2!$B:$E,2,0) -> P&L | AD98: Recurring | AE98: =VLOOKUP($B98,Dictionary_v2!$B:$E,3,0) -> 2. Candidates Sourcing | AF98: =VLOOKUP(AE98,Dictionary_v2!R:S,2,0) -> 2. Candidates Sourcing | AG98: =VLOOKUP($B98,Dictionary_v2!$B:$E,4,0) -> 1. Social media | AH98: =if(C98>0,"In","Out") -> Out | AI98: =if(C98>0,"In","Out") -> Out
A99: 46364 | B99: STRIPE | C99: -21.9 | D99: Failed | E99: Mercury Checking xx8107 | F99: STRIPE; TRANSFER; NEXIU AI LLC | P99: ############ | U99: 91000012513967 | V99: Insufficient funds | X99: 2026 | Y99: 2026 | Z99: 8 | AA99: 8 | AB99: 3 | AC99: =VLOOKUP($B99,Dictionary_v2!$B:$E,2,0) -> P&L | AD99: Recurring | AE99: =VLOOKUP($B99,Dictionary_v2!$B:$E,3,0) -> 8. Other fixed costs | AF99: =VLOOKUP(AE99,Dictionary_v2!R:S,2,0) -> 6. Other fixed and admin | AG99: =VLOOKUP($B99,Dictionary_v2!$B:$E,4,0) -> 2. Admin | AH99: =if(C99>0,"In","Out") -> Out | AI99: =if(C99>0,"In","Out") -> Out
A100: 46303 | B100: LatAm Talent (LatAm Talent & Recruitment Solutions) | C100: -2000 | D100: Sent | E100: Mercury Checking xx0301 | F100: Send Money transaction initiated on Mercury | G100: From Nexiu AI, LLC via mercury.com | P100: ############ | U100: 121145431493858 | X100: 2026 | Y100: 2026 | Z100: 8 | AA100: 8 | AB100: 3 | AC100: =VLOOKUP($B100,Dictionary_v2!$B:$E,2,0) -> Intercompany | AD100: Recurring | AE100: =VLOOKUP($B100,Dictionary_v2!$B:$E,3,0) | AG100: =VLOOKUP($B100,Dictionary_v2!$B:$E,4,0) | AH100: =if(C100>0,"In","Out") -> Out | AI100: =if(C100>0,"In","Out") -> Out
A101: 46303 | B101: Facebook | C101: -77 | D101: Sent | E101: Mercury Credit | F101: FACEBK *UJZCZX5E92 | I101: 3684 | J101: Ivan Amelong | K101: Advertising | P101: ############ | Q101: USD | T101: i@nexiu.ai | X101: 2026 | Y101: 2026 | Z101: 8 | AA101: 8 | AB101: 3 | AC101: =VLOOKUP($B101,Dictionary_v2!$B:$E,2,0) -> P&L | AD101: Recurring | AE101: =VLOOKUP($B101,Dictionary_v2!$B:$E,3,0) -> 2. Candidates Sourcing | AF101: =VLOOKUP(AE101,Dictionary_v2!R:S,2,0) -> 2. Candidates Sourcing | AG101: =VLOOKUP($B101,Dictionary_v2!$B:$E,4,0) -> 1. Social media | AH101: =if(C101>0,"In","Out") -> Out | AI101: =if(C101>0,"In","Out") -> Out
...

Sheet Ajustes Manuales cada mes
B2: 1 | C2: Facebook, card 2354 ---> | D2: 3. Platform | E2: 3. Platform | F2: 3. Messaging
B3: 2 | C3: Anthropic, 200 USD | D3: 6. Tech salaries | E3: 6. Other fixed and admin | F3: 1. Salaries

Sheet DolarApp
A1: created_on | B1: transaction_type | C1: transaction_state | D1: name | E1: description | F1: local_amount | G1: local_currency | H1: fx_rate | I1: base_amount | J1: base_currency | K1: fee_amount | L1: fee_currency | M1: adjustment_amount | N1: adjustment_currency | O1: post_transaction_balance | P1: card_last_four | Q1: cardholder_name | R1: merchant_category | S1: completed_at | T1: Year | U1: Month | V1: Quarter | W1: Statement | X1: Type 1 | Y1: Type 2 | Z1: Type 2_B | AA1: Type 3 | AB1: Type 4 | AC1: Status
A2: 46262.959 | B2: WITHDRAW | C2: COMPLETED | D2: Ivan Amelong | E2: Agosto 2026 | F2: -14311.45 | G2: MXN | H2: 17.0196 | I2: -840.88 | J2: USDC | K2: 0 | L2: USDC | M2: 0 | N2: USDC | O2: 869.14 | P2: XXXX | Q2: XXXX | R2: XXXX | S2: 46262.959 | T2: =YEAR(A2) -> 2026 | U2: =MONTH(A2) -> 8 | V2: =VLOOKUP(U2,Dictionary_v2!$O$3:$P$15,2,0) -> 3 | W2: =VLOOKUP($D2,Dictionary_v2!$G:$J,2,0) -> P&L | X2: Recurring | Y2: =VLOOKUP($D2,Dictionary_v2!$G:$J,3,0) -> 7. Founders | Z2: =VLOOKUP(Y2,Dictionary_v2!R:S,2,0) -> 6. Other fixed and admin | AA2: =VLOOKUP($D2,Dictionary_v2!$G:$J,4,0) -> 1. Salaries | AB2: =if(F2>0,"In","Out") -> Out | AC2: =VLOOKUP(C2,Dictionary_v2!L:M,2,0) -> Sent
A3: 46262.959 | B3: WITHDRAW | C3: COMPLETED | D3: Federico David Naides | E3: Agosto 2026 | F3: -14311.45 | G3: MXN | H3: 17.0196 | I3: -840.88 | J3: USDC | K3: 0 | L3: USDC | M3: 0 | N3: USDC | O3: 1710.02 | P3: XXXX | Q3: XXXX | R3: XXXX | S3: 46262.959 | T3: =YEAR(A3) -> 2026 | U3: =MONTH(A3) -> 8 | V3: =VLOOKUP(U3,Dictionary_v2!$O$3:$P$15,2,0) -> 3 | W3: =VLOOKUP($D3,Dictionary_v2!$G:$J,2,0) -> P&L | X3: Recurring | Y3: =VLOOKUP($D3,Dictionary_v2!$G:$J,3,0) -> 7. Founders | Z3: =VLOOKUP(Y3,Dictionary_v2!R:S,2,0) -> 6. Other fixed and admin | AA3: =VLOOKUP($D3,Dictionary_v2!$G:$J,4,0) -> 1. Salaries | AB3: =if(F3>0,"In","Out") -> Out | AC3: =VLOOKUP(C3,Dictionary_v2!L:M,2,0) -> Sent
A4: 46261.695 | B4: CARD_PAYMENT | C4: COMPLETED | D4: Www.mirlo.mx Mexico | E4: WWW.MIRLO.MX | F4: -40.81 | G4: MXN | H4: 16.9656 | I4: -2.41 | J4: USDC | K4: 0 | L4: USDC | M4: 0 | N4: USDC | O4: 869.14 | P4: 2535 | Q4: Ivan Amelong | R4: SERVICES | S4: 46263.375 | T4: =YEAR(A4) -> 2026 | U4: =MONTH(A4) -> 8 | V4: =VLOOKUP(U4,Dictionary_v2!$O$3:$P$15,2,0) -> 3 | W4: =VLOOKUP($D4,Dictionary_v2!$G:$J,2,0) -> P&L | X4: Recurring | Y4: =VLOOKUP($D4,Dictionary_v2!$G:$J,3,0) -> 3. Platform | Z4: =VLOOKUP(Y4,Dictionary_v2!R:S,2,0) -> 3. Platform | AA4: =VLOOKUP($D4,Dictionary_v2!$G:$J,4,0) -> 1. Variable | AB4: =if(F4>0,"In","Out") -> Out | AC4: =VLOOKUP(C4,Dictionary_v2!L:M,2,0) -> Sent
A5: 46255.95 | B5: WITHDRAW | C5: COMPLETED | D5: Nadia Meline Karaguezian | E5: Impuestos Jul 26 | F5: -4171 | G5: MXN | H5: 16.9059 | I5: -246.72 | J5: USDC | K5: 0 | L5: USDC | M5: 0 | N5: USDC | O5: 2553.31 | P5: XXXX | Q5: XXXX | R5: XXXX | S5: 46255.95 | T5: =YEAR(A5) -> 2026 | U5: =MONTH(A5) -> 8 | V5: =VLOOKUP(U5,Dictionary_v2!$O$3:$P$15,2,0) -> 3 | W5: =VLOOKUP($D5,Dictionary_v2!$G:$J,2,0) -> P&L | X5: Recurring | Y5: =VLOOKUP($D5,Dictionary_v2!$G:$J,3,0) -> 8. Other fixed costs | Z5: =VLOOKUP(Y5,Dictionary_v2!R:S,2,0) -> 6. Other fixed and admin | AA5: =VLOOKUP($D5,Dictionary_v2!$G:$J,4,0) -> 4. Taxes | AB5: =if(F5>0,"In","Out") -> Out | AC5: =VLOOKUP(C5,Dictionary_v2!L:M,2,0) -> Sent
A6: 46255.799 | B6: DEPOSIT | C6: COMPLETED | D6: KEKO MOBILITY SA DE CV | E6: Pago Reclutamiento Nexiu 371 DyA ML | F6: 30160 | G6: MXN | H6: 16.9282 | I6: 1781.64 | J6: USDC | K6: 0 | L6: USDC | M6: 0 | N6: USDC | O6: 2800.03 | P6: XXXX | Q6: XXXX | R6: XXXX | S6: 46255.799 | T6: =YEAR(A6) -> 2026 | U6: =MONTH(A6) -> 8 | V6: =VLOOKUP(U6,Dictionary_v2!$O$3:$P$15,2,0) -> 3 | W6: =VLOOKUP($D6,Dictionary_v2!$G:$J,2,0) -> P&L | X6: Recurring | Y6: =VLOOKUP($D6,Dictionary_v2!$G:$J,3,0) -> 1. Collections | Z6: =VLOOKUP(Y6,Dictionary_v2!R:S,2,0) -> 1. Collections | AA6: =VLOOKUP($D6,Dictionary_v2!$G:$J,4,0) -> 1. Full Stack | AB6: =if(F6>0,"In","Out") -> In | AC6: =VLOOKUP(C6,Dictionary_v2!L:M,2,0) -> Sent
A7: 46253.731 | B7: WITHDRAW | C7: COMPLETED | D7: Gloria L Guzman M | F7: -1741.5 | G7: MXN | H7: 16.9668 | I7: -102.64 | J7: USDC | K7: 0 | L7: USDC | M7: 0 | N7: USDC | O7: 1018.38 | P7: XXXX | Q7: XXXX | R7: XXXX | S7: 46253.731 | T7: =YEAR(A7) -> 2026 | U7: =MONTH(A7) -> 8 | V7: =VLOOKUP(U7,Dictionary_v2!$O$3:$P$15,2,0) -> 3 | W7: =VLOOKUP($D7,Dictionary_v2!$G:$J,2,0) -> P&L | X7: Recurring | Y7: =VLOOKUP($D7,Dictionary_v2!$G:$J,3,0) -> 1. Collections | Z7: =VLOOKUP(Y7,Dictionary_v2!R:S,2,0) -> 1. Collections | AA7: =VLOOKUP($D7,Dictionary_v2!$G:$J,4,0) -> 2. SaaS | AB7: =if(F7>0,"In","Out") -> Out | AC7: =VLOOKUP(C7,Dictionary_v2!L:M,2,0) -> Sent
A8: 46253.647 | B8: CARD_PAYMENT | C8: COMPLETED | D8: Www.mirlo.mx Mexico | E8: WWW.MIRLO.MX | F8: -74.1 | G8: MXN | H8: 16.9666 | I8: -4.37 | J8: USDC | K8: 0 | L8: USDC | M8: 0 | N8: USDC | O8: 1018.38 | P8: 2535 | Q8: Ivan Amelong | R8: SERVICES | S8: 46255.375 | T8: =YEAR(A8) -> 2026 | U8: =MONTH(A8) -> 8 | V8: =VLOOKUP(U8,Dictionary_v2!$O$3:$P$15,2,0) -> 3 | W8: =VLOOKUP($D8,Dictionary_v2!$G:$J,2,0) -> P&L | X8: Recurring | Y8: =VLOOKUP($D8,Dictionary_v2!$G:$J,3,0) -> 3. Platform | Z8: =VLOOKUP(Y8,Dictionary_v2!R:S,2,0) -> 3. Platform | AA8: =VLOOKUP($D8,Dictionary_v2!$G:$J,4,0) -> 1. Variable | AB8: =if(F8>0,"In","Out") -> Out | AC8: =VLOOKUP(C8,Dictionary_v2!L:M,2,0) -> Sent
A9: 46252.98 | B9: CARD_PAYMENT | C9: COMPLETED | D9: Www.mirlo.mx Mexico | E9: WWW.MIRLO.MX | F9: -78.26 | G9: MXN | H9: 17.0638 | I9: -4.59 | J9: USDC | K9: 0 | L9: USDC | M9: 0 | N9: USDC | O9: 1018.38 | P9: 2535 | Q9: Ivan Amelong | R9: SERVICES | S9: 46254.375 | T9: =YEAR(A9) -> 2026 | U9: =MONTH(A9) -> 8 | V9: =VLOOKUP(U9,Dictionary_v2!$O$3:$P$15,2,0) -> 3 | W9: =VLOOKUP($D9,Dictionary_v2!$G:$J,2,0) -> P&L | X9: Recurring | Y9: =VLOOKUP($D9,Dictionary_v2!$G:$J,3,0) -> 3. Platform | Z9: =VLOOKUP(Y9,Dictionary_v2!R:S,2,0) -> 3. Platform | AA9: =VLOOKUP($D9,Dictionary_v2!$G:$J,4,0) -> 1. Variable | AB9: =if(F9>0,"In","Out") -> Out | AC9: =VLOOKUP(C9,Dictionary_v2!L:M,2,0) -> Sent
A10: 46247.897 | B10: WITHDRAW | C10: COMPLETED | D10: Gloria L Guzman M | E10: Material Congreso AMESP | F10: -1741.5 | G10: MXN | H10: 17.0207 | I10: -102.32 | J10: USDC | K10: 0 | L10: USDC | M10: 0 | N10: USDC | O10: 1129.98 | P10: XXXX | Q10: XXXX | R10: XXXX | S10: 46247.897 | T10: =YEAR(A10) -> 2026 | U10: =MONTH(A10) -> 8 | V10: =VLOOKUP(U10,Dictionary_v2!$O$3:$P$15,2,0) -> 3 | W10: =VLOOKUP($D10,Dictionary_v2!$G:$J,2,0) -> P&L | X10: Recurring | Y10: =VLOOKUP($D10,Dictionary_v2!$G:$J,3,0) -> 1. Collections | Z10: =VLOOKUP(Y10,Dictionary_v2!R:S,2,0) -> 1. Collections | AA10: =VLOOKUP($D10,Dictionary_v2!$G:$J,4,0) -> 2. SaaS | AB10: =if(F10>0,"In","Out") -> Out | AC10: =VLOOKUP(C10,Dictionary_v2!L:M,2,0) -> Sent
A11: 46245.798 | B11: WITHDRAW | C11: COMPLETED | D11: AMESP Asociacion Mexicana de Empresas de Seguridad Privada | E11: 2do-congreso-seguridad-nexiu | F11: -25000 | G11: MXN | H11: 17.086 | I11: -1463.18 | J11: USDC | K11: 0 | L11: USDC | M11: 0 | N11: USDC | O11: 1232.3 | P11: XXXX | Q11: XXXX | R11: XXXX | S11: 46245.798 | T11: =YEAR(A11) -> 2026 | U11: =MONTH(A11) -> 8 | V11: =VLOOKUP(U11,Dictionary_v2!$O$3:$P$15,2,0) -> 3 | W11: =VLOOKUP($D11,Dictionary_v2!$G:$J,2,0) -> P&L | X11: Recurring | Y11: =VLOOKUP($D11,Dictionary_v2!$G:$J,3,0) -> 5. Marketing | Z11: =VLOOKUP(Y11,Dictionary_v2!R:S,2,0) -> 5. Marketing | AA11: =VLOOKUP($D11,Dictionary_v2!$G:$J,4,0) -> 3. Events | AB11: =if(F11>0,"In","Out") -> Out | AC11: =VLOOKUP(C11,Dictionary_v2!L:M,2,0) -> Sent
A12: 46245.542 | B12: DEPOSIT | C12: COMPLETED | D12: NEXIU AI LLC | E12: PAYMENT NEXIU AI LLC MRCR-QZ09MPAY7F [LatAm Talent & Recruit] From Nexiu AI, LLC via mercury.com | F12: 2000 | G12: USD | H12: 1 | I12: 2000 | J12: USDC | K12: 0 | L12: USDC | M12: 0 | N12: USDC | O12: 2695.48 | P12: XXXX | Q12: XXXX | R12: XXXX | S12: 46245.542 | T12: =YEAR(A12) -> 2026 | U12: =MONTH(A12) -> 8 | V12: =VLOOKUP(U12,Dictionary_v2!$O$3:$P$15,2,0) -> 3 | W12: =VLOOKUP($D12,Dictionary_v2!$G:$J,2,0) -> BS | X12: Recurring | Y12: =VLOOKUP($D12,Dictionary_v2!$G:$J,3,0) -> 0. Investments | Z12: =VLOOKUP(Y12,Dictionary_v2!R:S,2,0) -> 0. Investments | AA12: =VLOOKUP($D12,Dictionary_v2!$G:$J,4,0) -> 4. Intercompany | AB12: =if(F12>0,"In","Out") -> In | AC12: =VLOOKUP(C12,Dictionary_v2!L:M,2,0) -> Sent
A13: 46244.866 | B13: CARD_PAYMENT | C13: COMPLETED | D13: Viva Aerobus Apo | E13: Viva Aerobus | F13: -5771.81 | G13: MXN | H13: 17.1385 | I13: -336.78 | J13: USDC | K13: 0 | L13: USDC | M13: 0 | N13: USDC | O13: 1232.3 | P13: 2535 | Q13: Ivan Amelong | R13: TRAVEL | S13: 46246.375 | T13: =YEAR(A13) -> 2026 | U13: =MONTH(A13) -> 8 | V13: =VLOOKUP(U13,Dictionary_v2!$O$3:$P$15,2,0) -> 3 | W13: =VLOOKUP($D13,Dictionary_v2!$G:$J,2,0) -> P&L | X13: Recurring | Y13: =VLOOKUP($D13,Dictionary_v2!$G:$J,3,0) -> 5. Marketing | Z13: =VLOOKUP(Y13,Dictionary_v2!R:S,2,0) -> 5. Marketing | AA13: =VLOOKUP($D13,Dictionary_v2!$G:$J,4,0) -> 3. Events | AB13: =if(F13>0,"In","Out") -> Out | AC13: =VLOOKUP(C13,Dictionary_v2!L:M,2,0) -> Sent
A14: 46244.664 | B14: CARD_PAYMENT | C14: COMPLETED | D14: Www.mirlo.mx Mexico | E14: WWW.MIRLO.MX | F14: -111.55 | G14: MXN | H14: 17.1368 | I14: -6.51 | J14: USDC | K14: 0 | L14: USDC | M14: 0 | N14: USDC | O14: 1232.3 | P14: 2535 | Q14: Ivan Amelong | R14: SERVICES | S14: 46246.375 | T14: =YEAR(A14) -> 2026 | U14: =MONTH(A14) -> 8 | V14: =VLOOKUP(U14,Dictionary_v2!$O$3:$P$15,2,0) -> 3 | W14: =VLOOKUP($D14,Dictionary_v2!$G:$J,2,0) -> P&L | X14: Recurring | Y14: =VLOOKUP($D14,Dictionary_v2!$G:$J,3,0) -> 3. Platform | Z14: =VLOOKUP(Y14,Dictionary_v2!R:S,2,0) -> 3. Platform | AA14: =VLOOKUP($D14,Dictionary_v2!$G:$J,4,0) -> 1. Variable | AB14: =if(F14>0,"In","Out") -> Out | AC14: =VLOOKUP(C14,Dictionary_v2!L:M,2,0) -> Sent
A15: 46242.024 | B15: CARD_PAYMENT | C15: COMPLETED | D15: Www.mirlo.mx Mexico | E15: WWW.MIRLO.MX | F15: -119.87 | G15: MXN | H15: 17.1212 | I15: -7 | J15: USDC | K15: 0 | L15: USDC | M15: 0 | N15: USDC | O15: 1038.77 | P15: 2535 | Q15: Ivan Amelong | R15: SERVICES | S15: 46243.375 | T15: =YEAR(A15) -> 2026 | U15: =MONTH(A15) -> 8 | V15: =VLOOKUP(U15,Dictionary_v2!$O$3:$P$15,2,0) -> 3 | W15: =VLOOKUP($D15,Dictionary_v2!$G:$J,2,0) -> P&L | X15: Recurring | Y15: =VLOOKUP($D15,Dictionary_v2!$G:$J,3,0) -> 3. Platform | Z15: =VLOOKUP(Y15,Dictionary_v2!R:S,2,0) -> 3. Platform | AA15: =VLOOKUP($D15,Dictionary_v2!$G:$J,4,0) -> 1. Variable | AB15: =if(F15>0,"In","Out") -> Out | AC15: =VLOOKUP(C15,Dictionary_v2!L:M,2,0) -> Sent
A16: 46241.993 | B16: DEPOSIT | C16: COMPLETED | D16: AZUCENA DANAE MORALES MARTINEZ | E16: Pago LaTam Talent and Recruitment | F16: 12062 | G16: MXN | H16: 17.1512 | I16: 703.27 | J16: USDC | K16: 0 | L16: USDC | M16: 0 | N16: USDC | O16: 1045.77 | P16: XXXX | Q16: XXXX | R16: XXXX | S16: 46241.993 | T16: =YEAR(A16) -> 2026 | U16: =MONTH(A16) -> 8 | V16: =VLOOKUP(U16,Dictionary_v2!$O$3:$P$15,2,0) -> 3 | W16: =VLOOKUP($D16,Dictionary_v2!$G:$J,2,0) -> P&L | X16: Recurring | Y16: =VLOOKUP($D16,Dictionary_v2!$G:$J,3,0) -> 1. Collections | Z16: =VLOOKUP(Y16,Dictionary_v2!R:S,2,0) -> 1. Collections | AA16: =VLOOKUP($D16,Dictionary_v2!$G:$J,4,0) -> 2. SaaS | AB16: =if(F16>0,"In","Out") -> In | AC16: =VLOOKUP(C16,Dictionary_v2!L:M,2,0) -> Sent
A17: 46241.983 | B17: DEPOSIT | C17: COMPLETED | D17: AZUCENA DANAE MORALES MARTINEZ | E17: Validaci√≥n cuenta LatAm Talent | F17: 1 | G17: MXN | H17: 17.1512 | I17: 0.06 | J17: USDC | K17: 0 | L17: USDC | M17: 0 | N17: USDC | O17: 342.49 | P17: XXXX | Q17: XXXX | R17: XXXX | S17: 46241.983 | T17: =YEAR(A17) -> 2026 | U17: =MONTH(A17) -> 8 | V17: =VLOOKUP(U17,Dictionary_v2!$O$3:$P$15,2,0) -> 3 | W17: =VLOOKUP($D17,Dictionary_v2!$G:$J,2,0) -> P&L | X17: Recurring | Y17: =VLOOKUP($D17,Dictionary_v2!$G:$J,3,0) -> 1. Collections | Z17: =VLOOKUP(Y17,Dictionary_v2!R:S,2,0) -> 1. Collections | AA17: =VLOOKUP($D17,Dictionary_v2!$G:$J,4,0) -> 2. SaaS | AB17: =if(F17>0,"In","Out") -> In | AC17: =VLOOKUP(C17,Dictionary_v2!L:M,2,0) -> Sent
A18: 46240.858 | B18: WITHDRAW | C18: COMPLETED | D18: WeWork Mexico Co S. de R.L. de C.V | E18: Agosto 26 | F18: -10604.72 | G18: MXN | H18: 17.2091 | I18: -616.23 | J18: USDC | K18: 0 | L18: USDC | M18: 0 | N18: USDC | O18: 342.43 | P18: XXXX | Q18: XXXX | R18: XXXX | S18: 46240.858 | T18: =YEAR(A18) -> 2026 | U18: =MONTH(A18) -> 8 | V18: =VLOOKUP(U18,Dictionary_v2!$O$3:$P$15,2,0) -> 3 | W18: =VLOOKUP($D18,Dictionary_v2!$G:$J,2,0) -> P&L | X18: Recurring | Y18: =VLOOKUP($D18,Dictionary_v2!$G:$J,3,0) -> 8. Other fixed costs | Z18: =VLOOKUP(Y18,Dictionary_v2!R:S,2,0) -> 6. Other fixed and admin | AA18: =VLOOKUP($D18,Dictionary_v2!$G:$J,4,0) -> 3. Rent | AB18: =if(F18>0,"In","Out") -> Out | AC18: =VLOOKUP(C18,Dictionary_v2!L:M,2,0) -> Sent
A19: 46240.794 | B19: DEPOSIT | C19: COMPLETED | D19: TECNO AVIV SA DE CV | E19: TECNO AVIV | F19: 4020 | G19: MXN | H19: 17.2077 | I19: 233.62 | J19: USDC | K19: 0 | L19: USDC | M19: 0 | N19: USDC | O19: 958.66 | P19: XXXX | Q19: XXXX | R19: XXXX | S19: 46240.794 | T19: =YEAR(A19) -> 2026 | U19: =MONTH(A19) -> 8 | V19: =VLOOKUP(U19,Dictionary_v2!$O$3:$P$15,2,0) -> 3 | W19: =VLOOKUP($D19,Dictionary_v2!$G:$J,2,0) -> P&L | X19: Recurring | Y19: =VLOOKUP($D19,Dictionary_v2!$G:$J,3,0) -> 1. Collections | Z19: =VLOOKUP(Y19,Dictionary_v2!R:S,2,0) -> 1. Collections | AA19: =VLOOKUP($D19,Dictionary_v2!$G:$J,4,0) -> 2. SaaS | AB19: =if(F19>0,"In","Out") -> In | AC19: =VLOOKUP(C19,Dictionary_v2!L:M,2,0) -> Sent
A20: 46236.436 | B20: CARD_PAYMENT | C20: COMPLETED | D20: Indeed Iei26-02411127 Dublin | E20: Indeed IEI26-02411127 | F20: -769.34 | G20: MXN | H20: 17.3373 | I20: -44.37 | J20: USDC | K20: 0 | L20: USDC | M20: 0 | N20: USDC | O20: 725.05 | P20: 2535 | Q20: Ivan Amelong | R20: SERVICES | S20: 46238.375 | T20: =YEAR(A20) -> 2026 | U20: =MONTH(A20) -> 8 | V20: =VLOOKUP(U20,Dictionary_v2!$O$3:$P$15,2,0) -> 3 | W20: =VLOOKUP($D20,Dictionary_v2!$G:$J,2,0) -> P&L | X20: Recurring | Y20: =VLOOKUP($D20,Dictionary_v2!$G:$J,3,0) -> 2. Candidates Sourcing | Z20: =VLOOKUP(Y20,Dictionary_v2!R:S,2,0) -> 2. Candidates Sourcing | AA20: =VLOOKUP($D20,Dictionary_v2!$G:$J,4,0) -> 2. Job Portals | AB20: =if(F20>0,"In","Out") -> Out | AC20: =VLOOKUP(C20,Dictionary_v2!L:M,2,0) -> Sent
A21: 46235.99 | B21: CARD_PAYMENT | C21: COMPLETED | D21: Www.mirlo.mx Mexico | E21: WWW.MIRLO.MX | F21: -129 | G21: MXN | H21: 17.3373 | I21: -7.44 | J21: USDC | K21: 0 | L21: USDC | M21: 0 | N21: USDC | O21: 725.05 | P21: 2535 | Q21: Ivan Amelong | R21: SERVICES | S21: 46237.375 | T21: =YEAR(A21) -> 2026 | U21: =MONTH(A21) -> 8 | V21: =VLOOKUP(U21,Dictionary_v2!$O$3:$P$15,2,0) -> 3 | W21: =VLOOKUP($D21,Dictionary_v2!$G:$J,2,0) -> P&L | X21: Recurring | Y21: =VLOOKUP($D21,Dictionary_v2!$G:$J,3,0) -> 3. Platform | Z21: =VLOOKUP(Y21,Dictionary_v2!R:S,2,0) -> 3. Platform | AA21: =VLOOKUP($D21,Dictionary_v2!$G:$J,4,0) -> 1. Variable | AB21: =if(F21>0,"In","Out") -> Out | AC21: =VLOOKUP(C21,Dictionary_v2!L:M,2,0) -> Sent
A22: 46235.629 | B22: CARD_PAYMENT | C22: COMPLETED | D22: Payu *google Cloud Miguel Hidalg | E22: Google | F22: -2740.87 | G22: MXN | H22: 17.3373 | I22: -158.09 | J22: USDC | K22: 0 | L22: USDC | M22: 0 | N22: USDC | O22: 725.05 | P22: 2535 | Q22: Ivan Amelong | R22: ENTERTAINMENT | S22: 46238.375 | T22: =YEAR(A22) -> 2026 | U22: =MONTH(A22) -> 8 | V22: =VLOOKUP(U22,Dictionary_v2!$O$3:$P$15,2,0) -> 3 | W22: =VLOOKUP($D22,Dictionary_v2!$G:$J,2,0) -> P&L | X22: Recurring | Y22: =VLOOKUP($D22,Dictionary_v2!$G:$J,3,0) -> 2. Candidates Sourcing | Z22: =VLOOKUP(Y22,Dictionary_v2!R:S,2,0) -> 2. Candidates Sourcing | AA22: =VLOOKUP($D22,Dictionary_v2!$G:$J,4,0) -> 1. Social media | AB22: =if(F22>0,"In","Out") -> Out | AC22: =VLOOKUP(C22,Dictionary_v2!L:M,2,0) -> Sent
A23: 46235.25 | B23: CASHBACK | C23: COMPLETED | D23: Cashback | E23: Cashback payment | F23: 6.44 | G23: USDC | H23: 1 | I23: 6.44 | J23: USDC | K23: 0 | L23: USDC | M23: 0 | N23: USDC | O23: 934.95 | P23: XXXX | Q23: XXXX | R23: XXXX | S23: 46235.25 | T23: =YEAR(A23) -> 2026 | U23: =MONTH(A23) -> 8 | V23: =VLOOKUP(U23,Dictionary_v2!$O$3:$P$15,2,0) -> 3 | W23: =VLOOKUP($D23,Dictionary_v2!$G:$J,2,0) -> P&L | X23: Recurring | Y23: =VLOOKUP($D23,Dictionary_v2!$G:$J,3,0) -> 2. Candidates Sourcing | Z23: =VLOOKUP(Y23,Dictionary_v2!R:S,2,0) -> 2. Candidates Sourcing | AA23: =VLOOKUP($D23,Dictionary_v2!$G:$J,4,0) -> 2. Job Portals | AB23: =if(F23>0,"In","Out") -> In | AC23: =VLOOKUP(C23,Dictionary_v2!L:M,2,0) -> Sent
A24: 46234.715 | B24: WITHDRAW | C24: COMPLETED | D24: Federico David Naides | E24: Servicios Julio 26 | F24: -18214.58 | G24: MXN | H24: 17.3175 | I24: -1051.8 | J24: USDC | K24: 0 | L24: USDC | M24: 0 | N24: USDC | O24: 928.51 | P24: XXXX | Q24: XXXX | R24: XXXX | S24: 46234.715 | T24: =YEAR(A24) -> 2026 | U24: =MONTH(A24) -> 7 | V24: =VLOOKUP(U24,Dictionary_v2!$O$3:$P$15,2,0) -> 3 | W24: =VLOOKUP($D24,Dictionary_v2!$G:$J,2,0) -> P&L | X24: Recurring | Y24: =VLOOKUP($D24,Dictionary_v2!$G:$J,3,0) -> 7. Founders | Z24: =VLOOKUP(Y24,Dictionary_v2!R:S,2,0) -> 6. Other fixed and admin | AA24: =VLOOKUP($D24,Dictionary_v2!$G:$J,4,0) -> 1. Salaries | AB24: =if(F24>0,"In","Out") -> Out | AC24: =VLOOKUP(C24,Dictionary_v2!L:M,2,0) -> Sent
A25: 46232.87 | B25: WITHDRAW | C25: COMPLETED | D25: Ivan Amelong | E25: Julio 26 - Folio 7 | F25: -18214.58 | G25: MXN | H25: 17.4478 | I25: -1043.95 | J25: USDC | K25: 0 | L25: USDC | M25: 0 | N25: USDC | O25: 1980.31 | P25: XXXX | Q25: XXXX | R25: XXXX | S25: 46232.87 | T25: =YEAR(A25) -> 2026 | U25: =MONTH(A25) -> 7 | V25: =VLOOKUP(U25,Dictionary_v2!$O$3:$P$15,2,0) -> 3 | W25: =VLOOKUP($D25,Dictionary_v2!$G:$J,2,0) -> P&L | X25: Recurring | Y25: =VLOOKUP($D25,Dictionary_v2!$G:$J,3,0) -> 7. Founders | Z25: =VLOOKUP(Y25,Dictionary_v2!R:S,2,0) -> 6. Other fixed and admin | AA25: =VLOOKUP($D25,Dictionary_v2!$G:$J,4,0) -> 1. Salaries | AB25: =if(F25>0,"In","Out") -> Out | AC25: =VLOOKUP(C25,Dictionary_v2!L:M,2,0) -> Sent
A26: 46231.871 | B26: DEPOSIT | C26: COMPLETED | D26: ALTA RENTABILIDAD SA DE CV | E26: ALTA RENTABILIDAD FACT 32 | F26: 37700 | G26: MXN | H26: 17.4364 | I26: 2162.15 | J26: USDC | K26: 0 | L26: USDC | M26: 0 | N26: USDC | O26: 3024.26 | P26: XXXX | Q26: XXXX | R26: XXXX | S26: 46231.871 | T26: =YEAR(A26) -> 2026 | U26: =MONTH(A26) -> 7 | V26: =VLOOKUP(U26,Dictionary_v2!$O$3:$P$15,2,0) -> 3 | W26: =VLOOKUP($D26,Dictionary_v2!$G:$J,2,0) -> P&L | X26: Recurring | Y26: =VLOOKUP($D26,Dictionary_v2!$G:$J,3,0) -> 1. Collections | Z26: =VLOOKUP(Y26,Dictionary_v2!R:S,2,0) -> 1. Collections | AA26: =VLOOKUP($D26,Dictionary_v2!$G:$J,4,0) -> 1. Full Stack | AB26: =if(F26>0,"In","Out") -> In | AC26: =VLOOKUP(C26,Dictionary_v2!L:M,2,0) -> Sent
A27: 46230.972 | B27: WITHDRAW | C27: COMPLETED | D27: Morgan Philips Mexico | E27: Factura 2768 | F27: -11310 | G27: MXN | H27: 17.4526 | I27: -648.04 | J27: USDC | K27: 0 | L27: USDC | M27: 0 | N27: USDC | O27: 862.12 | P27: XXXX | Q27: XXXX | R27: XXXX | S27: 46230.973 | T27: =YEAR(A27) -> 2026 | U27: =MONTH(A27) -> 7 | V27: =VLOOKUP(U27,Dictionary_v2!$O$3:$P$15,2,0) -> 3 | W27: =VLOOKUP($D27,Dictionary_v2!$G:$J,2,0) -> P&L | X27: Recurring | Y27: =VLOOKUP($D27,Dictionary_v2!$G:$J,3,0) -> 9.Sales comissions | Z27: =VLOOKUP(Y27,Dictionary_v2!R:S,2,0) -> #N/A | AA27: =VLOOKUP($D27,Dictionary_v2!$G:$J,4,0) -> 1. Partnerships | AB27: =if(F27>0,"In","Out") -> Out | AC27: =VLOOKUP(C27,Dictionary_v2!L:M,2,0) -> Sent
A28: 46224.949 | B28: CARD_PAYMENT | C28: COMPLETED | D28: Www.mirlo.mx Mexico | E28: WWW.MIRLO.MX | F28: -65.77 | G28: MXN | H28: 17.3948 | I28: -3.78 | J28: USDC | K28: 0 | L28: USDC | M28: 0 | N28: USDC | O28: 1510.16 | P28: 2535 | Q28: Ivan Amelong | R28: SERVICES | S28: 46226.375 | T28: =YEAR(A28) -> 2026 | U28: =MONTH(A28) -> 7 | V28: =VLOOKUP(U28,Dictionary_v2!$O$3:$P$15,2,0) -> 3 | W28: =VLOOKUP($D28,Dictionary_v2!$G:$J,2,0) -> P&L | X28: Recurring | Y28: =VLOOKUP($D28,Dictionary_v2!$G:$J,3,0) -> 3. Platform | Z28: =VLOOKUP(Y28,Dictionary_v2!R:S,2,0) -> 3. Platform | AA28: =VLOOKUP($D28,Dictionary_v2!$G:$J,4,0) -> 1. Variable | AB28: =if(F28>0,"In","Out") -> Out | AC28: =VLOOKUP(C28,Dictionary_v2!L:M,2,0) -> Sent
A29: 46224.875 | B29: WITHDRAW | C29: COMPLETED | D29: Nadia Meline Karaguezian | F29: -8342 | G29: MXN | H29: 17.3897 | I29: -479.71 | J29: USDC | K29: 0 | L29: USDC | M29: 0 | N29: USDC | O29: 1513.94 | P29: XXXX | Q29: XXXX | R29: XXXX | S29: 46224.876 | T29: =YEAR(A29) -> 2026 | U29: =MONTH(A29) -> 7 | V29: =VLOOKUP(U29,Dictionary_v2!$O$3:$P$15,2,0) -> 3 | W29: =VLOOKUP($D29,Dictionary_v2!$G:$J,2,0) -> P&L | X29: Recurring | Y29: =VLOOKUP($D29,Dictionary_v2!$G:$J,3,0) -> 8. Other fixed costs | Z29: =VLOOKUP(Y29,Dictionary_v2!R:S,2,0) -> 6. Other fixed and admin | AA29: =VLOOKUP($D29,Dictionary_v2!$G:$J,4,0) -> 4. Taxes | AB29: =if(F29>0,"In","Out") -> Out | AC29: =VLOOKUP(C29,Dictionary_v2!L:M,2,0) -> Sent
A30: 46212.947 | B30: CARD_PAYMENT | C30: COMPLETED | D30: Www.mirlo.mx Mexico | E30: WWW.MIRLO.MX | F30: -115.71 | G30: MXN | H30: 17.5243 | I30: -6.6 | J30: USDC | K30: 0 | L30: USDC | M30: 0 | N30: USDC | O30: 1993.65 | P30: 2535 | Q30: Ivan Amelong | R30: SERVICES | S30: 46214.375 | T30: =YEAR(A30) -> 2026 | U30: =MONTH(A30) -> 7 | V30: =VLOOKUP(U30,Dictionary_v2!$O$3:$P$15,2,0) -> 3 | W30: =VLOOKUP($D30,Dictionary_v2!$G:$J,2,0) -> P&L | X30: Recurring | Y30: =VLOOKUP($D30,Dictionary_v2!$G:$J,3,0) -> 3. Platform | Z30: =VLOOKUP(Y30,Dictionary_v2!R:S,2,0) -> 3. Platform | AA30: =VLOOKUP($D30,Dictionary_v2!$G:$J,4,0) -> 1. Variable | AB30: =if(F30>0,"In","Out") -> Out | AC30: =VLOOKUP(C30,Dictionary_v2!L:M,2,0) -> Sent
A31: 46212.931 | B31: DEPOSIT | C31: COMPLETED | D31: CLICOH EXPRESS MX SA DE CV | E31: CONTRATACION 9841 | F31: 28582.4 | G31: MXN | H31: 17.546 | I31: 1629 | J31: USDC | K31: 0 | L31: USDC | M31: 0 | N31: USDC | O31: 2000.25 | P31: XXXX | Q31: XXXX | R31: XXXX | S31: 46212.931 | T31: =YEAR(A31) -> 2026 | U31: =MONTH(A31) -> 7 | V31: =VLOOKUP(U31,Dictionary_v2!$O$3:$P$15,2,0) -> 3 | W31: =VLOOKUP($D31,Dictionary_v2!$G:$J,2,0) -> P&L | X31: Recurring | Y31: =VLOOKUP($D31,Dictionary_v2!$G:$J,3,0) -> 1. Collections | Z31: =VLOOKUP(Y31,Dictionary_v2!R:S,2,0) -> 1. Collections | AA31: =VLOOKUP($D31,Dictionary_v2!$G:$J,4,0) -> 1. Full Stack | AB31: =if(F31>0,"In","Out") -> In | AC31: =VLOOKUP(C31,Dictionary_v2!L:M,2,0) -> Sent
A32: 46207.176 | B32: CARD_PAYMENT | C32: COMPLETED | D32: T1 Telcel Pyre Ciudad De Mex | E32: Telcel | F32: -50 | G32: MXN | H32: 17.4519 | I32: -2.87 | J32: USDC | K32: 0 | L32: USDC | M32: 0 | N32: USDC | O32: 371.25 | P32: 2535 | Q32: Ivan Amelong | R32: SERVICES | S32: 46208.375 | T32: =YEAR(A32) -> 2026 | U32: =MONTH(A32) -> 7 | V32: =VLOOKUP(U32,Dictionary_v2!$O$3:$P$15,2,0) -> 3 | W32: =VLOOKUP($D32,Dictionary_v2!$G:$J,2,0) -> P&L | X32: Recurring | Y32: =VLOOKUP($D32,Dictionary_v2!$G:$J,3,0) -> 3. Platform | Z32: =VLOOKUP(Y32,Dictionary_v2!R:S,2,0) -> 3. Platform | AA32: =VLOOKUP($D32,Dictionary_v2!$G:$J,4,0) -> 1. Variable | AB32: =if(F32>0,"In","Out") -> Out | AC32: =VLOOKUP(C32,Dictionary_v2!L:M,2,0) -> Sent
A33: 46206.96 | B33: DEPOSIT | C33: COMPLETED | D33: AZUCENA DANAE MORALES MARTINEZ | E33: MERCADO*PAGO | F33: 4216.6 | G33: MXN | H33: 17.4819 | I33: 241.2 | J33: USDC | K33: 0 | L33: USDC | M33: 0 | N33: USDC | O33: 374.12 | P33: XXXX | Q33: XXXX | R33: XXXX | S33: 46206.96 | T33: =YEAR(A33) -> 2026 | U33: =MONTH(A33) -> 7 | V33: =VLOOKUP(U33,Dictionary_v2!$O$3:$P$15,2,0) -> 3 | W33: =VLOOKUP($D33,Dictionary_v2!$G:$J,2,0) -> P&L | X33: Recurring | Y33: =VLOOKUP($D33,Dictionary_v2!$G:$J,3,0) -> 1. Collections | Z33: =VLOOKUP(Y33,Dictionary_v2!R:S,2,0) -> 1. Collections | AA33: =VLOOKUP($D33,Dictionary_v2!$G:$J,4,0) -> 2. SaaS | AB33: =if(F33>0,"In","Out") -> In | AC33: =VLOOKUP(C33,Dictionary_v2!L:M,2,0) -> Sent
A34: 46206.694 | B34: CARD_PAYMENT | C34: COMPLETED | D34: Payu *google Ope D M Miguel Hidalg | E34: Google | F34: -2346.04 | G34: MXN | H34: 17.4739 | I34: -134.26 | J34: USDC | K34: 0 | L34: USDC | M34: 0 | N34: USDC | O34: 371.25 | P34: 2535 | Q34: Ivan Amelong | R34: SERVICES | S34: 46209.375 | T34: =YEAR(A34) -> 2026 | U34: =MONTH(A34) -> 7 | V34: =VLOOKUP(U34,Dictionary_v2!$O$3:$P$15,2,0) -> 3 | W34: =VLOOKUP($D34,Dictionary_v2!$G:$J,2,0) -> P&L | X34: Recurring | Y34: =VLOOKUP($D34,Dictionary_v2!$G:$J,3,0) -> 2. Candidates Sourcing | Z34: =VLOOKUP(Y34,Dictionary_v2!R:S,2,0) -> 2. Candidates Sourcing | AA34: =VLOOKUP($D34,Dictionary_v2!$G:$J,4,0) -> 1. Social media | AB34: =if(F34>0,"In","Out") -> Out | AC34: =VLOOKUP(C34,Dictionary_v2!L:M,2,0) -> Sent
A35: 46206.694 | B35: CARD_PAYMENT | C35: COMPLETED | D35: Payu *google Ope D M Miguel Hidalg | E35: Google | F35: -2346.04 | G35: MXN | H35: 17.4739 | I35: -134.26 | J35: USDC | K35: 0 | L35: USDC | M35: 0 | N35: USDC | O35: 371.25 | P35: 2535 | Q35: Ivan Amelong | R35: SERVICES | S35: 46209.375 | T35: =YEAR(A35) -> 2026 | U35: =MONTH(A35) -> 7 | V35: =VLOOKUP(U35,Dictionary_v2!$O$3:$P$15,2,0) -> 3 | W35: =VLOOKUP($D35,Dictionary_v2!$G:$J,2,0) -> P&L | X35: Recurring | Y35: =VLOOKUP($D35,Dictionary_v2!$G:$J,3,0) -> 2. Candidates Sourcing | Z35: =VLOOKUP(Y35,Dictionary_v2!R:S,2,0) -> 2. Candidates Sourcing | AA35: =VLOOKUP($D35,Dictionary_v2!$G:$J,4,0) -> 1. Social media | AB35: =if(F35>0,"In","Out") -> Out | AC35: =VLOOKUP(C35,Dictionary_v2!L:M,2,0) -> Sent
A36: 46206.032 | B36: WITHDRAW | C36: COMPLETED | D36: WeWork Mexico Co S. de R.L. de C.V | E36: Julio 2026 | F36: -10566.44 | G36: MXN | H36: 17.4785 | I36: -604.54 | J36: USDC | K36: 0 | L36: USDC | M36: 0 | N36: USDC | O36: 401.44 | P36: XXXX | Q36: XXXX | R36: XXXX | S36: 46206.033 | T36: =YEAR(A36) -> 2026 | U36: =MONTH(A36) -> 7 | V36: =VLOOKUP(U36,Dictionary_v2!$O$3:$P$15,2,0) -> 3 | W36: =VLOOKUP($D36,Dictionary_v2!$G:$J,2,0) -> P&L | X36: Recurring | Y36: =VLOOKUP($D36,Dictionary_v2!$G:$J,3,0) -> 8. Other fixed costs | Z36: =VLOOKUP(Y36,Dictionary_v2!R:S,2,0) -> 6. Other fixed and admin | AA36: =VLOOKUP($D36,Dictionary_v2!$G:$J,4,0) -> 3. Rent | AB36: =if(F36>0,"In","Out") -> Out | AC36: =VLOOKUP(C36,Dictionary_v2!L:M,2,0) -> Sent
A37: 46205.428 | B37: CARD_PAYMENT | C37: COMPLETED | D37: Indeed Iei26-01998749 Dublin | E37: Indeed IEI26-01998749 | F37: -6350.49 | G37: MXN | H37: 17.5457 | I37: -361.94 | J37: USDC | K37: 0 | L37: USDC | M37: 0 | N37: USDC | O37: 371.25 | P37: 2535 | Q37: Ivan Amelong | R37: SERVICES | S37: 46207.375 | T37: =YEAR(A37) -> 2026 | U37: =MONTH(A37) -> 7 | V37: =VLOOKUP(U37,Dictionary_v2!$O$3:$P$15,2,0) -> 3 | W37: =VLOOKUP($D37,Dictionary_v2!$G:$J,2,0) -> P&L | X37: Recurring | Y37: =VLOOKUP($D37,Dictionary_v2!$G:$J,3,0) -> 2. Candidates Sourcing | Z37: =VLOOKUP(Y37,Dictionary_v2!R:S,2,0) -> 2. Candidates Sourcing | AA37: =VLOOKUP($D37,Dictionary_v2!$G:$J,4,0) -> 2. Job Portals | AB37: =if(F37>0,"In","Out") -> Out | AC37: =VLOOKUP(C37,Dictionary_v2!L:M,2,0) -> Sent
A38: 46204.251 | B38: CASHBACK | C38: COMPLETED | D38: Cashback | E38: Cashback payment | F38: 1.64 | G38: USDC | H38: 1 | I38: 1.64 | J38: USDC | K38: 0 | L38: USDC | M38: 0 | N38: USDC | O38: 1367.92 | P38: XXXX | Q38: XXXX | R38: XXXX | S38: 46204.251 | T38: =YEAR(A38) -> 2026 | U38: =MONTH(A38) -> 7 | V38: =VLOOKUP(U38,Dictionary_v2!$O$3:$P$15,2,0) -> 3 | W38: =VLOOKUP($D38,Dictionary_v2!$G:$J,2,0) -> P&L | X38: Recurring | Y38: =VLOOKUP($D38,Dictionary_v2!$G:$J,3,0) -> 2. Candidates Sourcing | Z38: =VLOOKUP(Y38,Dictionary_v2!R:S,2,0) -> 2. Candidates Sourcing | AA38: =VLOOKUP($D38,Dictionary_v2!$G:$J,4,0) -> 2. Job Portals | AB38: =if(F38>0,"In","Out") -> In | AC38: =VLOOKUP(C38,Dictionary_v2!L:M,2,0) -> Sent
A39: 46202.988 | B39: WITHDRAW | C39: COMPLETED | D39: Federico David Naides | F39: -36429.15 | G39: MXN | H39: 17.4654 | I39: -2085.79 | J39: USDC | K39: 0 | L39: USDC | M39: 0 | N39: USDC | O39: 1366.28 | P39: XXXX | Q39: XXXX | R39: XXXX | S39: 46202.988 | T39: =YEAR(A39) -> 2026 | U39: =MONTH(A39) -> 6 | V39: =VLOOKUP(U39,Dictionary_v2!$O$3:$P$15,2,0) -> 2 | W39: =VLOOKUP($D39,Dictionary_v2!$G:$J,2,0) -> P&L | X39: Recurring | Y39: =VLOOKUP($D39,Dictionary_v2!$G:$J,3,0) -> 7. Founders | Z39: =VLOOKUP(Y39,Dictionary_v2!R:S,2,0) -> 6. Other fixed and admin | AA39: =VLOOKUP($D39,Dictionary_v2!$G:$J,4,0) -> 1. Salaries | AB39: =if(F39>0,"In","Out") -> Out | AC39: =VLOOKUP(C39,Dictionary_v2!L:M,2,0) -> Sent
A40: 46202.988 | B40: WITHDRAW | C40: COMPLETED | D40: Ivan Amelong | F40: -36429.15 | G40: MXN | H40: 17.4668 | I40: -2085.62 | J40: USDC | K40: 0 | L40: USDC | M40: 0 | N40: USDC | O40: 3452.07 | P40: XXXX | Q40: XXXX | R40: XXXX | S40: 46202.988 | T40: =YEAR(A40) -> 2026 | U40: =MONTH(A40) -> 6 | V40: =VLOOKUP(U40,Dictionary_v2!$O$3:$P$15,2,0) -> 2 | W40: =VLOOKUP($D40,Dictionary_v2!$G:$J,2,0) -> P&L | X40: Recurring | Y40: =VLOOKUP($D40,Dictionary_v2!$G:$J,3,0) -> 7. Founders | Z40: =VLOOKUP(Y40,Dictionary_v2!R:S,2,0) -> 6. Other fixed and admin | AA40: =VLOOKUP($D40,Dictionary_v2!$G:$J,4,0) -> 1. Salaries | AB40: =if(F40>0,"In","Out") -> Out | AC40: =VLOOKUP(C40,Dictionary_v2!L:M,2,0) -> Sent
A41: 46199.856 | B41: DEPOSIT | C41: COMPLETED | D41: CLICOH EXPRESS MX SA DE CV | E41: F9772 CONTRATACION | F41: 16820 | G41: MXN | H41: 17.512 | I41: 960.48 | J41: USDC | K41: 0 | L41: USDC | M41: 0 | N41: USDC | O41: 5537.69 | P41: XXXX | Q41: XXXX | R41: XXXX | S41: 46199.856 | T41: =YEAR(A41) -> 2026 | U41: =MONTH(A41) -> 6 | V41: =VLOOKUP(U41,Dictionary_v2!$O$3:$P$15,2,0) -> 2 | W41: =VLOOKUP($D41,Dictionary_v2!$G:$J,2,0) -> P&L | X41: Recurring | Y41: =VLOOKUP($D41,Dictionary_v2!$G:$J,3,0) -> 1. Collections | Z41: =VLOOKUP(Y41,Dictionary_v2!R:S,2,0) -> 1. Collections | AA41: =VLOOKUP($D41,Dictionary_v2!$G:$J,4,0) -> 1. Full Stack | AB41: =if(F41>0,"In","Out") -> In | AC41: =VLOOKUP(C41,Dictionary_v2!L:M,2,0) -> Sent
A42: 46196.84 | B42: WITHDRAW | C42: COMPLETED | D42: Nadia Meline Karaguezian | E42: Impuestos Mayo 26 | F42: -894 | G42: MXN | H42: 17.5715 | I42: -50.88 | J42: USDC | K42: 0 | L42: USDC | M42: 0 | N42: USDC | O42: 4577.21 | P42: XXXX | Q42: XXXX | R42: XXXX | S42: 46196.841 | T42: =YEAR(A42) -> 2026 | U42: =MONTH(A42) -> 6 | V42: =VLOOKUP(U42,Dictionary_v2!$O$3:$P$15,2,0) -> 2 | W42: =VLOOKUP($D42,Dictionary_v2!$G:$J,2,0) -> P&L | X42: Recurring | Y42: =VLOOKUP($D42,Dictionary_v2!$G:$J,3,0) -> 8. Other fixed costs | Z42: =VLOOKUP(Y42,Dictionary_v2!R:S,2,0) -> 6. Other fixed and admin | AA42: =VLOOKUP($D42,Dictionary_v2!$G:$J,4,0) -> 4. Taxes | AB42: =if(F42>0,"In","Out") -> Out | AC42: =VLOOKUP(C42,Dictionary_v2!L:M,2,0) -> Sent
A43: 46191.398 | B43: CARD_PAYMENT | C43: COMPLETED | D43: Tiktok Ciudad De Mex | E43: TIKTOK | F43: -1017.32 | G43: MXN | H43: 17.3357 | I43: -58.68 | J43: USDC | K43: 0 | L43: USDC | M43: 0 | N43: USDC | O43: 4628.08 | P43: 2535 | Q43: Ivan Amelong | R43: SERVICES | S43: 46193.375 | T43: =YEAR(A43) -> 2026 | U43: =MONTH(A43) -> 6 | V43: =VLOOKUP(U43,Dictionary_v2!$O$3:$P$15,2,0) -> 2 | W43: =VLOOKUP($D43,Dictionary_v2!$G:$J,2,0) -> P&L | X43: Recurring | Y43: =VLOOKUP($D43,Dictionary_v2!$G:$J,3,0) -> 2. Candidates Sourcing | Z43: =VLOOKUP(Y43,Dictionary_v2!R:S,2,0) -> 2. Candidates Sourcing | AA43: =VLOOKUP($D43,Dictionary_v2!$G:$J,4,0) -> 1. Social media | AB43: =if(F43>0,"In","Out") -> Out | AC43: =VLOOKUP(C43,Dictionary_v2!L:M,2,0) -> Sent
A44: 46190.736 | B44: DEPOSIT | C44: COMPLETED | D44: ALTA RENTABILIDAD SA DE CV | E44: FACT A22 ALTA RENTABILIDAD | F44: 75400 | G44: MXN | H44: 17.1894 | I44: 4386.41 | J44: USDC | K44: 0 | L44: USDC | M44: 0 | N44: USDC | O44: 4686.77 | P44: XXXX | Q44: XXXX | R44: XXXX | S44: 46190.736 | T44: =YEAR(A44) -> 2026 | U44: =MONTH(A44) -> 6 | V44: =VLOOKUP(U44,Dictionary_v2!$O$3:$P$15,2,0) -> 2 | W44: =VLOOKUP($D44,Dictionary_v2!$G:$J,2,0) -> P&L | X44: Recurring | Y44: =VLOOKUP($D44,Dictionary_v2!$G:$J,3,0) -> 1. Collections | Z44: =VLOOKUP(Y44,Dictionary_v2!R:S,2,0) -> 1. Collections | AA44: =VLOOKUP($D44,Dictionary_v2!$G:$J,4,0) -> 1. Full Stack | AB44: =if(F44>0,"In","Out") -> In | AC44: =VLOOKUP(C44,Dictionary_v2!L:M,2,0) -> Sent
A45: 46185.797 | B45: WITHDRAW | C45: COMPLETED | D45: Notaria MF SC | F45: -13500 | G45: MXN | H45: 17.213 | I45: -784.29 | J45: USDC | K45: 0 | L45: USDC | M45: 0 | N45: USDC | O45: 300.35 | P45: XXXX | Q45: XXXX | R45: XXXX | S45: 46185.797 | T45: =YEAR(A45) -> 2026 | U45: =MONTH(A45) -> 6 | V45: =VLOOKUP(U45,Dictionary_v2!$O$3:$P$15,2,0) -> 2 | W45: =VLOOKUP($D45,Dictionary_v2!$G:$J,2,0) -> P&L | X45: Recurring | Y45: =VLOOKUP($D45,Dictionary_v2!$G:$J,3,0) -> 8. Other fixed costs | Z45: =VLOOKUP(Y45,Dictionary_v2!R:S,2,0) -> 6. Other fixed and admin | AA45: =VLOOKUP($D45,Dictionary_v2!$G:$J,4,0) -> 2. Admin | AB45: =if(F45>0,"In","Out") -> Out | AC45: =VLOOKUP(C45,Dictionary_v2!L:M,2,0) -> Sent
A46: 46177.052 | B46: CARD_PAYMENT | C46: COMPLETED | D46: Tiktok Ciudad De Mex | E46: TIKTOK | F46: -638 | G46: MXN | H46: 17.323 | I46: -36.83 | J46: USDC | K46: 0 | L46: USDC | M46: 0 | N46: USDC | O46: 1084.65 | P46: 2535 | Q46: Ivan Amelong | R46: SERVICES | S46: 46178.375 | T46: =YEAR(A46) -> 2026 | U46: =MONTH(A46) -> 6 | V46: =VLOOKUP(U46,Dictionary_v2!$O$3:$P$15,2,0) -> 2 | W46: =VLOOKUP($D46,Dictionary_v2!$G:$J,2,0) -> P&L | X46: Recurring | Y46: =VLOOKUP($D46,Dictionary_v2!$G:$J,3,0) -> 2. Candidates Sourcing | Z46: =VLOOKUP(Y46,Dictionary_v2!R:S,2,0) -> 2. Candidates Sourcing | AA46: =VLOOKUP($D46,Dictionary_v2!$G:$J,4,0) -> 1. Social media | AB46: =if(F46>0,"In","Out") -> Out | AC46: =VLOOKUP(C46,Dictionary_v2!L:M,2,0) -> Sent
A47: 46175.416 | B47: CARD_PAYMENT | C47: COMPLETED | D47: Indeed Iei26-01603854 Dublin | E47: Indeed IEI26-01603854 | F47: -253.75 | G47: MXN | H47: 17.2937 | I47: -14.67 | J47: USDC | K47: 0 | L47: USDC | M47: 0 | N47: USDC | O47: 1121.48 | P47: 2535 | Q47: Ivan Amelong | R47: SERVICES | S47: 46176.375 | T47: =YEAR(A47) -> 2026 | U47: =MONTH(A47) -> 6 | V47: =VLOOKUP(U47,Dictionary_v2!$O$3:$P$15,2,0) -> 2 | W47: =VLOOKUP($D47,Dictionary_v2!$G:$J,2,0) -> P&L | X47: Recurring | Y47: =VLOOKUP($D47,Dictionary_v2!$G:$J,3,0) -> 2. Candidates Sourcing | Z47: =VLOOKUP(Y47,Dictionary_v2!R:S,2,0) -> 2. Candidates Sourcing | AA47: =VLOOKUP($D47,Dictionary_v2!$G:$J,4,0) -> 2. Job Portals | AB47: =if(F47>0,"In","Out") -> Out | AC47: =VLOOKUP(C47,Dictionary_v2!L:M,2,0) -> Sent
A48: 46174.415 | B48: CARD_PAYMENT | C48: COMPLETED | D48: Tiktok Mx Ciudad De Mex | E48: TIKTOK MX | F48: -290.68 | G48: MXN | H48: 17.3306 | I48: -16.77 | J48: USDC | K48: 0 | L48: USDC | M48: 0 | N48: USDC | O48: 1121.48 | P48: 2535 | Q48: Ivan Amelong | R48: SERVICES | S48: 46176.375 | T48: =YEAR(A48) -> 2026 | U48: =MONTH(A48) -> 6 | V48: =VLOOKUP(U48,Dictionary_v2!$O$3:$P$15,2,0) -> 2 | W48: =VLOOKUP($D48,Dictionary_v2!$G:$J,2,0) -> P&L | X48: Recurring | Y48: =VLOOKUP($D48,Dictionary_v2!$G:$J,3,0) -> 2. Candidates Sourcing | Z48: =VLOOKUP(Y48,Dictionary_v2!R:S,2,0) -> 2. Candidates Sourcing | AA48: =VLOOKUP($D48,Dictionary_v2!$G:$J,4,0) -> 1. Social media | AB48: =if(F48>0,"In","Out") -> Out | AC48: =VLOOKUP(C48,Dictionary_v2!L:M,2,0) -> Sent
A49: 46174.251 | B49: CASHBACK | C49: COMPLETED | D49: Cashback | E49: Cashback payment | F49: 0.55 | G49: USDC | H49: 1 | I49: 0.55 | J49: USDC | K49: 0 | L49: USDC | M49: 0 | N49: USDC | O49: 1152.92 | P49: XXXX | Q49: XXXX | R49: XXXX | S49: 46174.251 | T49: =YEAR(A49) -> 2026 | U49: =MONTH(A49) -> 6 | V49: =VLOOKUP(U49,Dictionary_v2!$O$3:$P$15,2,0) -> 2 | W49: =VLOOKUP($D49,Dictionary_v2!$G:$J,2,0) -> P&L | X49: Recurring | Y49: =VLOOKUP($D49,Dictionary_v2!$G:$J,3,0) -> 2. Candidates Sourcing | Z49: =VLOOKUP(Y49,Dictionary_v2!R:S,2,0) -> 2. Candidates Sourcing | AA49: =VLOOKUP($D49,Dictionary_v2!$G:$J,4,0) -> 2. Job Portals | AB49: =if(F49>0,"In","Out") -> In | AC49: =VLOOKUP(C49,Dictionary_v2!L:M,2,0) -> Sent
A50: 46173.031 | B50: CARD_PAYMENT | C50: COMPLETED | D50: Tiktok Ads Singapore | E50: TikTok Ads | F50: -638 | G50: MXN | H50: 17.3386 | I50: -36.8 | J50: USDC | K50: 0 | L50: USDC | M50: 0 | N50: USDC | O50: 1152.92 | P50: 2535 | Q50: Ivan Amelong | R50: SERVICES | S50: 46174.375 | T50: =YEAR(A50) -> 2026 | U50: =MONTH(A50) -> 5 | V50: =VLOOKUP(U50,Dictionary_v2!$O$3:$P$15,2,0) -> 2 | W50: =VLOOKUP($D50,Dictionary_v2!$G:$J,2,0) -> P&L | X50: Recurring | Y50: =VLOOKUP($D50,Dictionary_v2!$G:$J,3,0) -> 2. Candidates Sourcing | Z50: =VLOOKUP(Y50,Dictionary_v2!R:S,2,0) -> 2. Candidates Sourcing | AA50: =VLOOKUP($D50,Dictionary_v2!$G:$J,4,0) -> 1. Social media | AB50: =if(F50>0,"In","Out") -> Out | AC50: =VLOOKUP(C50,Dictionary_v2!L:M,2,0) -> Sent
A51: 46171.781 | B51: WITHDRAW | C51: COMPLETED | D51: Nadia Meline Karaguezian | F51: -10946 | G51: MXN | H51: 17.3517 | I51: -630.83 | J51: USDC | K51: 0 | L51: USDC | M51: 0 | N51: USDC | O51: 1189.17 | P51: XXXX | Q51: XXXX | R51: XXXX | S51: 46171.782 | T51: =YEAR(A51) -> 2026 | U51: =MONTH(A51) -> 5 | V51: =VLOOKUP(U51,Dictionary_v2!$O$3:$P$15,2,0) -> 2 | W51: =VLOOKUP($D51,Dictionary_v2!$G:$J,2,0) -> P&L | X51: Recurring | Y51: =VLOOKUP($D51,Dictionary_v2!$G:$J,3,0) -> 8. Other fixed costs | Z51: =VLOOKUP(Y51,Dictionary_v2!R:S,2,0) -> 6. Other fixed and admin | AA51: =VLOOKUP($D51,Dictionary_v2!$G:$J,4,0) -> 4. Taxes | AB51: =if(F51>0,"In","Out") -> Out | AC51: =VLOOKUP(C51,Dictionary_v2!L:M,2,0) -> Sent
A52: 46170.703 | B52: WITHDRAW | C52: COMPLETED | D52: WeWork Mexico Co S. de R.L. de C.V | F52: -11140.19 | G52: MXN | H52: 17.3219 | I52: -643.13 | J52: USDC | K52: 0 | L52: USDC | M52: 0 | N52: USDC | O52: 1820 | P52: XXXX | Q52: XXXX | R52: XXXX | S52: 46170.704 | T52: =YEAR(A52) -> 2026 | U52: =MONTH(A52) -> 5 | V52: =VLOOKUP(U52,Dictionary_v2!$O$3:$P$15,2,0) -> 2 | W52: =VLOOKUP($D52,Dictionary_v2!$G:$J,2,0) -> P&L | X52: Recurring | Y52: =VLOOKUP($D52,Dictionary_v2!$G:$J,3,0) -> 8. Other fixed costs | Z52: =VLOOKUP(Y52,Dictionary_v2!R:S,2,0) -> 6. Other fixed and admin | AA52: =VLOOKUP($D52,Dictionary_v2!$G:$J,4,0) -> 3. Rent | AB52: =if(F52>0,"In","Out") -> Out | AC52: =VLOOKUP(C52,Dictionary_v2!L:M,2,0) -> Sent
A53: 46168.775 | B53: DEPOSIT | C53: COMPLETED | D53: BANCO PLATA SA INSTI TUCION DE BANCA MUL | E53: 11300 MAY26 LATAM TALENT RECRU | F53: 9280 | G53: MXN | H53: 17.3131 | I53: 536.01 | J53: USDC | K53: 0 | L53: USDC | M53: 0 | N53: USDC | O53: 2463.13 | P53: XXXX | Q53: XXXX | R53: XXXX | S53: 46168.775 | T53: =YEAR(A53) -> 2026 | U53: =MONTH(A53) -> 5 | V53: =VLOOKUP(U53,Dictionary_v2!$O$3:$P$15,2,0) -> 2 | W53: =VLOOKUP($D53,Dictionary_v2!$G:$J,2,0) -> P&L | X53: Recurring | Y53: =VLOOKUP($D53,Dictionary_v2!$G:$J,3,0) -> 1. Collections | Z53: =VLOOKUP(Y53,Dictionary_v2!R:S,2,0) -> 1. Collections | AA53: =VLOOKUP($D53,Dictionary_v2!$G:$J,4,0) -> 1. Full Stack | AB53: =if(F53>0,"In","Out") -> In | AC53: =VLOOKUP(C53,Dictionary_v2!L:M,2,0) -> Sent
A54: 46167.783 | B54: DEPOSIT | C54: COMPLETED | D54: SERVICIOS TECNOLOGICOS AALKAB S.A. DE C. | E54: Pago contratavciones mayo | F54: 8381 | G54: MXN | H54: 17.2958 | I54: 484.57 | J54: USDC | K54: 0 | L54: USDC | M54: 0 | N54: USDC | O54: 1927.12 | P54: XXXX | Q54: XXXX | R54: XXXX | S54: 46167.783 | T54: =YEAR(A54) -> 2026 | U54: =MONTH(A54) -> 5 | V54: =VLOOKUP(U54,Dictionary_v2!$O$3:$P$15,2,0) -> 2 | W54: =VLOOKUP($D54,Dictionary_v2!$G:$J,2,0) -> P&L | X54: Recurring | Y54: =VLOOKUP($D54,Dictionary_v2!$G:$J,3,0) -> 1. Collections | Z54: =VLOOKUP(Y54,Dictionary_v2!R:S,2,0) -> 1. Collections | AA54: =VLOOKUP($D54,Dictionary_v2!$G:$J,4,0) -> 1. Full Stack | AB54: =if(F54>0,"In","Out") -> In | AC54: =VLOOKUP(C54,Dictionary_v2!L:M,2,0) -> Sent
A55: 46163.856 | B55: DEPOSIT | C55: COMPLETED | D55: CLICOH EXPRESS MX SA DE CV | E55: NEXIU A18 | F55: 16820 | G55: MXN | H55: 17.3035 | I55: 972.06 | J55: USDC | K55: 0 | L55: USDC | M55: 0 | N55: USDC | O55: 1442.55 | P55: XXXX | Q55: XXXX | R55: XXXX | S55: 46163.856 | T55: =YEAR(A55) -> 2026 | U55: =MONTH(A55) -> 5 | V55: =VLOOKUP(U55,Dictionary_v2!$O$3:$P$15,2,0) -> 2 | W55: =VLOOKUP($D55,Dictionary_v2!$G:$J,2,0) -> P&L | X55: Recurring | Y55: =VLOOKUP($D55,Dictionary_v2!$G:$J,3,0) -> 1. Collections | Z55: =VLOOKUP(Y55,Dictionary_v2!R:S,2,0) -> 1. Collections | AA55: =VLOOKUP($D55,Dictionary_v2!$G:$J,4,0) -> 1. Full Stack | AB55: =if(F55>0,"In","Out") -> In | AC55: =VLOOKUP(C55,Dictionary_v2!L:M,2,0) -> Sent
A56: 46149.781 | B56: DEPOSIT | C56: COMPLETED | D56: SERVICIOS TECNOLOGICOS AALKAB S.A. DE C. | E56: Pago Aalkab | F56: 4189.92 | G56: MXN | H56: 17.277 | I56: 242.51 | J56: USDC | K56: 0 | L56: USDC | M56: 0 | N56: USDC | O56: 470.49 | P56: XXXX | Q56: XXXX | R56: XXXX | S56: 46149.781 | T56: =YEAR(A56) -> 2026 | U56: =MONTH(A56) -> 5 | V56: =VLOOKUP(U56,Dictionary_v2!$O$3:$P$15,2,0) -> 2 | W56: =VLOOKUP($D56,Dictionary_v2!$G:$J,2,0) -> P&L | X56: Recurring | Y56: =VLOOKUP($D56,Dictionary_v2!$G:$J,3,0) -> 1. Collections | Z56: =VLOOKUP(Y56,Dictionary_v2!R:S,2,0) -> 1. Collections | AA56: =VLOOKUP($D56,Dictionary_v2!$G:$J,4,0) -> 1. Full Stack | AB56: =if(F56>0,"In","Out") -> In | AC56: =VLOOKUP(C56,Dictionary_v2!L:M,2,0) -> Sent
A57: 46144.41 | B57: CARD_PAYMENT | C57: COMPLETED | D57: Indeed Iei26-01300310 Dublin | E57: Indeed IEI26-01300310 | F57: -962.38 | G57: MXN | H57: 17.4447 | I57: -55.17 | J57: USDC | K57: 0 | L57: USDC | M57: 0 | N57: USDC | O57: 227.98 | P57: 2535 | Q57: Ivan Amelong | R57: SERVICES | S57: 46145.375 | T57: =YEAR(A57) -> 2026 | U57: =MONTH(A57) -> 5 | V57: =VLOOKUP(U57,Dictionary_v2!$O$3:$P$15,2,0) -> 2 | W57: =VLOOKUP($D57,Dictionary_v2!$G:$J,2,0) -> P&L | X57: Recurring | Y57: =VLOOKUP($D57,Dictionary_v2!$G:$J,3,0) -> 2. Candidates Sourcing | Z57: =VLOOKUP(Y57,Dictionary_v2!R:S,2,0) -> 2. Candidates Sourcing | AA57: =VLOOKUP($D57,Dictionary_v2!$G:$J,4,0) -> 2. Job Portals | AB57: =if(F57>0,"In","Out") -> Out | AC57: =VLOOKUP(C57,Dictionary_v2!L:M,2,0) -> Sent
A58: 46143.25 | B58: CASHBACK | C58: COMPLETED | D58: Cashback | E58: Cashback payment | F58: 0.99 | G58: USDC | H58: 1 | I58: 0.99 | J58: USDC | K58: 0 | L58: USDC | M58: 0 | N58: USDC | O58: 283.14 | P58: XXXX | Q58: XXXX | R58: XXXX | S58: 46143.25 | T58: =YEAR(A58) -> 2026 | U58: =MONTH(A58) -> 5 | V58: =VLOOKUP(U58,Dictionary_v2!$O$3:$P$15,2,0) -> 2 | W58: =VLOOKUP($D58,Dictionary_v2!$G:$J,2,0) -> P&L | X58: Recurring | Y58: =VLOOKUP($D58,Dictionary_v2!$G:$J,3,0) -> 2. Candidates Sourcing | Z58: =VLOOKUP(Y58,Dictionary_v2!R:S,2,0) -> 2. Candidates Sourcing | AA58: =VLOOKUP($D58,Dictionary_v2!$G:$J,4,0) -> 2. Job Portals | AB58: =if(F58>0,"In","Out") -> In | AC58: =VLOOKUP(C58,Dictionary_v2!L:M,2,0) -> Sent
A59: 46142.769 | B59: WITHDRAW | C59: COMPLETED | D59: Federico David Naides | F59: -31224.99 | G59: MXN | H59: 17.4809 | I59: -1786.23 | J59: USDC | K59: 0 | L59: USDC | M59: 0 | N59: USDC | O59: 282.15 | P59: XXXX | Q59: XXXX | R59: XXXX | S59: 46142.769 | T59: =YEAR(A59) -> 2026 | U59: =MONTH(A59) -> 4 | V59: =VLOOKUP(U59,Dictionary_v2!$O$3:$P$15,2,0) -> 2 | W59: =VLOOKUP($D59,Dictionary_v2!$G:$J,2,0) -> P&L | X59: Recurring | Y59: =VLOOKUP($D59,Dictionary_v2!$G:$J,3,0) -> 7. Founders | Z59: =VLOOKUP(Y59,Dictionary_v2!R:S,2,0) -> 6. Other fixed and admin | AA59: =VLOOKUP($D59,Dictionary_v2!$G:$J,4,0) -> 1. Salaries | AB59: =if(F59>0,"In","Out") -> Out | AC59: =VLOOKUP(C59,Dictionary_v2!L:M,2,0) -> Sent
A60: 46142.769 | B60: WITHDRAW | C60: COMPLETED | D60: Ivan Amelong | F60: -31224.99 | G60: MXN | H60: 17.4799 | I60: -1786.34 | J60: USDC | K60: 0 | L60: USDC | M60: 0 | N60: USDC | O60: 2068.39 | P60: XXXX | Q60: XXXX | R60: XXXX | S60: 46142.769 | T60: =YEAR(A60) -> 2026 | U60: =MONTH(A60) -> 4 | V60: =VLOOKUP(U60,Dictionary_v2!$O$3:$P$15,2,0) -> 2 | W60: =VLOOKUP($D60,Dictionary_v2!$G:$J,2,0) -> P&L | X60: Recurring | Y60: =VLOOKUP($D60,Dictionary_v2!$G:$J,3,0) -> 7. Founders | Z60: =VLOOKUP(Y60,Dictionary_v2!R:S,2,0) -> 6. Other fixed and admin | AA60: =VLOOKUP($D60,Dictionary_v2!$G:$J,4,0) -> 1. Salaries | AB60: =if(F60>0,"In","Out") -> Out | AC60: =VLOOKUP(C60,Dictionary_v2!L:M,2,0) -> Sent
A61: 46142.302 | B61: WITHDRAW | C61: COMPLETED | D61: WeWork Mexico Co S. de R.L. de C.V | F61: -11607.62 | G61: MXN | H61: 17.5412 | I61: -661.73 | J61: USDC | K61: 0 | L61: USDC | M61: 0 | N61: USDC | O61: 3854.73 | P61: XXXX | Q61: XXXX | R61: XXXX | S61: 46142.303 | T61: =YEAR(A61) -> 2026 | U61: =MONTH(A61) -> 4 | V61: =VLOOKUP(U61,Dictionary_v2!$O$3:$P$15,2,0) -> 2 | W61: =VLOOKUP($D61,Dictionary_v2!$G:$J,2,0) -> P&L | X61: Recurring | Y61: =VLOOKUP($D61,Dictionary_v2!$G:$J,3,0) -> 8. Other fixed costs | Z61: =VLOOKUP(Y61,Dictionary_v2!R:S,2,0) -> 6. Other fixed and admin | AA61: =VLOOKUP($D61,Dictionary_v2!$G:$J,4,0) -> 3. Rent | AB61: =if(F61>0,"In","Out") -> Out | AC61: =VLOOKUP(C61,Dictionary_v2!L:M,2,0) -> Sent
A62: 46140.808 | B62: WITHDRAW | C62: COMPLETED | D62: Nexiu AI LLC | F62: -10115 | G62: USD | H62: 1 | I62: -10115 | J62: USDC | K62: 0 | L62: USDC | M62: 0 | N62: USDC | O62: 4516.46 | P62: XXXX | Q62: XXXX | R62: XXXX | S62: 46141.875 | T62: =YEAR(A62) -> 2026 | U62: =MONTH(A62) -> 4 | V62: =VLOOKUP(U62,Dictionary_v2!$O$3:$P$15,2,0) -> 2 | W62: =VLOOKUP($D62,Dictionary_v2!$G:$J,2,0) -> BS | X62: Recurring | Y62: =VLOOKUP($D62,Dictionary_v2!$G:$J,3,0) -> 0. Investments | Z62: =VLOOKUP(Y62,Dictionary_v2!R:S,2,0) -> 0. Investments | AA62: =VLOOKUP($D62,Dictionary_v2!$G:$J,4,0) -> 4. Intercompany | AB62: =if(F62>0,"In","Out") -> Out | AC62: =VLOOKUP(C62,Dictionary_v2!L:M,2,0) -> Sent
A63: 46132.892 | B63: DEPOSIT | C63: COMPLETED | D63: SERVICIOS TECNOLOGICOS AALKAB S.A. DE C. | E63: Pago Aalkab | F63: 11091.92 | G63: MXN | H63: 17.3293 | I63: 640.07 | J63: USDC | K63: 0 | L63: USDC | M63: 0 | N63: USDC | O63: 14631.46 | P63: XXXX | Q63: XXXX | R63: XXXX | S63: 46132.892 | T63: =YEAR(A63) -> 2026 | U63: =MONTH(A63) -> 4 | V63: =VLOOKUP(U63,Dictionary_v2!$O$3:$P$15,2,0) -> 2 | W63: =VLOOKUP($D63,Dictionary_v2!$G:$J,2,0) -> P&L | X63: Recurring | Y63: =VLOOKUP($D63,Dictionary_v2!$G:$J,3,0) -> 1. Collections | Z63: =VLOOKUP(Y63,Dictionary_v2!R:S,2,0) -> 1. Collections | AA63: =VLOOKUP($D63,Dictionary_v2!$G:$J,4,0) -> 1. Full Stack | AB63: =if(F63>0,"In","Out") -> In | AC63: =VLOOKUP(C63,Dictionary_v2!L:M,2,0) -> Sent
A64: 46129.766 | B64: WITHDRAW | C64: COMPLETED | D64: WeWork Mexico Co S. de R.L. de C.V | F64: -960.21 | G64: MXN | H64: 17.282 | I64: -55.56 | J64: USDC | K64: 0 | L64: USDC | M64: 0 | N64: USDC | O64: 13991.39 | P64: XXXX | Q64: XXXX | R64: XXXX | S64: 46129.767 | T64: =YEAR(A64) -> 2026 | U64: =MONTH(A64) -> 4 | V64: =VLOOKUP(U64,Dictionary_v2!$O$3:$P$15,2,0) -> 2 | W64: =VLOOKUP($D64,Dictionary_v2!$G:$J,2,0) -> P&L | X64: Recurring | Y64: =VLOOKUP($D64,Dictionary_v2!$G:$J,3,0) -> 8. Other fixed costs | Z64: =VLOOKUP(Y64,Dictionary_v2!R:S,2,0) -> 6. Other fixed and admin | AA64: =VLOOKUP($D64,Dictionary_v2!$G:$J,4,0) -> 3. Rent | AB64: =if(F64>0,"In","Out") -> Out | AC64: =VLOOKUP(C64,Dictionary_v2!L:M,2,0) -> Sent
A65: 46128.88 | B65: DEPOSIT | C65: COMPLETED | D65: UVI TECH SAPI DE CV | E65: VENDBILL1091442 | F65: 93650.28 | G65: MXN | H65: 17.2863 | I65: 5417.6 | J65: USDC | K65: 0 | L65: USDC | M65: 0 | N65: USDC | O65: 14046.96 | P65: XXXX | Q65: XXXX | R65: XXXX | S65: 46128.88 | T65: =YEAR(A65) -> 2026 | U65: =MONTH(A65) -> 4 | V65: =VLOOKUP(U65,Dictionary_v2!$O$3:$P$15,2,0) -> 2 | W65: =VLOOKUP($D65,Dictionary_v2!$G:$J,2,0) -> P&L | X65: Recurring | Y65: =VLOOKUP($D65,Dictionary_v2!$G:$J,3,0) -> 1. Collections | Z65: =VLOOKUP(Y65,Dictionary_v2!R:S,2,0) -> 1. Collections | AA65: =VLOOKUP($D65,Dictionary_v2!$G:$J,4,0) -> 1. Full Stack | AB65: =if(F65>0,"In","Out") -> In | AC65: =VLOOKUP(C65,Dictionary_v2!L:M,2,0) -> Sent
A66: 46128.722 | B66: DEPOSIT | C66: COMPLETED | D66: BANCO PLATA SA INSTI TUCION DE BANCA MUL | E66: 11300 APR16 LATAM TALENT RECRU | F66: 9280 | G66: MXN | H66: 17.2816 | I66: 536.99 | J66: USDC | K66: 0 | L66: USDC | M66: 0 | N66: USDC | O66: 8629.35 | P66: XXXX | Q66: XXXX | R66: XXXX | S66: 46128.722 | T66: =YEAR(A66) -> 2026 | U66: =MONTH(A66) -> 4 | V66: =VLOOKUP(U66,Dictionary_v2!$O$3:$P$15,2,0) -> 2 | W66: =VLOOKUP($D66,Dictionary_v2!$G:$J,2,0) -> P&L | X66: Recurring | Y66: =VLOOKUP($D66,Dictionary_v2!$G:$J,3,0) -> 1. Collections | Z66: =VLOOKUP(Y66,Dictionary_v2!R:S,2,0) -> 1. Collections | AA66: =VLOOKUP($D66,Dictionary_v2!$G:$J,4,0) -> 1. Full Stack | AB66: =if(F66>0,"In","Out") -> In | AC66: =VLOOKUP(C66,Dictionary_v2!L:M,2,0) -> Sent
A67: 46114.428 | B67: CARD_PAYMENT | C67: COMPLETED | D67: Indeed Iei26-00909015 Dublin | E67: Indeed IEI26-00909015 | F67: -1774.75 | G67: MXN | H67: 17.9436 | I67: -98.91 | J67: USDC | K67: 0 | L67: USDC | M67: 0 | N67: USDC | O67: 8092.36 | P67: 2535 | Q67: Ivan Amelong | R67: SERVICES | S67: 46116.375 | T67: =YEAR(A67) -> 2026 | U67: =MONTH(A67) -> 4 | V67: =VLOOKUP(U67,Dictionary_v2!$O$3:$P$15,2,0) -> 2 | W67: =VLOOKUP($D67,Dictionary_v2!$G:$J,2,0) -> P&L | X67: Recurring | Y67: =VLOOKUP($D67,Dictionary_v2!$G:$J,3,0) -> 2. Candidates Sourcing | Z67: =VLOOKUP(Y67,Dictionary_v2!R:S,2,0) -> 2. Candidates Sourcing | AA67: =VLOOKUP($D67,Dictionary_v2!$G:$J,4,0) -> 2. Job Portals | AB67: =if(F67>0,"In","Out") -> Out | AC67: =VLOOKUP(C67,Dictionary_v2!L:M,2,0) -> Sent
A68: 46113.844 | B68: WITHDRAW | C68: COMPLETED | D68: Ricardo Lopez | F68: -7806.24 | G68: MXN | H68: 17.8329 | I68: -437.74 | J68: USDC | K68: 0 | L68: USDC | M68: 0 | N68: USDC | O68: 8191.27 | P68: XXXX | Q68: XXXX | R68: XXXX | S68: 46113.844 | T68: =YEAR(A68) -> 2026 | U68: =MONTH(A68) -> 4 | V68: =VLOOKUP(U68,Dictionary_v2!$O$3:$P$15,2,0) -> 2 | W68: =VLOOKUP($D68,Dictionary_v2!$G:$J,2,0) -> P&L | X68: Recurring | Y68: =VLOOKUP($D68,Dictionary_v2!$G:$J,3,0) -> 8. Other fixed costs | Z68: =VLOOKUP(Y68,Dictionary_v2!R:S,2,0) -> 6. Other fixed and admin | AA68: =VLOOKUP($D68,Dictionary_v2!$G:$J,4,0) -> 2. Admin | AB68: =if(F68>0,"In","Out") -> Out | AC68: =VLOOKUP(C68,Dictionary_v2!L:M,2,0) -> Sent
A69: 46113.25 | B69: CASHBACK | C69: COMPLETED | D69: Cashback | E69: Cashback payment | F69: 11.67 | G69: USDC | H69: 1 | I69: 11.67 | J69: USDC | K69: 0 | L69: USDC | M69: 0 | N69: USDC | O69: 8629.02 | P69: XXXX | Q69: XXXX | R69: XXXX | S69: 46113.25 | T69: =YEAR(A69) -> 2026 | U69: =MONTH(A69) -> 4 | V69: =VLOOKUP(U69,Dictionary_v2!$O$3:$P$15,2,0) -> 2 | W69: =VLOOKUP($D69,Dictionary_v2!$G:$J,2,0) -> P&L | X69: Recurring | Y69: =VLOOKUP($D69,Dictionary_v2!$G:$J,3,0) -> 2. Candidates Sourcing | Z69: =VLOOKUP(Y69,Dictionary_v2!R:S,2,0) -> 2. Candidates Sourcing | AA69: =VLOOKUP($D69,Dictionary_v2!$G:$J,4,0) -> 2. Job Portals | AB69: =if(F69>0,"In","Out") -> In | AC69: =VLOOKUP(C69,Dictionary_v2!L:M,2,0) -> Sent
A70: 46112.795 | B70: WITHDRAW | C70: COMPLETED | D70: WeWork Mexico Co S. de R.L. de C.V | E70: Marzo 26 | F70: -24833.6 | G70: MXN | H70: 17.9465 | I70: -1383.76 | J70: USDC | K70: 0 | L70: USDC | M70: 0 | N70: USDC | O70: 8617.35 | P70: XXXX | Q70: XXXX | R70: XXXX | S70: 46112.796 | T70: =YEAR(A70) -> 2026 | U70: =MONTH(A70) -> 3 | V70: =VLOOKUP(U70,Dictionary_v2!$O$3:$P$15,2,0) -> 1 | W70: P&L | X70: Recurring | Y70: 8. Other fixed costs | Z70: 6. Other fixed and admin | AA70: 3. Rent | AB70: =if(F70>0,"In","Out") -> Out | AC70: =VLOOKUP(C70,Dictionary_v2!L:M,2,0) -> Sent
A71: 46112.757 | B71: DEPOSIT | C71: COMPLETED | D71: Nexiu AI LLC | E71: MercuryACH Nexiu AI LLC MRCR-2EWPMCBOKA 260331 [LatAm Talent & Recruit] From Nexiu AI, LLC via mercury.com | F71: 10000 | G71: USD | H71: 1 | I71: 10000 | J71: USDC | K71: 0 | L71: USDC | M71: 0 | N71: USDC | O71: 10001.1 | P71: XXXX | Q71: XXXX | R71: XXXX | S71: 46112.757 | T71: =YEAR(A71) -> 2026 | U71: =MONTH(A71) -> 3 | V71: =VLOOKUP(U71,Dictionary_v2!$O$3:$P$15,2,0) -> 1 | W71: BS | X71: Recurring | Y71: 0. Investments | Z71: 0. Investments | AA71: 4. Intercompany | AB71: =if(F71>0,"In","Out") -> In | AC71: =VLOOKUP(C71,Dictionary_v2!L:M,2,0) -> Sent
A72: 46099.647 | B72: WITHDRAW | C72: COMPLETED | D72: WeWork Mexico Co S. de R.L. de C.V | F72: -11086.17 | G72: MXN | H72: 17.6567 | I72: -627.87 | J72: USDC | K72: 0 | L72: USDC | M72: 0 | N72: USDC | O72: 1.1 | P72: XXXX | Q72: XXXX | R72: XXXX | S72: 46099.647 | T72: =YEAR(A72) -> 2026 | U72: =MONTH(A72) -> 3 | V72: =VLOOKUP(U72,Dictionary_v2!$O$3:$P$15,2,0) -> 1 | W72: P&L | X72: Recurring | Y72: 8. Other fixed costs | Z72: 6. Other fixed and admin | AA72: 3. Rent | AB72: =if(F72>0,"In","Out") -> Out | AC72: =VLOOKUP(C72,Dictionary_v2!L:M,2,0) -> Sent
A73: 46095.802 | B73: CARD_PAYMENT | C73: COMPLETED | D73: Indeed Iei26-00787671 Dublin | E73: Indeed IEI26-00787671 | F73: -10005.49 | G73: MXN | H73: 17.8885 | I73: -559.33 | J73: USDC | K73: 0 | L73: USDC | M73: 0 | N73: USDC | O73: 628.98 | P73: 2535 | Q73: Ivan Amelong | R73: SERVICES | S73: 46097.375 | T73: =YEAR(A73) -> 2026 | U73: =MONTH(A73) -> 3 | V73: =VLOOKUP(U73,Dictionary_v2!$O$3:$P$15,2,0) -> 1 | W73: P&L | X73: Recurring | Y73: 2. Candidates Sourcing | Z73: 2. Candidates Sourcing | AA73: 2. Job Portals | AB73: =if(F73>0,"In","Out") -> Out | AC73: =VLOOKUP(C73,Dictionary_v2!L:M,2,0) -> Sent
A74: 46094.753 | B74: DEPOSIT | C74: COMPLETED | D74: BANCO PLATA SA INSTI TUCION DE BANCA MUL | E74: 11300 MAR13 LATAM TALENT RECRU | F74: 18560 | G74: MXN | H74: 17.892 | I74: 1037.33 | J74: USDC | K74: 0 | L74: USDC | M74: 0 | N74: USDC | O74: 1188.3 | P74: XXXX | Q74: XXXX | R74: XXXX | S74: 46094.753 | T74: =YEAR(A74) -> 2026 | U74: =MONTH(A74) -> 3 | V74: =VLOOKUP(U74,Dictionary_v2!$O$3:$P$15,2,0) -> 1 | W74: P&L | X74: Recurring | Y74: 1. Collections | Z74: 1. Collections | AA74: 1. Full Stack | AB74: =if(F74>0,"In","Out") -> In | AC74: =VLOOKUP(C74,Dictionary_v2!L:M,2,0) -> Sent
A75: 46091.633 | B75: CARD_PAYMENT | C75: REVERTED | D75: Google*temporary Hold Cc Google.com | E75: Google | F75: -20 | G75: MXN | H75: 17.5034 | I75: -1.14 | J75: USDC | K75: 0 | L75: USDC | M75: 0 | N75: USDC | O75: XXXX | P75: 2535 | Q75: Ivan Amelong | R75: ENTERTAINMENT | S75: XXXX | T75: =YEAR(A75) -> 2026 | U75: =MONTH(A75) -> 3 | V75: =VLOOKUP(U75,Dictionary_v2!$O$3:$P$15,2,0) -> 1 | W75: P&L | X75: Recurring | Y75: 2. Candidates Sourcing | Z75: 2. Candidates Sourcing | AA75: 1. Social media | AB75: =if(F75>0,"In","Out") -> Out | AC75: =VLOOKUP(C75,Dictionary_v2!L:M,2,0) -> Failed
A76: 46083.431 | B76: CARD_PAYMENT | C76: COMPLETED | D76: Indeed Iei26-00603017 Dublin | E76: Indeed IEI26-00603017 | F76: -459.82 | G76: MXN | H76: 17.2909 | I76: -26.59 | J76: USDC | K76: 0 | L76: USDC | M76: 0 | N76: USDC | O76: 150.97 | P76: 2535 | Q76: Ivan Amelong | R76: SERVICES | S76: 46084.375 | T76: =YEAR(A76) -> 2026 | U76: =MONTH(A76) -> 3 | V76: =VLOOKUP(U76,Dictionary_v2!$O$3:$P$15,2,0) -> 1 | W76: P&L | X76: Recurring | Y76: 2. Candidates Sourcing | Z76: 2. Candidates Sourcing | AA76: 2. Job Portals | AB76: =if(F76>0,"In","Out") -> Out | AC76: =VLOOKUP(C76,Dictionary_v2!L:M,2,0) -> Sent
A77: 46082.25 | B77: CASHBACK | C77: COMPLETED | D77: Cashback | E77: Cashback payment | F77: 14.32 | G77: USDC | H77: 1 | I77: 14.32 | J77: USDC | K77: 0 | L77: USDC | M77: 0 | N77: USDC | O77: 177.56 | P77: XXXX | Q77: XXXX | R77: XXXX | S77: 46082.25 | T77: =YEAR(A77) -> 2026 | U77: =MONTH(A77) -> 3 | V77: =VLOOKUP(U77,Dictionary_v2!$O$3:$P$15,2,0) -> 1 | W77: P&L | X77: Recurring | Y77: 1. Collections | Z77: 1. Collections | AA77: 1. Full Stack | AB77: =if(F77>0,"In","Out") -> In | AC77: =VLOOKUP(C77,Dictionary_v2!L:M,2,0) -> Sent
A78: 46081.847 | B78: CARD_PAYMENT | C78: COMPLETED | D78: Indeed Iei26-00557574 Dublin | E78: Indeed IEI26-00557574 | F78: -10004.43 | G78: MXN | H78: 17.207 | I78: -581.42 | J78: USDC | K78: 0 | L78: USDC | M78: 0 | N78: USDC | O78: 177.56 | P78: 2535 | Q78: Ivan Amelong | R78: SERVICES | S78: 46083.375 | T78: =YEAR(A78) -> 2026 | U78: =MONTH(A78) -> 2 | V78: =VLOOKUP(U78,Dictionary_v2!$O$3:$P$15,2,0) -> 1 | W78: P&L | X78: Recurring | Y78: 2. Candidates Sourcing | Z78: 2. Candidates Sourcing | AA78: 2. Job Portals | AB78: =if(F78>0,"In","Out") -> Out | AC78: =VLOOKUP(C78,Dictionary_v2!L:M,2,0) -> Sent
A79: 46076.847 | B79: CARD_PAYMENT | C79: COMPLETED | D79: Indeed Iei26-00531466 Dublin | E79: Indeed IEI26-00531466 | F79: -10008.92 | G79: MXN | H79: 17.2691 | I79: -579.58 | J79: USDC | K79: 0 | L79: USDC | M79: 0 | N79: USDC | O79: 1349.55 | P79: 2535 | Q79: Ivan Amelong | R79: SERVICES | S79: 46078.375 | T79: =YEAR(A79) -> 2026 | U79: =MONTH(A79) -> 2 | V79: =VLOOKUP(U79,Dictionary_v2!$O$3:$P$15,2,0) -> 1 | W79: P&L | X79: Recurring | Y79: 2. Candidates Sourcing | Z79: 2. Candidates Sourcing | AA79: 2. Job Portals | AB79: =if(F79>0,"In","Out") -> Out | AC79: =VLOOKUP(C79,Dictionary_v2!L:M,2,0) -> Sent
A80: 46076.787 | B80: DEPOSIT | C80: COMPLETED | D80: PODEMOS PROGRESAR SA PI DE CV SOFOM ENR | E80: ATRACCION CANDIDATOS BB466267 | F80: 12383 | G80: MXN | H80: 17.2624 | I80: 717.34 | J80: USDC | K80: 0 | L80: USDC | M80: 0 | N80: USDC | O80: 1929.13 | P80: XXXX | Q80: XXXX | R80: XXXX | S80: 46076.787 | T80: =YEAR(A80) -> 2026 | U80: =MONTH(A80) -> 2 | V80: =VLOOKUP(U80,Dictionary_v2!$O$3:$P$15,2,0) -> 1 | W80: P&L | X80: Recurring | Y80: 1. Collections | Z80: 1. Collections | AA80: 2. SaaS | AB80: =if(F80>0,"In","Out") -> In | AC80: =VLOOKUP(C80,Dictionary_v2!L:M,2,0) -> Sent
A81: 46076.785 | B81: DEPOSIT | C81: COMPLETED | D81: PODEMOS PROGRESAR SA PI DE CV SOFOM ENR | E81: SOFTWARE RECLUTAMIENTO 07AF516 | F81: 14518.56 | G81: MXN | H81: 17.2628 | I81: 841.03 | J81: USDC | K81: 0 | L81: USDC | M81: 0 | N81: USDC | O81: 1211.79 | P81: XXXX | Q81: XXXX | R81: XXXX | S81: 46076.785 | T81: =YEAR(A81) -> 2026 | U81: =MONTH(A81) -> 2 | V81: =VLOOKUP(U81,Dictionary_v2!$O$3:$P$15,2,0) -> 1 | W81: P&L | X81: Recurring | Y81: 1. Collections | Z81: 1. Collections | AA81: 2. SaaS | AB81: =if(F81>0,"In","Out") -> In | AC81: =VLOOKUP(C81,Dictionary_v2!L:M,2,0) -> Sent
A82: 46072.669 | B82: WITHDRAW | C82: COMPLETED | D82: Roilaw Project SAS de CV | E82: Servicios legales | F82: -7540 | G82: MXN | H82: 17.2549 | I82: -436.98 | J82: USDC | K82: 0 | L82: USDC | M82: 0 | N82: USDC | O82: 370.76 | P82: XXXX | Q82: XXXX | R82: XXXX | S82: 46072.67 | T82: =YEAR(A82) -> 2026 | U82: =MONTH(A82) -> 2 | V82: =VLOOKUP(U82,Dictionary_v2!$O$3:$P$15,2,0) -> 1 | W82: P&L | X82: Recurring | Y82: 8. Other fixed costs | Z82: 6. Other fixed and admin | AA82: 2. Admin | AB82: =if(F82>0,"In","Out") -> Out | AC82: =VLOOKUP(C82,Dictionary_v2!L:M,2,0) -> Sent
A83: 46067.001 | B83: CARD_PAYMENT | C83: COMPLETED | D83: Indeed Iei26-00490088 Dublin | E83: Indeed IEI26-00490088 | F83: -10006.4 | G83: MXN | H83: 17.1494 | I83: -583.48 | J83: USDC | K83: 0 | L83: USDC | M83: 0 | N83: USDC | O83: 807.74 | P83: 2535 | Q83: Ivan Amelong | R83: SERVICES | S83: 46068.375 | T83: =YEAR(A83) -> 2026 | U83: =MONTH(A83) -> 2 | V83: =VLOOKUP(U83,Dictionary_v2!$O$3:$P$15,2,0) -> 1 | W83: P&L | X83: Recurring | Y83: 2. Candidates Sourcing | Z83: 2. Candidates Sourcing | AA83: 2. Job Portals | AB83: =if(F83>0,"In","Out") -> Out | AC83: =VLOOKUP(C83,Dictionary_v2!L:M,2,0) -> Sent
A84: 46066.844 | B84: CARD_PAYMENT | C84: FAILED | D84: Indeed Iei26-00490088 Dublin | E84: Indeed IEI26-00490088 | F84: -10006.4 | G84: MXN | H84: 17.1556 | I84: -583.27 | J84: USDC | K84: 0 | L84: USDC | M84: 0 | N84: USDC | O84: XXXX | P84: 2535 | Q84: Ivan Amelong | R84: SERVICES | S84: XXXX | T84: =YEAR(A84) -> 2026 | U84: =MONTH(A84) -> 2 | V84: =VLOOKUP(U84,Dictionary_v2!$O$3:$P$15,2,0) -> 1 | X84: Failed | Y84: Failed | Z84: Failed | AB84: =if(F84>0,"In","Out") -> Out | AC84: =VLOOKUP(C84,Dictionary_v2!L:M,2,0) -> Failed
A85: 46055.406 | B85: CARD_PAYMENT | C85: COMPLETED | D85: Indeed Iei26-00378096 Dublin | E85: Indeed IEI26-00378096 | F85: -4539.74 | G85: MXN | H85: 17.4356 | I85: -260.37 | J85: USDC | K85: 0 | L85: USDC | M85: 0 | N85: USDC | O85: 1391.22 | P85: 2535 | Q85: Ivan Amelong | R85: SERVICES | S85: 46056.375 | T85: =YEAR(A85) -> 2026 | U85: =MONTH(A85) -> 2 | V85: =VLOOKUP(U85,Dictionary_v2!$O$3:$P$15,2,0) -> 1 | W85: P&L | X85: Recurring | Y85: 2. Candidates Sourcing | Z85: 2. Candidates Sourcing | AA85: 2. Job Portals | AB85: =if(F85>0,"In","Out") -> Out | AC85: =VLOOKUP(C85,Dictionary_v2!L:M,2,0) -> Sent
A86: 46054.437 | B86: CARD_PAYMENT | C86: COMPLETED | D86: Tiktok Ciudad De Mex | E86: TIKTOK | F86: -142.67 | G86: MXN | H86: 17.453 | I86: -8.17 | J86: USDC | K86: 0 | L86: USDC | M86: 0 | N86: USDC | O86: 1391.22 | P86: 2535 | Q86: Ivan Amelong | R86: SERVICES | S86: 46056.375 | T86: =YEAR(A86) -> 2026 | U86: =MONTH(A86) -> 2 | V86: =VLOOKUP(U86,Dictionary_v2!$O$3:$P$15,2,0) -> 1 | W86: P&L | X86: Recurring | Y86: 2. Candidates Sourcing | Z86: 2. Candidates Sourcing | AA86: 1. Social media | AB86: =if(F86>0,"In","Out") -> Out | AC86: =VLOOKUP(C86,Dictionary_v2!L:M,2,0) -> Sent
A87: 46041.879 | B87: WITHDRAW | C87: COMPLETED | D87: Ricardo Lopez | E87: Honorarios contablesAgo25-Ene26 | F87: -9367.5 | G87: MXN | H87: 17.5748 | I87: -533.01 | J87: USDC | K87: 0 | L87: USDC | M87: 0 | N87: USDC | O87: 1658.64 | P87: XXXX | Q87: XXXX | R87: XXXX | S87: 46041.88 | T87: =YEAR(A87) -> 2026 | U87: =MONTH(A87) -> 1 | V87: =VLOOKUP(U87,Dictionary_v2!$O$3:$P$15,2,0) -> 1 | W87: P&L | X87: Recurring | Y87: 8. Other fixed costs | Z87: 6. Other fixed and admin | AA87: 2. Admin | AB87: =if(F87>0,"In","Out") -> Out | AC87: =VLOOKUP(C87,Dictionary_v2!L:M,2,0) -> Sent
A88: 46041.825 | B88: WITHDRAW | C88: FAILED | D88: Ricardo Lopez | E88: Honorarios contablesAgo25-Ene26 | F88: -9367.5 | G88: MXN | H88: 17.5814 | I88: -532.81 | J88: USDC | K88: 0 | L88: USDC | M88: 0 | N88: USDC | O88: XXXX | P88: XXXX | Q88: XXXX | R88: XXXX | S88: XXXX | T88: =YEAR(A88) -> 2026 | U88: =MONTH(A88) -> 1 | V88: =VLOOKUP(U88,Dictionary_v2!$O$3:$P$15,2,0) -> 1 | X88: Failed | Y88: Failed | Z88: Failed | AB88: =if(F88>0,"In","Out") -> Out | AC88: =VLOOKUP(C88,Dictionary_v2!L:M,2,0) -> Failed
A89: 46038.725 | B89: WITHDRAW | C89: FAILED | D89: Ricardo Lopez | E89: Honorarios contablesAgo25-Ene26 | F89: -9367.5 | G89: MXN | H89: 17.6659 | I89: -530.26 | J89: USDC | K89: 0 | L89: USDC | M89: 0 | N89: USDC | O89: XXXX | P89: XXXX | Q89: XXXX | R89: XXXX | S89: XXXX | T89: =YEAR(A89) -> 2026 | U89: =MONTH(A89) -> 1 | V89: =VLOOKUP(U89,Dictionary_v2!$O$3:$P$15,2,0) -> 1 | X89: Failed | Y89: Failed | Z89: Failed | AB89: =if(F89>0,"In","Out") -> Out | AC89: =VLOOKUP(C89,Dictionary_v2!L:M,2,0) -> Failed
A90: 46037.892 | B90: CARD_PAYMENT | C90: REVERTED | D90: Tiktok Ads Singapore | E90: TikTok Ads | F90: -200 | G90: MXN | H90: 17.6428 | I90: -11.34 | J90: USDC | K90: 0 | L90: USDC | M90: 0 | N90: USDC | O90: XXXX | P90: 2535 | Q90: Ivan Amelong | R90: SERVICES | S90: XXXX | T90: =YEAR(A90) -> 2026 | U90: =MONTH(A90) -> 1 | V90: =VLOOKUP(U90,Dictionary_v2!$O$3:$P$15,2,0) -> 1 | W90: P&L | X90: Recurring | Y90: 2. Candidates Sourcing | Z90: 2. Candidates Sourcing | AA90: 1. Social media | AB90: =if(F90>0,"In","Out") -> Out | AC90: =VLOOKUP(C90,Dictionary_v2!L:M,2,0) -> Failed
A91: 46037.892 | B91: CARD_PAYMENT | C91: REVERTED | D91: Tiktok Ciudad De Mex | E91: TIKTOK | F91: -20 | G91: MXN | H91: 17.6428 | I91: -1.13 | J91: USDC | K91: 0 | L91: USDC | M91: 0 | N91: USDC | O91: XXXX | P91: 2535 | Q91: Ivan Amelong | R91: SERVICES | S91: XXXX | T91: =YEAR(A91) -> 2026 | U91: =MONTH(A91) -> 1 | V91: =VLOOKUP(U91,Dictionary_v2!$O$3:$P$15,2,0) -> 1 | W91: P&L | X91: Recurring | Y91: 2. Candidates Sourcing | Z91: 2. Candidates Sourcing | AA91: 1. Social media | AB91: =if(F91>0,"In","Out") -> Out | AC91: =VLOOKUP(C91,Dictionary_v2!L:M,2,0) -> Failed
A92: 46037.881 | B92: WITHDRAW | C92: FAILED | D92: Ricardo Lopez | E92: Honorarios contablesAgo25-Ene26 | F92: -9367.5 | G92: MXN | H92: 17.6624 | I92: -530.36 | J92: USDC | K92: 0 | L92: USDC | M92: 0 | N92: USDC | O92: XXXX | P92: XXXX | Q92: XXXX | R92: XXXX | S92: XXXX | T92: =YEAR(A92) -> 2026 | U92: =MONTH(A92) -> 1 | V92: =VLOOKUP(U92,Dictionary_v2!$O$3:$P$15,2,0) -> 1 | X92: Failed | Y92: Failed | Z92: Failed | AB92: =if(F92>0,"In","Out") -> Out | AC92: =VLOOKUP(C92,Dictionary_v2!L:M,2,0) -> Failed
A93: 46037.781 | B93: DEPOSIT | C93: COMPLETED | D93: UVI TECH SAPI DE CV | E93: VENDBILL1046050 | F93: 38658.16 | G93: MXN | H93: 17.6298 | I93: 2192.78 | J93: USDC | K93: 0 | L93: USDC | M93: 0 | N93: USDC | O93: 2192.78 | P93: XXXX | Q93: XXXX | R93: XXXX | S93: 46037.781 | T93: =YEAR(A93) -> 2026 | U93: =MONTH(A93) -> 1 | V93: =VLOOKUP(U93,Dictionary_v2!$O$3:$P$15,2,0) -> 1 | W93: P&L | X93: Recurring | Y93: 1. Collections | Z93: 1. Collections | AA93: 1. Full Stack | AB93: =if(F93>0,"In","Out") -> In | AC93: =VLOOKUP(C93,Dictionary_v2!L:M,2,0) -> Sent

Sheet Consolidated
B1: Year | C1: Month | D1: Quarter | E1: Statement | F1: Type | G1: Type 2 | H1: Type 2_B | I1: Type 3 | J1: Type 4 | K1: Description | L1: Amount | M1: Status | N1: Account
B2: =Mercury!Y3 -> 2026 | C2: =Mercury!AA3 -> 8 | D2: =Mercury!AB3 -> 3 | E2: =Mercury!AC3 -> P&L | F2: =Mercury!AD3 -> Recurring | G2: =Mercury!AE3 -> 2. Candidates Sourcing | H2: =Mercury!AF3 -> 2. Candidates Sourcing | I2: =Mercury!AG3 -> 1. Social Media | J2: =Mercury!AI3 -> In | K2: =Mercury!B3 -> Mercury IO Cashback | L2: =Mercury!C3 -> 131.38 | M2: =Mercury!D3 -> Sent | N2: Mercury
B3: =Mercury!Y4 -> 2026 | C3: =Mercury!AA4 -> 8 | D3: =Mercury!AB4 -> 3 | E3: =Mercury!AC4 -> Intercompany | F3: =Mercury!AD4 -> Recurring | G3: =Mercury!AE4 | H3: =Mercury!AF4 | I3: =Mercury!AG4 | J3: =Mercury!AI4 -> In | K3: =Mercury!B4 -> Welcome to Column N.A. (Mercury Checking xx5998) | L3: =Mercury!C4 -> 8777.25 | M3: =Mercury!D4 -> Sent | N3: Mercury
B4: =Mercury!Y5 -> 2026 | C4: =Mercury!AA5 -> 8 | D4: =Mercury!AB5 -> 3 | E4: =Mercury!AC5 -> Intercompany | F4: =Mercury!AD5 -> Recurring | G4: =Mercury!AE5 | H4: =Mercury!AF5 | I4: =Mercury!AG5 | J4: =Mercury!AI5 -> Out | K4: =Mercury!B5 -> Mercury Credit | L4: =Mercury!C5 -> -8777.25 | M4: =Mercury!D5 -> Sent | N4: Mercury
B5: =Mercury!Y6 -> 2026 | C5: =Mercury!AA6 -> 8 | D5: =Mercury!AB6 -> 3 | E5: =Mercury!AC6 -> P&L | F5: =Mercury!AD6 -> Recurring | G5: =Mercury!AE6 -> 3. Platform | H5: =Mercury!AF6 -> 3. Platform | I5: =Mercury!AG6 -> 1. Variable | J5: =Mercury!AI6 -> Out | K5: =Mercury!B6 -> Anthropic | L5: =Mercury!C6 -> -90.02 | M5: =Mercury!D6 -> Sent | N5: Mercury
B6: =Mercury!Y7 -> 2026 | C6: =Mercury!AA7 -> 8 | D6: =Mercury!AB7 -> 3 | E6: =Mercury!AC7 -> P&L | F6: =Mercury!AD7 -> Recurring | G6: =Mercury!AE7 -> 2. Candidates Sourcing | H6: =Mercury!AF7 -> 2. Candidates Sourcing | I6: =Mercury!AG7 -> 1. Social media | J6: =Mercury!AI7 -> Out | K6: =Mercury!B7 -> Facebook | L6: =Mercury!C7 -> -48.95 | M6: =Mercury!D7 -> Sent | N6: Mercury
B7: =Mercury!Y8 -> 2026 | C7: =Mercury!AA8 -> 8 | D7: =Mercury!AB8 -> 3 | E7: =Mercury!AC8 -> P&L | F7: =Mercury!AD8 -> Recurring | G7: =Mercury!AE8 -> 7. Founders | H7: =Mercury!AF8 -> 6. Other fixed and admin | I7: =Mercury!AG8 -> 1. Salaries | J7: =Mercury!AI8 -> Out | K7: =Mercury!B8 -> Ivan Amelong - Wise (Ivan Amelong) | L7: =Mercury!C8 -> -5500 | M7: =Mercury!D8 -> Sent | N7: Mercury
B8: =Mercury!Y9 -> 2026 | C8: =Mercury!AA9 -> 8 | D8: =Mercury!AB9 -> 3 | E8: =Mercury!AC9 -> P&L | F8: =Mercury!AD9 -> Recurring | G8: =Mercury!AE9 -> 7. Founders | H8: =Mercury!AF9 -> 6. Other fixed and admin | I8: =Mercury!AG9 -> 1. Salaries | J8: =Mercury!AI9 -> Out | K8: =Mercury!B9 -> Fede (BoA) (Federico David Naides) | L8: =Mercury!C9 -> -5500 | M8: =Mercury!D9 -> Sent | N8: Mercury
B9: =Mercury!Y10 -> 2026 | C9: =Mercury!AA10 -> 8 | D9: =Mercury!AB10 -> 3 | E9: =Mercury!AC10 -> P&L | F9: =Mercury!AD10 -> Recurring | G9: =Mercury!AE10 -> 3. Platform | H9: =Mercury!AF10 -> 3. Platform | I9: =Mercury!AG10 -> 2. Fixed | J9: =Mercury!AI10 -> Out | K9: =Mercury!B10 -> Intl. Wire Fee | L9: =Mercury!C10 -> -15 | M9: =Mercury!D10 -> Sent | N9: Mercury
B10: =Mercury!Y11 -> 2026 | C10: =Mercury!AA11 -> 8 | D10: =Mercury!AB11 -> 3 | E10: =Mercury!AC11 -> P&L | F10: =Mercury!AD11 -> Recurring | G10: =Mercury!AE11 -> 7. Founders | H10: =Mercury!AF11 -> 6. Other fixed and admin | I10: =Mercury!AG11 -> 1. Salaries | J10: =Mercury!AI11 -> Out | K10: =Mercury!B11 -> Efren (Ecuador) (Efren Rogelio Narvaez Peña) | L10: =Mercury!C11 -> -5000 | M10: =Mercury!D11 -> Sent | N10: Mercury
B11: =Mercury!Y12 -> 2026 | C11: =Mercury!AA12 -> 8 | D11: =Mercury!AB12 -> 3 | E11: =Mercury!AC12 -> Intercompany | F11: =Mercury!AD12 -> Recurring | G11: =Mercury!AE12 | H11: =Mercury!AF12 | I11: =Mercury!AG12 | J11: =Mercury!AI12 -> Out | K11: =Mercury!B12 -> Welcome to Column N.A. (Mercury Checking xx5998) | L11: =Mercury!C12 -> -11585.8 | M11: =Mercury!D12 -> Sent | N11: Mercury
B12: =Mercury!Y13 -> 2026 | C12: =Mercury!AA13 -> 8 | D12: =Mercury!AB13 -> 3 | E12: =Mercury!AC13 -> Intercompany | F12: =Mercury!AD13 -> Recurring | G12: =Mercury!AE13 | H12: =Mercury!AF13 | I12: =Mercury!AG13 | J12: =Mercury!AI13 -> In | K12: =Mercury!B13 -> Mercury Checking xx0301 | L12: =Mercury!C13 -> 11585.8 | M12: =Mercury!D13 -> Sent | N12: Mercury
B13: =Mercury!Y14 -> 2026 | C13: =Mercury!AA14 -> 8 | D13: =Mercury!AB14 -> 3 | E13: =Mercury!AC14 -> Intercompany | F13: =Mercury!AD14 -> Recurring | G13: =Mercury!AE14 | H13: =Mercury!AF14 | I13: =Mercury!AG14 | J13: =Mercury!AI14 -> Out | K13: =Mercury!B14 -> Welcome to Column N.A. (Mercury Checking xx5998) | L13: =Mercury!C14 -> -19000 | M13: =Mercury!D14 -> Sent | N13: Mercury
... B1369: =Mercury!Y1370 -> 2025 | C1369: =Mercury!AA1370 -> 1 | D1369: =Mercury!AB1370 -> 1 | E1369: =Mercury!AC1370 -> BS | F1369: =Mercury!AD1370 -> One-off | G1369: =Mercury!AE1370 -> 0. Investments | H1369: =Mercury!AF1370 -> 0. Investments | I1369: =Mercury!AG1370 -> 2. Founders | J1369: =Mercury!AI1370 -> In | K1369: =Mercury!B1370 -> Ivan Amelong - Wise (Ivan Amelong) | L1369: =Mercury!C1370 -> 1000 | M1369: =Mercury!D1370 -> Sent | N1369: Mercury
B1370: =DolarApp!T2 -> 2026 | C1370: =DolarApp!U2 -> 8 | D1370: =DolarApp!V2 -> 3 | E1370: =DolarApp!W2 -> P&L | F1370: =DolarApp!X2 -> Recurring | G1370: =DolarApp!Y2 -> 7. Founders | H1370: =DolarApp!Z2 -> 6. Other fixed and admin | I1370: =DolarApp!AA2 -> 1. Salaries | J1370: =DolarApp!AB2 -> Out | K1370: =DolarApp!D2 -> Ivan Amelong | L1370: =DolarApp!I2 -> -840.88 | M1370: =DolarApp!AC2 -> Sent | N1370: DolarApp
B1371: =DolarApp!T3 -> 2026 | C1371: =DolarApp!U3 -> 8 | D1371: =DolarApp!V3 -> 3 | E1371: =DolarApp!W3 -> P&L | F1371: =DolarApp!X3 -> Recurring | G1371: =DolarApp!Y3 -> 7. Founders | H1371: =DolarApp!Z3 -> 6. Other fixed and admin | I1371: =DolarApp!AA3 -> 1. Salaries | J1371: =DolarApp!AB3 -> Out | K1371: =DolarApp!D3 -> Federico David Naides | L1371: =DolarApp!I3 -> -840.88 | M1371: =DolarApp!AC3 -> Sent | N1371: DolarApp
B1372: =DolarApp!T4 -> 2026 | C1372: =DolarApp!U4 -> 8 | D1372: =DolarApp!V4 -> 3 | E1372: =DolarApp!W4 -> P&L | F1372: =DolarApp!X4 -> Recurring | G1372: =DolarApp!Y4 -> 3. Platform | H1372: =DolarApp!Z4 -> 3. Platform | I1372: =DolarApp!AA4 -> 1. Variable | J1372: =DolarApp!AB4 -> Out | K1372: =DolarApp!D4 -> Www.mirlo.mx Mexico | L1372: =DolarApp!I4 -> -2.41 | M1372: =DolarApp!AC4 -> Sent | N1372: DolarApp
B1373: =DolarApp!T5 -> 2026 | C1373: =DolarApp!U5 -> 8 | D1373: =DolarApp!V5 -> 3 | E1373: =DolarApp!W5 -> P&L | F1373: =DolarApp!X5 -> Recurring | G1373: =DolarApp!Y5 -> 8. Other fixed costs | H1373: =DolarApp!Z5 -> 6. Other fixed and admin | I1373: =DolarApp!AA5 -> 4. Taxes | J1373: =DolarApp!AB5 -> Out | K1373: =DolarApp!D5 -> Nadia Meline Karaguezian | L1373: =DolarApp!I5 -> -246.72 | M1373: =DolarApp!AC5 -> Sent | N1373: DolarApp
B1374: =DolarApp!T6 -> 2026 | C1374: =DolarApp!U6 -> 8 | D1374: =DolarApp!V6 -> 3 | E1374: =DolarApp!W6 -> P&L | F1374: =DolarApp!X6 -> Recurring | G1374: =DolarApp!Y6 -> 1. Collections | H1374: =DolarApp!Z6 -> 1. Collections | I1374: =DolarApp!AA6 -> 1. Full Stack | J1374: =DolarApp!AB6 -> In | K1374: =DolarApp!D6 -> KEKO MOBILITY SA DE CV | L1374: =DolarApp!I6 -> 1781.64 | M1374: =DolarApp!AC6 -> Sent | N1374: DolarApp
B1375: =DolarApp!T7 -> 2026 | C1375: =DolarApp!U7 -> 8 | D1375: =DolarApp!V7 -> 3 | E1375: =DolarApp!W7 -> P&L | F1375: =DolarApp!X7 -> Recurring | G1375: =DolarApp!Y7 -> 1. Collections | H1375: =DolarApp!Z7 -> 1. Collections | I1375: =DolarApp!AA7 -> 2. SaaS | J1375: =DolarApp!AB7 -> Out | K1375: =DolarApp!D7 -> Gloria L Guzman M | L1375: =DolarApp!I7 -> -102.64 | M1375: =DolarApp!AC7 -> Sent | N1375: DolarApp
B1376: =DolarApp!T8 -> 2026 | C1376: =DolarApp!U8 -> 8 | D1376: =DolarApp!V8 -> 3 | E1376: =DolarApp!W8 -> P&L | F1376: =DolarApp!X8 -> Recurring | G1376: =DolarApp!Y8 -> 3. Platform | H1376: =DolarApp!Z8 -> 3. Platform | I1376: =DolarApp!AA8 -> 1. Variable | J1376: =DolarApp!AB8 -> Out | K1376: =DolarApp!D8 -> Www.mirlo.mx Mexico | L1376: =DolarApp!I8 -> -4.37 | M1376: =DolarApp!AC8 -> Sent | N1376: DolarApp
B1377: =DolarApp!T9 -> 2026 | C1377: =DolarApp!U9 -> 8 | D1377: =DolarApp!V9 -> 3 | E1377: =DolarApp!W9 -> P&L | F1377: =DolarApp!X9 -> Recurring | G1377: =DolarApp!Y9 -> 3. Platform | H1377: =DolarApp!Z9 -> 3. Platform | I1377: =DolarApp!AA9 -> 1. Variable | J1377: =DolarApp!AB9 -> Out | K1377: =DolarApp!D9 -> Www.mirlo.mx Mexico | L1377: =DolarApp!I9 -> -4.59 | M1377: =DolarApp!AC9 -> Sent | N1377: DolarApp
B1378: =DolarApp!T10 -> 2026 | C1378: =DolarApp!U10 -> 8 | D1378: =DolarApp!V10 -> 3 | E1378: =DolarApp!W10 -> P&L | F1378: =DolarApp!X10 -> Recurring | G1378: =DolarApp!Y10 -> 1. Collections | H1378: =DolarApp!Z10 -> 1. Collections | I1378: =DolarApp!AA10 -> 2. SaaS | J1378: =DolarApp!AB10 -> Out | K1378: =DolarApp!D10 -> Gloria L Guzman M | L1378: =DolarApp!I10 -> -102.32 | M1378: =DolarApp!AC10 -> Sent | N1378: DolarApp
B1379: =DolarApp!T11 -> 2026 | C1379: =DolarApp!U11 -> 8 | D1379: =DolarApp!V11 -> 3 | E1379: =DolarApp!W11 -> P&L | F1379: =DolarApp!X11 -> Recurring | G1379: =DolarApp!Y11 -> 5. Marketing | H1379: =DolarApp!Z11 -> 5. Marketing | I1379: =DolarApp!AA11 -> 3. Events | J1379: =DolarApp!AB11 -> Out | K1379: =DolarApp!D11 -> AMESP Asociacion Mexicana de Empresas de Seguridad Privada | L1379: =DolarApp!I11 -> -1463.18 | M1379: =DolarApp!AC11 -> Sent | N1379: DolarApp
B1380: =DolarApp!T12 -> 2026 | C1380: =DolarApp!U12 -> 8 | D1380: =DolarApp!V12 -> 3 | E1380: =DolarApp!W12 -> BS | F1380: =DolarApp!X12 -> Recurring | G1380: =DolarApp!Y12 -> 0. Investments | H1380: =DolarApp!Z12 -> 0. Investments | I1380: =DolarApp!AA12 -> 4. Intercompany | J1380: =DolarApp!AB12 -> In | K1380: =DolarApp!D12 -> NEXIU AI LLC | L1380: =DolarApp!I12 -> 2000 | M1380: =DolarApp!AC12 -> Sent | N1380: DolarApp
B1381: =DolarApp!T13 -> 2026 | C1381: =DolarApp!U13 -> 8 | D1381: =DolarApp!V13 -> 3 | E1381: =DolarApp!W13 -> P&L | F1381: =DolarApp!X13 -> Recurring | G1381: =DolarApp!Y13 -> 5. Marketing | H1381: =DolarApp!Z13 -> 5. Marketing | I1381: =DolarApp!AA13 -> 3. Events | J1381: =DolarApp!AB13 -> Out | K1381: =DolarApp!D13 -> Viva Aerobus Apo | L1381: =DolarApp!I13 -> -336.78 | M1381: =DolarApp!AC13 -> Sent | N1381: DolarApp
... B1461: =DolarApp!T93 -> 2026 | C1461: =DolarApp!U93 -> 1 | D1461: =DolarApp!V93 -> 1 | E1461: =DolarApp!W93 -> P&L | F1461: =DolarApp!X93 -> Recurring | G1461: =DolarApp!Y93 -> 1. Collections | H1461: =DolarApp!Z93 -> 1. Collections | I1461: =DolarApp!AA93 -> 1. Full Stack | J1461: =DolarApp!AB93 -> In | K1461: =DolarApp!D93 -> UVI TECH SAPI DE CV | L1461: =DolarApp!I93 -> 2192.78 | M1461: =DolarApp!AC93 -> Sent | N1461: DolarApp

Sheet Cash Flow_Mercury

Sheet Cash Flow_all
A1: SUM of Amount | B1: Year | C1: Month
B2: 2025 | N2: 2026 | V2: Grand Total | AA2: SUM of Amount | AB2: Quarter
A3: Type 2 | B3: 1 | C3: 2 | D3: 3 | E3: 4 | F3: 5 | G3: 6 | H3: 7 | I3: 8 | J3: 9 | K3: 10 | L3: 11 | M3: 12 | N3: 1 | O3: 2 | P3: 3 | Q3: 4 | R3: 5 | S3: 6 | T3: 7 | U3: 8 | AA3: Type 2 | AB3: 1 | AC3: 2 | AD3: 3 | AE3: Grand Total
A4: 1. Collections | E4: 960 | F4: 11779.28 | G4: 1954 | H4: 5538 | I4: 8708.57 | J4: 7963.66 | K4: 6519 | L4: 6078 | M4: 28856 | N4: 2758.78 | O4: 11828.37 | P4: 21805.65 | Q4: 6594.66 | R4: 2235.15 | S4: 13926.89 | T4: 12032.35 | U4: 16933.63 | V4: 166471.99 | AA4: 1. Collections | AB4: 36392.8 | AC4: 22756.7 | AD4: 28965.98 | AE4: 88115.48
A5: 2. Candidates Sourcing | B5: -300.79 | C5: -224.95 | D5: -460.15 | E5: -1780.3 | F5: -1257.27 | G5: -980.36 | H5: -1831.71 | I5: -2405.36 | J5: -1467.75 | K5: -4717.73 | L5: -7587.9 | M5: -5499.47 | N5: -5861.35 | O5: -8900.96 | P5: -6934.2 | Q5: -5231.94 | R5: -9040.83 | S5: -6834.89 | T5: -7936.73 | U5: -7267.19 | V5: -86521.83 | AA5: 2. Candidates Sourcing | AB5: -21696.51 | AC5: -21107.66 | AD5: -15203.92 | AE5: -58008.09
A6: 3. Platform | B6: -80.16 | C6: -171.09 | D6: -453.83 | E6: -551.21 | F6: -578.65 | G6: -469.45 | H6: -710.17 | I6: -434.65 | J6: -507.68 | K6: -498.98 | L6: -1384.24 | M6: -444.89 | N6: -733.8 | O6: -602.32 | P6: -652.54 | Q6: -1721.29 | R6: -1984.14 | S6: -1608.95 | T6: -1815.72 | U6: -1892.27 | V6: -17296.03 | AA6: 3. Platform | AB6: -1988.66 | AC6: -5299.38 | AD6: -3722.99 | AE6: -11011.03
A7: 4. People | E7: -770 | F7: -780 | G7: -800 | H7: -1227 | I7: -1417.9 | J7: -817 | K7: -2449 | L7: -2333 | M7: -2179 | N7: -870 | O7: -1473.88 | P7: -1823.18 | Q7: -1869.3 | R7: -1872.11 | S7: -1857.48 | T7: -1864.6 | U7: -2065.96 | V7: -26469.41 | AA7: 4. People | AB7: -4167.06 | AC7: -5598.89 | AD7: -3930.56 | AE7: -13696.51
A8: 5. Marketing | G8: -467.37 | I8: -473.97 | J8: -474.76 | K8: -478.78 | L8: -479.92 | M8: -716.4 | N8: -1062.88 | O8: -2138.32 | P8: -900 | Q8: -1819 | R8: -2400 | S8: -2400 | T8: -2411.73 | U8: -4972.91 | V8: -21196.04 | AA8: 5. Marketing | AB8: -4101.2 | AC8: -6619 | AD8: -7384.64 | AE8: -18104.84
A9: 6. Tech salaries | F9: -500 | G9: -500 | H9: -800 | I9: -800 | J9: -800 | K9: -800 | L9: -800 | M9: -1900 | N9: -800 | O9: -3300 | P9: -3315 | Q9: -1100 | R9: -320 | T9: -200 | U9: -200 | V9: -16135 | AA9: 6. Tech salaries | AB9: -7415 | AC9: -1420 | AD9: -400 | AE9: -9235
A10: 7. Founders | M10: -13000 | N10: -15500 | O10: -17500 | P10: -17515 | Q10: -17572.61 | R10: -17500 | S10: -17671.41 | T10: -17595.75 | U10: -17681.76 | V10: -151536.53 | AA10: 7. Founders | AB10: -50515 | AC10: -39244.02 | AD10: -48777.51 | AE10: -138536.53
A11: 8. Other fixed costs | D11: -419.6 | F11: -2050 | G11: -15.17 | H11: -995 | J11: -375 | K11: -423.02 | L11: -698.36 | M11: -433.46 | N11: -975.64 | O11: -5755.88 | P11: -4253.24 | Q11: -4357.97 | R11: -1312.54 | S11: -850.36 | T11: -1101.47 | U11: -862.95 | V11: -24879.66 | AA11: 8. Other fixed costs | AB11: -10984.76 | AC11: -6520.87 | AD11: -1964.42 | AE11: -19470.05
A12: 9.Sales comissions | T12: -648.04 | V12: -648.04 | AA12: 9.Sales comissions | AD12: -648.04 | AE12: -648.04
A13: Grand Total | B13: -380.95 | C13: -396.04 | D13: -1333.58 | E13: -2141.51 | F13: 6613.36 | G13: -1278.35 | H13: -25.88 | I13: 3176.69 | J13: 3521.47 | K13: -2848.51 | L13: -7205.42 | M13: 4682.78 | N13: -23044.89 | O13: -27842.99 | P13: -13587.51 | Q13: -27077.45 | R13: -32194.47 | S13: -17296.2 | T13: -21541.69 | U13: -18009.41 | V13: -178210.55 | AA13: Grand Total | AB13: -64475.39 | AC13: -63053.12 | AD13: -53066.1 | AE13: -180594.61
A14: Cash balance | N14: ='EOM cash balance'!C16 -> 2450.8011 | O14: ='EOM cash balance'!C17 -> 240327.66 | P14: ='EOM cash balance'!C18 -> 230686.35 | Q14: ='EOM cash balance'!C19 -> 199884.15 | R14: ='EOM cash balance'!C20 -> 169701 | S14: ='EOM cash balance'!C21 -> 152102 | T14: ='EOM cash balance'!C22 -> 131360.04 | U14: ='EOM cash balance'!C23 -> 114005.14
A15: Check | P15: =P14-O14-P13 -> 3946.197 | Q15: =Q14-P14-Q13 -> -3724.7408 | R15: =R14-Q14-R13 -> 2011.3151 | S15: =S14-R14-S13 -> -302.8 | T15: =T14-S14-T13 -> 799.73 | U15: =U14-T14-U13 -> 654.51
A17: Month | N17: =N3 -> 1 | O17: =O3 -> 2 | P17: =P3 -> 3 | Q17: =Q3 -> 4 | R17: =R3 -> 5 | S17: =S3 -> 6 | T17: =T3 -> 7 | U17: =U3 -> 8 | ... X17: =X3 | AA17: Quarter
A18: Collections | N18: =N4 -> 2758.78 | O18: =O4 -> 11828.37 | P18: =P4 -> 21805.65 | Q18: =Q4 -> 6594.66 | R18: =R4 -> 2235.15 | S18: =S4 -> 13926.89 | T18: =T4 -> 12032.35 | U18: =U4 -> 16933.63 | AA18: Collections | AB18: =AB4 -> 36392.8 | AC18: =AC4 -> 22756.7 | AD18: =AD4 -> 28965.98 | AE18: =AE4 -> 88115.48
A19: Candidate + mark | N19: =N5+N8 -> -6924.23 | O19: =O5+O8 -> -11039.28 | P19: =P5+P8 -> -7834.2 | Q19: =Q5+Q8 -> -7050.94 | R19: =R5+R8 -> -11440.83 | S19: =S5+S8 -> -9234.89 | T19: =T5+T8 -> -10348.46 | U19: =U5+U8 -> -12240.1 | AA19: Candidate + mark | AB19: =AB5+AB8 -> -25797.71 | AC19: =AC5+AC8 -> -27726.66 | AD19: =AD5+AD8 -> -22588.56 | AE19: =AE5+AE8 -> -76112.93
A20: Full Stack Gross Margin | N20: =SUM(N18:N19) -> -4165.45 | O20: =SUM(O18:O19) -> 789.09 | P20: =SUM(P18:P19) -> 13971.45 | Q20: =SUM(Q18:Q19) -> -456.28 | R20: =SUM(R18:R19) -> -9205.68 | S20: =SUM(S18:S19) -> 4692 | T20: =SUM(T18:T19) -> 1683.89 | U20: =SUM(U18:U19) -> 4693.53 | AA20: Full Stack Gross Margin | AB20: =SUM(AB18:AB19) -> 10595.09 | AC20: =SUM(AC18:AC19) -> -4969.96 | AD20: =SUM(AD18:AD19) -> 6377.42 | AE20: =SUM(AE18:AE19) -> 12002.55
A21: Ops team | N21: =N7 -> -870 | O21: =O7 -> -1473.88 | P21: =P7 -> -1823.18 | Q21: =Q7 -> -1869.3 | R21: =R7 -> -1872.11 | S21: =S7 -> -1857.48 | T21: =T7 -> -1864.6 | U21: =U7 -> -2065.96 | AA21: Ops team | AB21: =AB7 -> -4167.06 | AC21: =AC7 -> -5598.89 | AD21: =AD7 -> -3930.56 | AE21: =AE7 -> -13696.51
A22: Full stack Variable margin | N22: =SUM(N20:N21) -> -5035.45 | O22: =SUM(O20:O21) -> -684.79 | P22: =SUM(P20:P21) -> 12148.27 | Q22: =SUM(Q20:Q21) -> -2325.58 | R22: =SUM(R20:R21) -> -11077.79 | S22: =SUM(S20:S21) -> 2834.52 | T22: =SUM(T20:T21) -> -180.71 | U22: =SUM(U20:U21) -> 2627.57 | AA22: Full stack Variable margin | AB22: =SUM(AB20:AB21) -> 6428.03 | AC22: =SUM(AC20:AC21) -> -10568.85 | AD22: =SUM(AD20:AD21) -> 2446.86 | AE22: =SUM(AE20:AE21) -> -1693.96
A23: Platform | N23: =N6 -> -733.8 | O23: =O6 -> -602.32 | P23: =P6 -> -652.54 | Q23: =Q6 -> -1721.29 | R23: =R6 -> -1984.14 | S23: =S6 -> -1608.95 | T23: =T6 -> -1815.72 | U23: =U6 -> -1892.27 | AA23: Platform | AB23: =AB6 -> -1988.66 | AC23: =AC6 -> -5299.38 | AD23: =AD6 -> -3722.99 | AE23: =AE6 -> -11011.03
A24: Full stack Operational | N24: =SUM(N22:N23) -> -5769.25 | O24: =SUM(O22:O23) -> -1287.11 | P24: =SUM(P22:P23) -> 11495.73 | Q24: =SUM(Q22:Q23) -> -4046.87 | R24: =SUM(R22:R23) -> -13061.93 | S24: =SUM(S22:S23) -> 1225.57 | T24: =SUM(T22:T23) -> -1996.43 | U24: =SUM(U22:U23) -> 735.3 | AA24: Full stack Operational | AB24: =SUM(AB22:AB23) -> 4439.37 | AC24: =SUM(AC22:AC23) -> -15868.23 | AD24: =SUM(AD22:AD23) -> -1276.13 | AE24: =SUM(AE22:AE23) -> -12704.99
A25: Tech & Founders | N25: =suM(N9:N10) -> -16300 | O25: =suM(O9:O10) -> -20800 | P25: =suM(P9:P10) -> -20830 | Q25: =suM(Q9:Q10) -> -18672.61 | R25: =suM(R9:R10) -> -17820 | S25: =suM(S9:S10) -> -17671.41 | T25: =suM(T9:T10) -> -17795.75 | U25: =suM(U9:U10) -> -17881.76 | AA25: Tech & Founders | AB25: =suM(AB9:AB10) -> -57930 | AC25: =suM(AC9:AC10) -> -40664.02 | AD25: =suM(AD9:AD10) -> -49177.51 | AE25: =suM(AE9:AE10) -> -147771.53
A26: Other fixed costs | N26: =N11 -> -975.64 | O26: =O11 -> -5755.88 | P26: =P11 -> -4253.24 | Q26: =Q11 -> -4357.97 | R26: =R11 -> -1312.54 | S26: =S11 -> -850.36 | T26: =T11 -> -1101.47 | U26: =U11 -> -862.95 | AA26: Other fixed costs | AB26: =AB11 -> -10984.76 | AC26: =AC11 -> -6520.87 | AD26: =AD11 -> -1964.42 | AE26: =AE11 -> -19470.05
A27: EBIT | N27: =suM(N24:N26) -> -23044.89 | O27: =suM(O24:O26) -> -27842.99 | P27: =suM(P24:P26) -> -13587.51 | Q27: =suM(Q24:Q26) -> -27077.45 | R27: =suM(R24:R26) -> -32194.47 | S27: =suM(S24:S26) -> -17296.2 | T27: =suM(T24:T26) -> -20893.65 | U27: =suM(U24:U26) -> -18009.41 | AA27: EBIT | AB27: =suM(AB24:AB26) -> -64475.39 | AC27: =suM(AC24:AC26) -> -63053.12 | AD27: =suM(AD24:AD26) -> -52418.06 | AE27: =suM(AE24:AE26) -> -179946.57
A32: Cummulative | N32: =N3 -> 1 | O32: =O3 -> 2 | P32: =P3 -> 3 | Q32: =Q3 -> 4 | R32: =R3 -> 5 | S32: =S3 -> 6 | T32: =T3 -> 7 | U32: =U3 -> 8
A33: Collections | N33: =N4 -> 2758.78 | O33: =N33+O4 -> 14587.15 | P33: =O33+P4 -> 36392.8 | Q33: =P33+Q4 -> 42987.46 | R33: =Q33+R4 -> 45222.61 | S33: =R33+S4 -> 59149.5 | T33: =S33+T4 -> 71181.85 | U33: =T33+U4 -> 88115.48
A34: Candidate + mark | N34: =N5+N8 -> -6924.23 | O34: =N34+O5+O8 -> -17963.51 | P34: =O34+P5+P8 -> -25797.71 | Q34: =P34+Q5+Q8 -> -32848.65 | R34: =Q34+R5+R8 -> -44289.48 | S34: =R34+S5+S8 -> -53524.37 | T34: =S34+T5+T8 -> -63872.83 | U34: =T34+U5+U8 -> -76112.93
A35: Full Stack Gross Margin | N35: =SUM(N33:N34) -> -4165.45 | O35: =SUM(O33:O34) -> -3376.36 | P35: =SUM(P33:P34) -> 10595.09 | Q35: =SUM(Q33:Q34) -> 10138.81 | R35: =SUM(R33:R34) -> 933.13 | S35: =SUM(S33:S34) -> 5625.13 | T35: =SUM(T33:T34) -> 7309.02 | U35: =SUM(U33:U34) -> 12002.55
A36: Ops team | N36: =N7 -> -870 | O36: =N36+O7 -> -2343.88 | P36: =O36+P7 -> -4167.06 | Q36: =P36+Q7 -> -6036.36 | R36: =Q36+R7 -> -7908.47 | S36: =R36+S7 -> -9765.95 | T36: =S36+T7 -> -11630.55 | U36: =T36+U7 -> -13696.51
A37: Full stack Variable margin | N37: =SUM(N35:N36) -> -5035.45 | O37: =SUM(O35:O36) -> -5720.24 | P37: =SUM(P35:P36) -> 6428.03 | Q37: =SUM(Q35:Q36) -> 4102.45 | R37: =SUM(R35:R36) -> -6975.34 | S37: =SUM(S35:S36) -> -4140.82 | T37: =SUM(T35:T36) -> -4321.53 | U37: =SUM(U35:U36) -> -1693.96
A38: Platform | N38: =N6 -> -733.8 | O38: =N38+O6 -> -1336.12 | P38: =O38+P6 -> -1988.66 | Q38: =P38+Q6 -> -3709.95 | R38: =Q38+R6 -> -5694.09 | S38: =R38+S6 -> -7303.04 | T38: =S38+T6 -> -9118.76 | U38: =T38+U6 -> -11011.03
A39: Full stack Operational | N39: =SUM(N37:N38) -> -5769.25 | O39: =SUM(O37:O38) -> -7056.36 | P39: =SUM(P37:P38) -> 4439.37 | Q39: =SUM(Q37:Q38) -> 392.5 | R39: =SUM(R37:R38) -> -12669.43 | S39: =SUM(S37:S38) -> -11443.86 | T39: =SUM(T37:T38) -> -13440.29 | U39: =SUM(U37:U38) -> -12704.99
A40: Tech & Founders | N40: =suM(N9:N10) -> -16300 | O40: =N40+suM(O9:O10) -> -37100 | P40: =O40+suM(P9:P10) -> -57930 | Q40: =P40+suM(Q9:Q10) -> -76602.61 | R40: =Q40+suM(R9:R10) -> -94422.61 | S40: =R40+suM(S9:S10) -> -112094.02 | T40: =S40+suM(T9:T10) -> -129889.77 | U40: =T40+suM(U9:U10) -> -147771.53
A41: Other fixed costs | N41: =N11 -> -975.64 | O41: =N41+O11 -> -6731.52 | P41: =O41+P11 -> -10984.76 | Q41: =P41+Q11 -> -15342.73 | R41: =Q41+R11 -> -16655.27 | S41: =R41+S11 -> -17505.63 | T41: =S41+T11 -> -18607.1 | U41: =T41+U11 -> -19470.05
A42: EBIT | N42: =suM(N39:N41) -> -23044.89 | O42: =suM(O39:O41) -> -50887.88 | P42: =suM(P39:P41) -> -64475.39 | Q42: =suM(Q39:Q41) -> -91552.84 | R42: =suM(R39:R41) -> -123747.31 | S42: =suM(S39:S41) -> -141043.51 | T42: =suM(T39:T41) -> -161937.16 | U42: =suM(U39:U41) -> -179946.57

Sheet temp meta
J6: =E6/SUM(D6:E6) -> 0
J7: =E7/SUM(D7:E7) -> 0.9847431
J8: =E8/SUM(D8:E8) -> 0.97686873
J9: =E9/SUM(D9:E9) -> 0.92873266
J10: =E10/SUM(D10:E10) -> 0.40651043
J11: =E11/SUM(D11:E11) -> 0.54952404
J12: =E12/SUM(D12:E12) -> 0.058037777
J13: =E13/SUM(D13:E13) -> 0.013682838
J14: =E14/SUM(D14:E14) -> 0.20404594
J15: =E15/SUM(D15:E15) -> 0.13868
J16: =E16/SUM(D16:E16) -> 0.17858393
J17: =E17/SUM(D17:E17) -> 0.049058851
... J25: =E25/SUM(D25:E25) -> 0.12087703

Sheet Unit economics

Sheet Reporte_500
C28: 379 | D28: 5082 | E28: 10749 | F28: 6701 | G28: =222069+8617.3457 -> 230686.35 | H28: =150736+1366 -> 152102
H29: =H28-G28 -> -78584.346
H30: =H29-H26 -> -78584.346

Sheet EOM cash balance
D1: https://docs.google.com/spreadsheets/d/1BdHcs12xRZpqeiusQixCJAkY-ZdlXvL0DbqYIueC4WE/edit?usp=sharing
B3: EOM | C3: Cash balance | D3: Cash balance Mercury | E3: Cash balance Dollar App | K3: Delta cash
B4: 45688 | C4: =suM(D4:E4) -> 619 | D4: 619 | E4: 0
B5: 45716 | C5: =suM(D5:E5) -> 223 | D5: 223 | E5: 0 | K5: =C5-C4 -> -396
B6: 45747 | C6: =suM(D6:E6) -> 379 | D6: 379 | E6: 0 | K6: =C6-C5 -> 156
B7: 45777 | C7: =suM(D7:E7) -> 151 | D7: 151 | E7: 0 | K7: =C7-C6 -> -228
B8: 45808 | C8: =suM(D8:E8) -> 6261 | D8: 6261 | E8: 0 | K8: =C8-C7 -> 6110
B9: 45838 | C9: =suM(D9:E9) -> 5082 | D9: 5082 | E9: 0 | K9: =C9-C8 -> -1179
B10: 45869 | C10: =suM(D10:E10) -> 4997 | D10: 4997 | E10: 0 | K10: =C10-C9 -> -85
B11: 45900 | C11: =suM(D11:E11) -> 8101 | D11: 8101 | E11: 0 | K11: =C11-C10 -> 3104 | M11: 3176.69
B12: 45930 | C12: =suM(D12:E12) -> 10749 | D12: 10749 | E12: 0 | K12: =C12-C11 -> 2648 | M12: 3521.47
B13: 45961 | C13: =suM(D13:E13) -> 8500 | D13: 8500 | E13: 0 | K13: =C13-C12 -> -2249 | M13: -2848.51
B14: 45991 | C14: =suM(D14:E14) -> 808 | D14: 808 | E14: 0 | K14: =C14-C13 -> -7692 | M14: -7205.42
B15: 46022 | C15: =suM(D15:E15) -> 6701 | D15: 6701 | E15: 0 | K15: =C15-C14 -> 5893 | M15: 4682.78
B16: 46053 | C16: =suM(D16:E16) -> 2450.8011 | D16: 791.03 | E16: 1659.7711 | K16: =C16-C15 -> -4250.1989 | M16: 4682.78
B17: 46081 | C17: =suM(D17:E17) -> 240327.66 | D17: 239583 | E17: 744.6587 | K17: =C17-C16 -> 237876.86 | L17: -285000
B18: 46112 | C18: =suM(D18:E18) -> 230686.35 | D18: 222069 | E18: 8617.3457 | K18: =C18-C17 -> -9641.313
B19: 46142 | C19: =suM(D19:E19) -> 199884.15 | D19: 199602 | E19: 282.1549 | K19: =C19-C18 -> -30802.191
B20: 46173 | C20: =suM(D20:E20) -> 169701 | D20: 168512 | E20: 1189
B21: 46203 | C21: =suM(D21:E21) -> 152102 | D21: =150736 -> 150736 | E21: 1366
B22: 46234 | C22: =suM(D22:E22) -> 131360.04 | D22: 130635 | E22: 725.04
B23: 46265 | C23: =suM(D23:E23) -> 114005.14 | D23: 113136 | E23: 869.14

Sheet Working capital WIP
D1: https://docs.google.com/spreadsheets/d/1BdHcs12xRZpqeiusQixCJAkY-ZdlXvL0DbqYIueC4WE/edit?usp=sharing
B3: EOM | C3: Cash balance | D3: Cash balance Mercury | E3: Cash balance Dollar App | F3: Acc. Receivable | G3: Payable | H3: Working capital | J3: Receivable sin Farmashop | K3: WK sin Farmashop
B4: 45688 | C4: =suM(D4:E4) -> 619 | D4: 619 | E4: 0 | G4: 0 | H4: =C4+F4-G4 -> 619 | K4: =C4+J4-G4 -> 619
B5: 45716 | C5: =suM(D5:E5) -> 223 | D5: 223 | E5: 0 | G5: 0 | H5: =C5+F5-G5 -> 223 | K5: =C5+J5-G5 -> 223
B6: 45747 | C6: =suM(D6:E6) -> 379 | D6: 379 | E6: 0 | G6: 0 | H6: =C6+F6-G6 -> 379 | K6: =C6+J6-G6 -> 379
B7: 45777 | C7: =suM(D7:E7) -> 151 | D7: 151 | E7: 0 | F7: 2507.28 | G7: 0 | H7: =C7+F7-G7 -> 2658.28 | J7: =F7 -> 2507.28 | K7: =C7+J7-G7 -> 2658.28
B8: 45808 | C8: =suM(D8:E8) -> 6261 | D8: 6261 | E8: 0 | F8: 2924 | G8: 0 | H8: =C8+F8-G8 -> 9185 | J8: =F8 -> 2924 | K8: =C8+J8-G8 -> 9185
B9: 45838 | C9: =suM(D9:E9) -> 5082 | D9: 5082 | E9: 0 | F9: 6000 | G9: 0 | H9: =C9+F9-G9 -> 11082 | J9: =F9 -> 6000 | K9: =C9+J9-G9 -> 11082
B10: 45869 | C10: =suM(D10:E10) -> 4997 | D10: 4997 | E10: 0 | F10: 3907.57 | G10: 0 | H10: =C10+F10-G10 -> 8904.57 | J10: =F10 -> 3907.57 | K10: =C10+J10-G10 -> 8904.57
B11: 45900 | C11: =suM(D11:E11) -> 8101 | D11: 8101 | E11: 0 | F11: 8059.44 | G11: 0 | H11: =C11+F11-G11 -> 16160.44 | J11: =F11 -> 8059.44 | K11: =C11+J11-G11 -> 16160.44
B12: 45930 | C12: =suM(D12:E12) -> 10749 | D12: 10749 | E12: 0 | F12: 5316 | G12: 0 | H12: =C12+F12-G12 -> 16065 | J12: =F12 -> 5316 | K12: =C12+J12-G12 -> 16065
B13: 45961 | C13: =suM(D13:E13) -> 8500 | D13: 8500 | E13: 0 | F13: 16355 | G13: 0 | H13: =C13+F13-G13 -> 24855 | J13: =F13-13200 -> 3155 | K13: =C13+J13-G13 -> 11655
B14: 45991 | C14: =suM(D14:E14) -> 808 | D14: 808 | E14: 0 | F14: =24858++4000 -> 28858 | G14: 0 | H14: =C14+F14-G14 -> 29666 | J14: =F14-13200 -> 15658 | K14: =C14+J14-G14 -> 16466
B15: 46022 | C15: =suM(D15:E15) -> 6701 | D15: 6701 | E15: 0 | F15: 10400 | G15: 0 | H15: =C15+F15-G15 -> 17101 | J15: =F15 -> 10400 | K15: =C15+J15-G15 -> 17101
B16: 46053 | C16: =suM(D16:E16) -> 791.03 | D16: 791.03 | F16: 13270 | G16: 0 | H16: =C16+F16-G16 -> 14061.03 | J16: =F16 -> 13270 | K16: =C16+J16-G16 -> 14061.03
B17: 46081 | C17: =suM(D17:E17) -> 239583 | D17: 239583 | F17: =12994+200+4000 -> 17194 | G17: 0 | H17: =C17+F17-G17 -> 256777 | J17: =F17 -> 17194 | K17: =C17+J17-G17 -> 256777
B18: 46112 | C18: =suM(D18:E18) -> 230686.35 | D18: 222069 | E18: 8617.3457 | H18: =C18+F18-G18 -> 230686.35 | J18: =F18 | K18: =C18+J18-G18 -> 230686.35
B19: 46142 | C19: =suM(D19:E19) -> 199884 | D19: 199602 | E19: 282 | H19: =C19+F19-G19 -> 199884 | J19: =F19 | K19: =C19+J19-G19 -> 199884

Sheet Check (in-out) vs. Mercury

Sheet Dictionary_v2
B2: LLC | G2: SA de CV
B3: Description | C3: Statement | D3: Type 2 | E3: Type 3 | G3: description | H3: Statement | I3: Type 2 | J3: Type 3 | L3: transaction_state | O3: Month | P3: Quarter | R3: Type 2 | S3: Type 2_B
B4: 1/CLICOH EXPRESS MX SA DE CV | C4: P&L | D4: 1. Collections | E4: 1. Full Stack | H4: P&L | I4: 8. Other fixed costs | J4: 3. Rent | L4: FAILED | M4: Failed | O4: 1 | P4: 1 | R4: 0. Investments | S4: 0. Investments
B5: 1/MEDANO SERVICES RESORTS SAPI D | C5: P&L | D5: 1. Collections | E5: 1. Full Stack | G5: 11300 MAR13 LATAM TALENT RECRU | H5: P&L | I5: 1. Collections | J5: 1. Full Stack | L5: REVERTED | M5: Failed | O5: 2 | P5: 1 | R5: 1. Collections | S5: 1. Collections
B6: 1/PM SOLTECH SA DE CV | C6: P&L | D6: 1. Collections | E6: 1. Full Stack | G6: ATRACCION CANDIDATOS BB466267 | H6: P&L | I6: 1. Collections | J6: 2. SaaS | L6: COMPLETED | M6: Sent | O6: 3 | P6: 1 | R6: 2. Candidates Sourcing | S6: 2. Candidates Sourcing
B7: 1/VITAE SALUD Y CALIDAD DE VIDA | C7: P&L | D7: 1. Collections | E7: 1. Full Stack | G7: Cashback payment | H7: P&L | I7: 1. Collections | J7: 1. Full Stack | O7: 4 | P7: 2 | R7: 3. Platform | S7: 3. Platform
B8: 500 LATAM SEED IV-C, L.L.C. | C8: BS | D8: 0. Investments | E8: 1. VC | G8: Honorarios contablesAgo25-Ene26 | H8: P&L | I8: 8. Other fixed costs | J8: 2. Admin | O8: 5 | P8: 2 | R8: 4. People | S8: 4. People
B9: Aerom√©xico | C9: P&L | D9: 8. Other fixed costs | E9: 1. Travel | G9: Indeed IEI26-00378096 | H9: P&L | I9: 2. Candidates Sourcing | J9: 2. Job Portals | O9: 6 | P9: 2 | R9: 5. Marketing | S9: 5. Marketing
B10: Ai Fireflies | C10: P&L | D10: 3. Platform | E10: 2. Fixed | G10: Indeed IEI26-00490088 | H10: P&L | I10: 2. Candidates Sourcing | J10: 2. Job Portals | O10: 7 | P10: 3 | R10: 6. Tech salaries | S10: 6. Other fixed and admin
B11: Aldana Casas (Aldana Casas) | C11: P&L | D11: 5. Marketing | E11: 1. People | G11: Indeed IEI26-00531466 | H11: P&L | I11: 2. Candidates Sourcing | J11: 2. Job Portals | O11: 8 | P11: 3 | R11: 7. Founders | S11: 6. Other fixed and admin
B12: Alex Tigselema (Alex Ignacio Tigselema Pacheco) | C12: P&L | D12: 6. Tech salaries | E12: 1. Salaries | G12: Indeed IEI26-00557574 | H12: P&L | I12: 2. Candidates Sourcing | J12: 2. Job Portals | O12: 9 | P12: 3 | R12: 8. Other fixed costs | S12: 6. Other fixed and admin
B13: Andrea Gomez (Andrea G√≥mez Romero) | C13: P&L | D13: 4. People | E13: 1. Operations | G13: Indeed IEI26-00603017 | H13: P&L | I13: 2. Candidates Sourcing | J13: 2. Job Portals | O13: 10 | P13: 4 | R13: Failed | S13: Failed
B14: Andrea Gomez (Andrea Gómez Romero) | C14: P&L | D14: 4. People | E14: 1. Operations | G14: Indeed IEI26-00787671 | H14: P&L | I14: 2. Candidates Sourcing | J14: 2. Job Portals | O14: 11 | P14: 4
B15: Anthropic | C15: P&L | D15: 3. Platform | E15: 1. Variable | G15: Marzo 26 | H15: P&L | I15: 8. Other fixed costs | J15: 3. Rent | O15: 12 | P15: 4
B16: Apollo.io | C16: P&L | D16: 2. Candidates Sourcing | E16: 4. Others | G16: MercuryACH Nexiu AI LLC MRCR-2EWPMCBOKA 260331 [LatAm Talent & Recruit] From Nexiu AI, LLC via mercury.com | H16: BS | I16: 0. Investments | J16: 4. Intercompany
B17: Apple | C17: P&L | D17: 6. Tech salaries | E17: 1. Salaries | G17: Servicios legales | H17: P&L | I17: 8. Other fixed costs | J17: 2. Admin
B18: CLICOH EXPRESS MX SA DE CV | C18: P&L | D18: 1. Collections | E18: 1. Full Stack | G18: SOFTWARE RECLUTAMIENTO 07AF516 | H18: P&L | I18: 1. Collections | J18: 2. SaaS
B19: COBOE SOCIEDAD ANONI MA | C19: P&L | D19: 1. Collections | E19: 2. SaaS | G19: TIKTOK | H19: P&L | I19: 2. Candidates Sourcing | J19: 1. Social media
B20: Compra Roilaw Project | C20: P&L | D20: 8. Other fixed costs | E20: 2. Admin | G20: VENDBILL1046050 | H20: P&L | I20: 1. Collections | J20: 1. Full Stack
B21: Computrabajo (Bb-Dgnet Lt) | C21: P&L | D21: 2. Candidates Sourcing | E21: 2. Job Portals | G21: Indeed Iei26-01300310 Dublin | H21: P&L | I21: 2. Candidates Sourcing | J21: 2. Job Portals
B22: Cookiebot | C22: P&L | D22: 3. Platform | E22: 2. Fixed | G22: Federico David Naides | H22: P&L | I22: 7. Founders | J22: 1. Salaries
B23: Delaware Corp & Tax | C23: P&L | D23: 8. Other fixed costs | E23: 2. Admin | G23: Ivan Amelong | H23: P&L | I23: 7. Founders | J23: 1. Salaries
B24: DolarApp | C24: P&L | D24: 1. Collections | E24: 1. Full Stack | G24: WeWork Mexico Co S. de R.L. de C.V | H24: P&L | I24: 8. Other fixed costs | J24: 3. Rent
B25: Dropbox | C25: P&L | D25: 3. Platform | E25: 2. Fixed | G25: Nexiu AI LLC | H25: BS | I25: 0. Investments | J25: 4. Intercompany
B26: Efren Narvaez (Citibank) (Efren Rogelio Narvaez Pe√±a) | C26: P&L | D26: 7. Founders | E26: 1. Salaries | G26: SERVICIOS TECNOLOGICOS AALKAB S.A. DE C. | H26: P&L | I26: 1. Collections | J26: 1. Full Stack
B27: Efren Narvaez (Citibank) (Efren Rogelio Narvaez Peña) | C27: P&L | D27: 7. Founders | E27: 1. Salaries | G27: WeWork Mexico Co S. de R.L. de C.V | H27: P&L | I27: 8. Other fixed costs | J27: 3. Rent
... B48: Lagrowthmachine | C48: P&L | D48: 2. Candidates Sourcing | E48: 4. Others | G48: KEKO MOBILITY SA DE CV | H48: P&L | I48: 1. Collections | J48: 1. Full Stack
B49: LatAm Talent (LatAm Talent & Recruitment Solutions) | C49: Intercompany | G49: Gloria L Guzman M | H49: P&L | I49: 1. Collections | J49: 2. SaaS
B50: LATIN AMERICA FUTURE AUTOMOBILE MEX | C50: P&L | D50: 1. Collections | E50: 1. Full Stack | G50: AMESP Asociacion Mexicana de Empresas de Seguridad Privada | H50: P&L | I50: 5. Marketing | J50: 3. Events
B51: LinkedIn | C51: P&L | D51: 2. Candidates Sourcing | E51: 3. Linkedin | G51: Viva Aerobus Apo | H51: P&L | I51: 5. Marketing | J51: 3. Events
B52: Lovable | C52: P&L | D52: 3. Platform | E52: 2. Fixed | G52: TECNO AVIV SA DE CV | H52: P&L | I52: 1. Collections | J52: 2. SaaS
B53: Lux Rewards Cashback | C53: P&L | D53: 3. Platform | E53: 2. Fixed | G53: Indeed Iei26-02411127 Dublin | H53: P&L | I53: 2. Candidates Sourcing | J53: 2. Job Portals
B54: Mercury | C54: P&L | D54: 2. Candidates Sourcing | E54: 4. Others | G54: Payu *google Cloud Miguel Hidalg | H54: P&L | I54: 2. Candidates Sourcing | J54: 1. Social media
B55: Merpago*buscojobsinte | C55: P&L | D55: 2. Candidates Sourcing | E55: 2. Job Portals
B56: Metapay | C56: P&L | D56: 3. Platform | E56: 2. Fixed
B57: MongoDB | C57: P&L | D57: 2. Candidates Sourcing | E57: 4. Others
B58: Monica Tonanzin Garc√≠a Vega (Monica Tonanzin Garc√≠a Vega) | C58: P&L | D58: 4. People | E58: 1. Operations
B59: Monica Tonanzin García Vega (Monica Tonanzin García Vega) | C59: P&L | D59: 4. People | E59: 1. Operations
B60: N8n Cloud1 | C60: P&L | D60: 3. Platform | E60: 2. Fixed
B61: OpenAI | C61: P&L | D61: 3. Platform | E61: 1. Variable
B62: Optimus Digital | C62: P&L | D62: 5. Marketing | E62: 2. Agency
B63: Paddle | C63: P&L | D63: 3. Platform | E63: 2. Fixed
B64: PAYMON LLC | C64: P&L | D64: 1. Collections | E64: 1. Full Stack
B65: Payu *Google Ads | C65: P&L | D65: 2. Candidates Sourcing | E65: 4. Others
B66: Payu *Occ | C66: P&L | D66: 2. Candidates Sourcing | E66: 2. Job Portals
... B78: TikTok | C78: P&L | D78: 2. Candidates Sourcing | E78: 1. Social Media
B79: Treasury | C79: Intercompany
B80: Twilio | C80: P&L | D80: 3. Platform | E80: 1. Variable
B81: United Airlines | C81: P&L | D81: 8. Other fixed costs | E81: 1. Travel
B82: Unstract | C82: P&L | D82: 3. Platform | E82: 2. Fixed
B83: Vapi | C83: P&L | D83: 3. Platform | E83: 1. Variable
B84: Vapi Api | C84: P&L | D84: 3. Platform | E84: 1. Variable
B85: Vercel | C85: P&L | D85: 3. Platform | E85: 2. Fixed
B86: Viva Aerobus Cib | C86: P&L | D86: 8. Other fixed costs | E86: 1. Travel
B87: Waalaxy | C87: P&L | D87: 2. Candidates Sourcing | E87: 4. Others
B88: Webflow | C88: P&L | D88: 3. Platform | E88: 2. Fixed
B89: WeWork | C89: P&L | D89: 8. Other fixed costs | E89: 3. Rent
B90: WeWork México (WeWork México Co S. de R.L de C.V) | C90: P&L | D90: 8. Other fixed costs | E90: 3. Rent
B91: Whaticket | C91: P&L | D91: 3. Platform | E91: 1. Variable
... B93: Bamboo Restaurant | C93: P&L | D93: 8. Other fixed costs | E93: 1. Travel
B94: Bridge Arx | C94: Intercompany
B95: Bullmetrix LLC (Bullmetrix LLC) | C95: P&L | D95: 5. Marketing | E95: 2. Agency
B96: Caltrain San Carlos | C96: P&L | D96: 8. Other fixed costs | E96: 1. Travel
B97: Corp E Corp | C97: P&L | D97: 8. Other fixed costs | E97: 2. Admin
B98: McTeague's Saloon | C98: P&L | D98: 8. Other fixed costs | E98: 1. Travel
B99: Mercury Checking xx8107 | C99: Intercompany
B100: Mercury IO Cashback | C100: P&L | D100: 2. Candidates Sourcing | E100: 1. Social Media
B101: Merpago*pax | C101: P&L | D101: 8. Other fixed costs | E101: 1. Travel
B102: Monroe Residence Club | C102: P&L | D102: 8. Other fixed costs | E102: 1. Travel
B103: Pydantic Logfire | C103: P&L | D103: 3. Platform | E103: 1. Variable
B104: Sears Fine Food | C104: P&L | D104: 8. Other fixed costs | E104: 1. Travel
B105: Ti Piceria Ristorante | C105: P&L | D105: 8. Other fixed costs | E105: 1. Travel
B106: Uber | C106: P&L | D106: 8. Other fixed costs | E106: 1. Travel
B107: Whole Foods Market | C107: P&L | D107: 8. Other fixed costs | E107: 1. Travel
B108: Efren (Ecuador) (Efren Rogelio Narvaez Peña) | C108: P&L | D108: 7. Founders | E108: 1. Salaries
B109: Mercury Credit | C109: Intercompany
B110: Payu *Google Ope D M | C110: P&L | D110: 2. Candidates Sourcing | E110: 1. Social Media
B111: OpenRouter | C111: P&L | D111: 3. Platform | E111: 1. Variable
B112: Welcome to Column N.A. (Mercury Checking xx5998) | C112: Intercompany
B113: Mercury Checking xx0301 | C113: Intercompany
B114: Grupalia (XYZ PAGOS) | C114: P&L | D114: 1. Collections | E114: 1. Full Stack
B115: OXXO | C115: P&L | D115: 5. Marketing | E115: 1. Variable
B116: Rest C Real Tijuana | C116: P&L | D116: 5. Marketing | E116: 3. Events
B117: Office Max Tijuana | C117: P&L | D117: 5. Marketing | E117: 3. Events
B118: Hot Real Inn Tijuana | C118: P&L | D118: 5. Marketing | E118: 3. Events
B119: Short.io | C119: P&L | D119: 3. Platform | E119: 1. Variable
B120: PolyAI | C120: P&L | D120: 3. Platform | E120: 1. Variable
B121: Nexiu Ai LLC | C121: Intercompany
B122: Sfo Manufactory Bar 66 | C122: P&L | D122: 8. Other fixed costs | E122: 1. Travel
